Workbook

Sheet Dashboard
B1: Export Packing - Cost per Vessel and Outsourcing Check
B2: FRP pressure vessels 1.4-3.0 m | 19 export packing jobs, Oct-25 to Jul-26 | rates as of Aug-26
B3: Case study by Kousani Das | Sep-2026 | all data simulated for illustration - no company, customer or supplier data included (see Notes)
B5: SELECT | F5: KEY FINDINGS
B6: Vessel size (mm) | D6: 2400 | F6: ="1. Actual vs design: 2.0 m jobs used "&TEXT('Proposed Std'!D33/'Proposed Std'!C33-1,"0%")&" more timber than the BOM. The other 6 sizes had no BOM - standards proposed from "&COUNTIF('Job Costing'!B5:B23,"<>2000")&" jobs." -> 1. Actual vs design: 2.0 m jobs used 6% more timber than the BOM. The other 6 sizes had no BOM - standards proposed from 16 jobs.
B7: Vessels per shipment | D7: 4 | F7: ="2. Flat-rack sizes (2.4 m and above) cost "&TEXT(H11/E11,"0.0")&"x a container size to pack - heavier saddles and weather cover." -> 2. Flat-rack sizes (2.4 m and above) cost 2.0x a container size to pack - heavier saddles and weather cover.
F8: ="3. In-house is the cheapest way to pack every size; the turnkey packer quotes about "&TEXT(AVERAGE('Size Model'!E43:I43),"0.0")&"x our own cost." -> 3. In-house is the cheapest way to pack every size; the turnkey packer quotes about 1.2x our own cost.
F9: 4. Next step: release the proposed BOMs. Buy ready-made skids only if the packing bay becomes a bottleneck.
B10: Vessels packed | E10: Avg cost per vessel - container sizes | H10: Avg cost per vessel - flat-rack sizes | K10: Rupee move since USD price set | N10: Cheapest for selected size
B11: =SUM('Job Costing'!C5:C23) -> 60 | E11: =SUMIFS('Job Costing'!X5:X23,'Job Costing'!E5:E23,"40HC")/SUMIFS('Job Costing'!C5:C23,'Job Costing'!E5:E23,"40HC") -> 13125.772 | H11: =SUMIFS('Job Costing'!X5:X23,'Job Costing'!E5:E23,"Flat rack")/SUMIFS('Job Costing'!C5:C23,'Job Costing'!E5:E23,"Flat rack") -> 26353.187 | K11: =Inputs!$C$88/Inputs!$C$87-1 -> 0.094010268 | N11: =HLOOKUP(D6,'Size Model'!C4:I41,38,0) -> In-house
B12: =COUNTA('Job Costing'!A5:A23)&" jobs" -> 19 jobs | E12: ="1.4-2.0 m" -> 1.4-2.0 m | H12: ="2.4-3.0 m" -> 2.4-3.0 m | K12: ="USD-INR "&TEXT(Inputs!$C$87,"0.00")&" to "&TEXT(Inputs!$C$88,"0.00") -> USD-INR 87.65 to 95.89 | N12: ="at "&D7&" vessels per shipment" -> at 4 vessels per shipment
B46: Terms
B47: • Flat rack: open container frame for vessels too wide for a closed container door
B48: • 40HC: 40-ft high-cube container. Skid / saddle: timber base the vessel lies on
B49: • PK-A / PK-B / PK-C: contractor labour only / buy ready-made skids / turnkey packer
B50: • Packing-bay day: one day of the packing area being used. Mistri / jogali: carpenter / helper

Sheet Notes
A1: Notes - what this workbook does
A3: Goal | B3: Management asked for two things: close the gap between actual and design BOMs, and decide which outsourced activities should be done in-house. Export packing had a written BOM for only one vessel size (2.0 m); every other size was packed as the supervisor decided. This workbook costs the past packing jobs, proposes a standard BOM for the 6 sizes without one, and compares in-house packing with three outsourcing options.
A4: Roles | B4: Engineering inputs (packing method, vessel dimensions, what a BOM should contain) came from the project engineer. Data collection, cleaning, the costing model, the analysis and the dashboard are my work.
A5: Data | B5: Fictional case study. All data - orders, SAP stores issues, labour log, BOM, vendor quotes - is simulated to mirror the structure of real SAP exports and shop records. No company, customer or supplier data is included. Material rates, wages and USD-INR are anchored to public market data (links at the bottom of Data - Rates).
A6: Steps | B6: 1) Pasted the SAP export and logs (Data tabs). 2) Added check columns: corrected job, size, rate item, timber cft, fixed dates and hours, rate conversions. 3) Costed each job (Job Costing). 4) Averaged use per vessel by size = proposed standard (Proposed Std). 5) Compared in-house with 3 outsourcing options (Size Model, Outsourcing). 6) Dashboard.
A7: Data issues fixed | B7: 2 SAP lines posted to the wrong job and 1 job with Ref2 blank (job taken from comments); 3 dates typed as text; 1 day of hours not noted (8 hrs taken); timber quoted once per CBM, tape per box of 12; 1 rate including GST; 1 typo (Rs 1,660/kg should be 166); 27 vendor item names mapped to 13 items.
A8: Assumptions | B8: Design pressure 7.5-10 bar (wall thickness at the upper end - a few mm, no effect on packing cost). Jobs before Feb-26 have no labour record: labour = average hours per vessel of logged jobs of the same size. OT paid at double rate. Supervision + marking Rs 1,025 per shipment. Crews: 24 man-hrs/day in-house, 40 for PK-C. Billed packaging price is an illustrative index. All assumptions are on the Inputs tab.
A9: Limitations | B9: Small sample - 19 jobs, 1 to 5 per size. Proposed standards are averages and need production sign-off. Flat-rack lashing not checked against sea-transport forces. Vendor quotes are estimates built from market rates.
A10: Terms | B10: Flat rack = open container frame for over-width cargo. 40HC = 40-ft high-cube container. Skid / saddle = timber base. Packing-bay day = one day of the packing area in use. Mistri / jogali = carpenter / helper. PK-A / PK-B / PK-C = contractor labour only / buy ready-made skids / turnkey packer.

Sheet Inputs
A1: Inputs
A2: Blue on green = typed by me. Black = linked. Change assumptions here only.
A4: 1. Current rates (latest valid line in Data - Rates)
A5: Item | B5: UoM | C5: Rate ₹ | D5: As of | E5: Rates row
A6: Timber | B6: cft | C6: ='Data - Rates'!M35 -> 780 | D6: ='Data - Rates'!A35 -> 46253 | E6: 35
A7: Nails | B7: set | C7: ='Data - Rates'!M26 -> 99 | D7: ='Data - Rates'!A26 -> 46183 | E7: 26
A8: Foam | B8: roll | C8: ='Data - Rates'!M31 -> 2250 | D8: ='Data - Rates'!A31 -> 46211 | E8: 31
A9: Ratchet belt | B9: nos | C9: ='Data - Rates'!M29 -> 950 | D9: ='Data - Rates'!A29 -> 46211 | E9: 29
A10: Gum tape | B10: roll | C10: ='Data - Rates'!M32 -> 84 | D10: ='Data - Rates'!A32 -> 46211 | E10: 32
A11: Stretch film | B11: kg | C11: ='Data - Rates'!M30 -> 167.79661 | D11: ='Data - Rates'!A30 -> 46211 | E11: 30
A12: Bubble wrap | B12: roll | C12: ='Data - Rates'!M34 -> 710 | D12: ='Data - Rates'!A34 -> 46238 | E12: 34
A13: Ply cover | B13: nos | C13: ='Data - Rates'!M14 -> 160 | D13: ='Data - Rates'!A14 -> 45915 | E13: 14
A14: Tarpaulin | B14: sqft | C14: ='Data - Rates'!M15 -> 5 | D14: ='Data - Rates'!A15 -> 45915 | E14: 15
A15: Fumigation | B15: per 40HC | C15: ='Data - Rates'!M33 -> 3500 | D15: ='Data - Rates'!A33 -> 46213 | E15: 33
A16: Carpenter | B16: day | C16: ='Data - Rates'!M24 -> 800 | D16: ='Data - Rates'!A24 -> 46113 | E16: 24
A17: Helper | B17: day | C17: ='Data - Rates'!M28 -> 480 | D17: ='Data - Rates'!A28 -> 46204 | E17: 28
A19: 2. Labour and other assumptions
A20: Contractor margin on labour | C20: 0.1 | D20: labour contractor bill
A21: Working hours per day | C21: 8 | D21: WB: 8.5 hr day incl. 0.5 hr rest
A22: Supervision + marking per shipment ₹ | C22: 1025 | D22: 0.5 day supervisor (~₹425) + stencil/labels/photos ₹600
A23: Our packing crew (man-hrs per day) | C23: 24 | D23: 1 mistri + 2 jogali x 8 hrs
A24: PK-C crew (man-hrs per day) | C24: 40 | D24: assumed 5-man crew
A25: PK-B skid sets per tempo trip | C25: 3 | D25: assumed
A26: Value of a free packing-bay day ₹ | C26: 0 | D26: 0 = ignore. Set >0 if the packing bay is a bottleneck
A28: 3. Wage history (from Data - Rates) - used by job date
A29: From date | B29: Carpenter ₹/day | C29: Helper ₹/day
A30: 45870 | B30: 760 | C30: 460
A31: 46113 | B31: 800 | C31: 460
A32: 46204 | B32: 800 | C32: 480
A34: 4. Fumigation rate history (per 40HC container)
A35: From date | B35: ₹ per container
A36: 45910 | B36: 3000
A37: 46050 | B37: 3200
A38: 46213 | B38: 3500
A39: 5. Outsourcing quotes per vessel (from quote e-mails, Aug-Sep 26)
A40: Size (mm) | B40: PK-A labour only | C40: PK-B skid set | D40: PK-C turnkey
A41: 1400 | B41: 800 | C41: 6400 | D41: NQ = not quoted (PK-C does not take jobs below 1.8 m)
A42: 1600 | B42: 900 | C42: 6850 | D42: NQ
A43: 1800 | B43: 1100 | C43: 7350 | D43: 15000
A44: 2000 | B44: 1000 | C44: 7200 | D44: 14000
A45: 2400 | B45: 2200 | C45: 15050 | D45: 31000
A46: 2600 | B46: 2300 | C46: 15900 | D46: 33000
A47: 3000 | B47: 2700 | C47: 17350 | D47: 37500
A48: PK-A mobilisation per visit ₹ | C48: 2500
A49: PK-B tempo per trip ₹ | C49: 1800
A50: PK-C mobilisation per visit ₹ | C50: 7500
A52: 6. Vessel dimensions (engineering inputs - typical proportions, approx.)
A53: Size (mm) | B53: Design pressure (bar) | C53: Wall thk range (mm) | D53: Wall used (mm) | E53: OD (mm) | F53: Dish to dish (mm) | G53: Overall length (mm) | H53: Packed width | I53: Packed height | J53: Fits 40HC door? | K53: Ship mode | L53: Vsl per 40HC
A54: 1400 | B54: 7.5 - 10 | C54: 11.5 - 14 | D54: 14 | E54: =A54+2*D54 -> 1428 | F54: 2560 | G54: 3210 | H54: =E54+60 -> 1488 | I54: =E54+280 -> 1708 | J54: =IF(AND(H54<=2340,I54<=2585),"Yes","No") -> Yes | K54: =IF(J54="Yes","40HC","Flat rack") -> 40HC | L54: =IF(K54="40HC",ROUNDDOWN(12032/(G54+100),0),"-") -> 3
A55: 1600 | B55: 7.5 - 10 | C55: 12.5 - 15.5 | D55: 15.5 | E55: =A55+2*D55 -> 1631 | F55: 2640 | G55: 3290 | H55: =E55+60 -> 1691 | I55: =E55+280 -> 1911 | J55: =IF(AND(H55<=2340,I55<=2585),"Yes","No") -> Yes | K55: =IF(J55="Yes","40HC","Flat rack") -> 40HC | L55: =IF(K55="40HC",ROUNDDOWN(12032/(G55+100),0),"-") -> 3
A56: 1800 | B56: 7.5 - 10 | C56: 13.5 - 17 | D56: 17 | E56: =A56+2*D56 -> 1834 | F56: 2920 | G56: 3570 | H56: =E56+60 -> 1894 | I56: =E56+280 -> 2114 | J56: =IF(AND(H56<=2340,I56<=2585),"Yes","No") -> Yes | K56: =IF(J56="Yes","40HC","Flat rack") -> 40HC | L56: =IF(K56="40HC",ROUNDDOWN(12032/(G56+100),0),"-") -> 3
A57: 2000 | B57: 7.5 - 10 | C57: 14.5 - 18.5 | D57: 18.5 | E57: =A57+2*D57 -> 2037 | F57: 2400 | G57: 3050 | H57: =E57+60 -> 2097 | I57: =E57+280 -> 2317 | J57: =IF(AND(H57<=2340,I57<=2585),"Yes","No") -> Yes | K57: =IF(J57="Yes","40HC","Flat rack") -> 40HC | L57: =IF(K57="40HC",ROUNDDOWN(12032/(G57+100),0),"-") -> 3
A58: 2400 | B58: 7.5 - 10 | C58: 17 - 21 | D58: 21 | E58: =A58+2*D58 -> 2442 | F58: 3760 | G58: 4410 | H58: =E58+60 -> 2502 | I58: =E58+280 -> 2722 | J58: =IF(AND(H58<=2340,I58<=2585),"Yes","No") -> No | K58: =IF(J58="Yes","40HC","Flat rack") -> Flat rack | L58: =IF(K58="40HC",ROUNDDOWN(12032/(G58+100),0),"-") -> -
A59: 2600 | B59: 7.5 - 10 | C59: 18 - 22.5 | D59: 22.5 | E59: =A59+2*D59 -> 2645 | F59: 4040 | G59: 4690 | H59: =E59+60 -> 2705 | I59: =E59+280 -> 2925 | J59: =IF(AND(H59<=2340,I59<=2585),"Yes","No") -> No | K59: =IF(J59="Yes","40HC","Flat rack") -> Flat rack | L59: =IF(K59="40HC",ROUNDDOWN(12032/(G59+100),0),"-") -> -
A60: 3000 | B60: 7.5 - 10 | C60: 20 - 25.5 | D60: 25.5 | E60: =A60+2*D60 -> 3051 | F60: 4500 | G60: 5150 | H60: =E60+60 -> 3111 | I60: =E60+280 -> 3331 | J60: =IF(AND(H60<=2340,I60<=2585),"Yes","No") -> No | K60: =IF(J60="Yes","40HC","Flat rack") -> Flat rack | L60: =IF(K60="40HC",ROUNDDOWN(12032/(G60+100),0),"-") -> -
A61: Design pressure taken as a 7.5-10 bar range; wall thickness at the upper end is used (a few mm - no effect on packing cost).
A62: 40HC door approx 2340 W x 2585 H; packed width = OD + 60 (wrap), height = OD + 280 (saddle + wrap); container length 12,032 mm.
A64: 7. USD-INR and billed packaging charge
A65: Date | B65: USD-INR | C65: Source
A66: 45882 | B66: 87.65 | C66: bookmyforex.com
A67: 45912 | B67: 88.26 | C67: PTI via taxtmi.com
A68: 45946 | B68: 87.82 | C68: motilaloswal.com
A69: 45960 | B69: 88.7 | C69: newsonair.gov.in
A70: 45975 | B70: 88.66 | C70: PTI via taxtmi.com
A71: 45992 | B71: 89.53 | C71: business-standard.com
A72: 46022 | B72: 89.88 | C72: PTI via taxtmi.com
A73: 46077 | B73: 90.96 | C73: newsarenaindia.com
A74: 46099 | B74: 92.63 | C74: newsarenaindia.com
A75: 46125 | B75: 93.54 | C75: muthootsecurities.com
A76: 46132 | B76: 93.16 | C76: cholasecurities.com
A77: 46142 | B77: 95.11 | C77: muthootsecurities.com
... A85: 46284 | B85: 95.89 | C85: dailypioneer.com
A87: USD-INR when USD packaging price was set | C87: =B66 -> 87.65
A88: USD-INR now (latest above) | C88: =B85 -> 95.89
A90: Size (mm) | B90: Billed packaging index (2.4 m = 100)
A91: 2400 | B91: 100
A92: 2600 | B92: 106
A93: Index base - USD per 100 (illustrative) | C93: 600 | D93: illustrative value

Sheet Job Costing
A1: Job costing - packing cost per job (actuals)
A2: Blue = typed from SAP sales orders / GR docs. Jobs before Feb-26 have no labour record - average hrs per vessel of the same size used.
A4: Job no. | B4: Size (mm) | C4: Vessels | D4: Packed on | E4: Ship mode | F4: Timber ₹ | G4: Consumables ₹ | H4: Returns ₹ | I4: Material ₹ | J4: Mistri hrs (log) | K4: Jogali hrs (log) | L4: Labour record? | M4: Mistri hrs / vsl | N4: Jogali hrs / vsl | O4: Mistri hrs used | P4: Jogali hrs used | Q4: Carpenter ₹/day | R4: Helper ₹/day | S4: Labour ₹ | T4: OT hrs | U4: OT extra ₹ | V4: Fumigation ₹ | W4: Supervision ₹ | X4: Total ₹ | Y4: ₹ per vessel | Z4: USD-INR | AA4: USD per vessel | AB4: Timber cft issued | AC4: Notes
A5: J/25-26/135 | B5: 2600 | C5: 3 | D5: 45939 | E5: =VLOOKUP(B5,Inputs!$A$54:$L$60,11,0) -> Flat rack | F5: =SUMIFS('Data - SAP Issues'!$I$4:$I$254,'Data - SAP Issues'!$K$4:$K$254,A5,'Data - SAP Issues'!$M$4:$M$254,"Timber") -> 31538.33 | G5: =SUMIFS('Data - SAP Issues'!$I$4:$I$254,'Data - SAP Issues'!$K$4:$K$254,A5)-F5 -> 33544.2 | H5: 0 | I5: =F5+G5-H5 -> 65082.53 | J5: =SUMIFS('Data - Labour'!$M$5:$M$92,'Data - Labour'!$G$5:$G$92,A5,'Data - Labour'!$B$5:$B$92,"Mistri") -> 0 | K5: =SUMIFS('Data - Labour'!$M$5:$M$92,'Data - Labour'!$G$5:$G$92,A5,'Data - Labour'!$B$5:$B$92,"Jogali") -> 0 | L5: =IF(J5+K5>0,"Yes","No") -> No | M5: =IF(L5="Yes",J5/C5,"") | N5: =IF(L5="Yes",K5/C5,"") | O5: =IF(L5="Yes",J5,AVERAGEIFS($M$5:$M$23,$B$5:$B$23,B5)*C5) -> 26.625 | P5: =IF(L5="Yes",K5,AVERAGEIFS($N$5:$N$23,$B$5:$B$23,B5)*C5) -> 61.5625 | Q5: =VLOOKUP(D5,Inputs!$A$30:$C$32,2,TRUE()) -> 760 | R5: =VLOOKUP(D5,Inputs!$A$30:$C$32,3,TRUE()) -> 460 | S5: =(O5*Q5+P5*R5)/Inputs!$C$21*(1+Inputs!$C$20) -> 6676.1406 | T5: =SUMIFS('Data - Labour'!$N$5:$N$92,'Data - Labour'!$G$5:$G$92,A5) -> 0 | U5: =T5*(Q5+R5)/2/Inputs!$C$21*(1+Inputs!$C$20) -> 0 | V5: =IF(E5="40HC",ROUNDUP(C5/VLOOKUP(B5,Inputs!$A$54:$L$60,12,0),0)*VLOOKUP(D5,Inputs!$A$36:$B$38,2,TRUE()),0) -> 0 | W5: =Inputs!$C$22 -> 1025 | X5: =I5+S5+U5+V5+W5 -> 72783.671 | Y5: =X5/C5 -> 24261.224 | Z5: =VLOOKUP(D5,Inputs!$A$66:$B$85,2,TRUE()) -> 88.26 | AA5: =Y5/Z5 -> 274.88357 | AB5: =SUMIFS('Data - SAP Issues'!$N$4:$N$254,'Data - SAP Issues'!$K$4:$K$254,A5) -> 45.048939 | AC5: no labour record (before Feb-26)
A6: J/25-26/118 | B6: 2400 | C6: 2 | D6: 45951 | E6: =VLOOKUP(B6,Inputs!$A$54:$L$60,11,0) -> Flat rack | F6: =SUMIFS('Data - SAP Issues'!$I$4:$I$254,'Data - SAP Issues'!$K$4:$K$254,A6,'Data - SAP Issues'!$M$4:$M$254,"Timber") -> 20415.81 | G6: =SUMIFS('Data - SAP Issues'!$I$4:$I$254,'Data - SAP Issues'!$K$4:$K$254,A6)-F6 -> 22543.6 | H6: 0 | I6: =F6+G6-H6 -> 42959.41 | J6: =SUMIFS('Data - Labour'!$M$5:$M$92,'Data - Labour'!$G$5:$G$92,A6,'Data - Labour'!$B$5:$B$92,"Mistri") -> 0 | K6: =SUMIFS('Data - Labour'!$M$5:$M$92,'Data - Labour'!$G$5:$G$92,A6,'Data - Labour'!$B$5:$B$92,"Jogali") -> 0 | L6: =IF(J6+K6>0,"Yes","No") -> No | M6: =IF(L6="Yes",J6/C6,"") | N6: =IF(L6="Yes",K6/C6,"") | O6: =IF(L6="Yes",J6,AVERAGEIFS($M$5:$M$23,$B$5:$B$23,B6)*C6) -> 19.633333 | P6: =IF(L6="Yes",K6,AVERAGEIFS($N$5:$N$23,$B$5:$B$23,B6)*C6) -> 37.9 | Q6: =VLOOKUP(D6,Inputs!$A$30:$C$32,2,TRUE()) -> 760 | R6: =VLOOKUP(D6,Inputs!$A$30:$C$32,3,TRUE()) -> 460 | S6: =(O6*Q6+P6*R6)/Inputs!$C$21*(1+Inputs!$C$20) -> 4448.8583 | T6: =SUMIFS('Data - Labour'!$N$5:$N$92,'Data - Labour'!$G$5:$G$92,A6) -> 0 | U6: =T6*(Q6+R6)/2/Inputs!$C$21*(1+Inputs!$C$20) -> 0 | V6: =IF(E6="40HC",ROUNDUP(C6/VLOOKUP(B6,Inputs!$A$54:$L$60,12,0),0)*VLOOKUP(D6,Inputs!$A$36:$B$38,2,TRUE()),0) -> 0 | W6: =Inputs!$C$22 -> 1025 | X6: =I6+S6+U6+V6+W6 -> 48433.268 | Y6: =X6/C6 -> 24216.634 | Z6: =VLOOKUP(D6,Inputs!$A$66:$B$85,2,TRUE()) -> 87.82 | AA6: =Y6/Z6 -> 275.75306 | AB6: =SUMIFS('Data - SAP Issues'!$N$4:$N$254,'Data - SAP Issues'!$K$4:$K$254,A6) -> 29.161646 | AC6: no labour record (before Feb-26)
A7: J/25-26/120 | B7: 1800 | C7: 4 | D7: 45967 | E7: =VLOOKUP(B7,Inputs!$A$54:$L$60,11,0) -> 40HC | F7: =SUMIFS('Data - SAP Issues'!$I$4:$I$254,'Data - SAP Issues'!$K$4:$K$254,A7,'Data - SAP Issues'!$M$4:$M$254,"Timber") -> 21654.84 | G7: =SUMIFS('Data - SAP Issues'!$I$4:$I$254,'Data - SAP Issues'!$K$4:$K$254,A7)-F7 -> 20153 | H7: 0 | I7: =F7+G7-H7 -> 41807.84 | J7: =SUMIFS('Data - Labour'!$M$5:$M$92,'Data - Labour'!$G$5:$G$92,A7,'Data - Labour'!$B$5:$B$92,"Mistri") -> 0 | K7: =SUMIFS('Data - Labour'!$M$5:$M$92,'Data - Labour'!$G$5:$G$92,A7,'Data - Labour'!$B$5:$B$92,"Jogali") -> 0 | L7: =IF(J7+K7>0,"Yes","No") -> No | M7: =IF(L7="Yes",J7/C7,"") | N7: =IF(L7="Yes",K7/C7,"") | O7: =IF(L7="Yes",J7,AVERAGEIFS($M$5:$M$23,$B$5:$B$23,B7)*C7) -> 19 | P7: =IF(L7="Yes",K7,AVERAGEIFS($N$5:$N$23,$B$5:$B$23,B7)*C7) -> 40.5 | Q7: =VLOOKUP(D7,Inputs!$A$30:$C$32,2,TRUE()) -> 760 | R7: =VLOOKUP(D7,Inputs!$A$30:$C$32,3,TRUE()) -> 460 | S7: =(O7*Q7+P7*R7)/Inputs!$C$21*(1+Inputs!$C$20) -> 4547.125 | T7: =SUMIFS('Data - Labour'!$N$5:$N$92,'Data - Labour'!$G$5:$G$92,A7) -> 0 | U7: =T7*(Q7+R7)/2/Inputs!$C$21*(1+Inputs!$C$20) -> 0 | V7: =IF(E7="40HC",ROUNDUP(C7/VLOOKUP(B7,Inputs!$A$54:$L$60,12,0),0)*VLOOKUP(D7,Inputs!$A$36:$B$38,2,TRUE()),0) -> 6000 | W7: =Inputs!$C$22 -> 1025 | X7: =I7+S7+U7+V7+W7 -> 53379.965 | Y7: =X7/C7 -> 13344.991 | Z7: =VLOOKUP(D7,Inputs!$A$66:$B$85,2,TRUE()) -> 88.7 | AA7: =Y7/Z7 -> 150.45086 | AB7: =SUMIFS('Data - SAP Issues'!$N$4:$N$254,'Data - SAP Issues'!$K$4:$K$254,A7) -> 30.93156 | AC7: no labour record (before Feb-26)
A8: J/25-26/122 | B8: 2600 | C8: 2 | D8: 45979 | E8: =VLOOKUP(B8,Inputs!$A$54:$L$60,11,0) -> Flat rack | F8: =SUMIFS('Data - SAP Issues'!$I$4:$I$254,'Data - SAP Issues'!$K$4:$K$254,A8,'Data - SAP Issues'!$M$4:$M$254,"Timber") -> 25860.44 | G8: =SUMIFS('Data - SAP Issues'!$I$4:$I$254,'Data - SAP Issues'!$K$4:$K$254,A8)-F8 -> 24937.8 | H8: 0 | I8: =F8+G8-H8 -> 50798.24 | J8: =SUMIFS('Data - Labour'!$M$5:$M$92,'Data - Labour'!$G$5:$G$92,A8,'Data - Labour'!$B$5:$B$92,"Mistri") -> 0 | K8: =SUMIFS('Data - Labour'!$M$5:$M$92,'Data - Labour'!$G$5:$G$92,A8,'Data - Labour'!$B$5:$B$92,"Jogali") -> 0 | L8: =IF(J8+K8>0,"Yes","No") -> No | M8: =IF(L8="Yes",J8/C8,"") | N8: =IF(L8="Yes",K8/C8,"") | O8: =IF(L8="Yes",J8,AVERAGEIFS($M$5:$M$23,$B$5:$B$23,B8)*C8) -> 17.75 | P8: =IF(L8="Yes",K8,AVERAGEIFS($N$5:$N$23,$B$5:$B$23,B8)*C8) -> 41.041667 | Q8: =VLOOKUP(D8,Inputs!$A$30:$C$32,2,TRUE()) -> 760 | R8: =VLOOKUP(D8,Inputs!$A$30:$C$32,3,TRUE()) -> 460 | S8: =(O8*Q8+P8*R8)/Inputs!$C$21*(1+Inputs!$C$20) -> 4450.7604 | T8: =SUMIFS('Data - Labour'!$N$5:$N$92,'Data - Labour'!$G$5:$G$92,A8) -> 0 | U8: =T8*(Q8+R8)/2/Inputs!$C$21*(1+Inputs!$C$20) -> 0 | V8: =IF(E8="40HC",ROUNDUP(C8/VLOOKUP(B8,Inputs!$A$54:$L$60,12,0),0)*VLOOKUP(D8,Inputs!$A$36:$B$38,2,TRUE()),0) -> 0 | W8: =Inputs!$C$22 -> 1025 | X8: =I8+S8+U8+V8+W8 -> 56274 | Y8: =X8/C8 -> 28137 | Z8: =VLOOKUP(D8,Inputs!$A$66:$B$85,2,TRUE()) -> 88.66 | AA8: =Y8/Z8 -> 317.35845 | AB8: =SUMIFS('Data - SAP Issues'!$N$4:$N$254,'Data - SAP Issues'!$K$4:$K$254,A8) -> 36.938674 | AC8: no labour record (before Feb-26); 3 battens split - addl issue
A9: J/25-26/124 | B9: 2400 | C9: 4 | D9: 45988 | E9: =VLOOKUP(B9,Inputs!$A$54:$L$60,11,0) -> Flat rack | F9: =SUMIFS('Data - SAP Issues'!$I$4:$I$254,'Data - SAP Issues'!$K$4:$K$254,A9,'Data - SAP Issues'!$M$4:$M$254,"Timber") -> 42075.3 | G9: =SUMIFS('Data - SAP Issues'!$I$4:$I$254,'Data - SAP Issues'!$K$4:$K$254,A9)-F9 -> 42876.8 | H9: 0 | I9: =F9+G9-H9 -> 84952.1 | J9: =SUMIFS('Data - Labour'!$M$5:$M$92,'Data - Labour'!$G$5:$G$92,A9,'Data - Labour'!$B$5:$B$92,"Mistri") -> 0 | K9: =SUMIFS('Data - Labour'!$M$5:$M$92,'Data - Labour'!$G$5:$G$92,A9,'Data - Labour'!$B$5:$B$92,"Jogali") -> 0 | L9: =IF(J9+K9>0,"Yes","No") -> No | M9: =IF(L9="Yes",J9/C9,"") | N9: =IF(L9="Yes",K9/C9,"") | O9: =IF(L9="Yes",J9,AVERAGEIFS($M$5:$M$23,$B$5:$B$23,B9)*C9) -> 39.266667 | P9: =IF(L9="Yes",K9,AVERAGEIFS($N$5:$N$23,$B$5:$B$23,B9)*C9) -> 75.8 | Q9: =VLOOKUP(D9,Inputs!$A$30:$C$32,2,TRUE()) -> 760 | R9: =VLOOKUP(D9,Inputs!$A$30:$C$32,3,TRUE()) -> 460 | S9: =(O9*Q9+P9*R9)/Inputs!$C$21*(1+Inputs!$C$20) -> 8897.7167 | T9: =SUMIFS('Data - Labour'!$N$5:$N$92,'Data - Labour'!$G$5:$G$92,A9) -> 0 | U9: =T9*(Q9+R9)/2/Inputs!$C$21*(1+Inputs!$C$20) -> 0 | V9: =IF(E9="40HC",ROUNDUP(C9/VLOOKUP(B9,Inputs!$A$54:$L$60,12,0),0)*VLOOKUP(D9,Inputs!$A$36:$B$38,2,TRUE()),0) -> 0 | W9: =Inputs!$C$22 -> 1025 | X9: =I9+S9+U9+V9+W9 -> 94874.817 | Y9: =X9/C9 -> 23718.704 | Z9: =VLOOKUP(D9,Inputs!$A$66:$B$85,2,TRUE()) -> 88.66 | AA9: =Y9/Z9 -> 267.5243 | AB9: =SUMIFS('Data - SAP Issues'!$N$4:$N$254,'Data - SAP Issues'!$K$4:$K$254,A9) -> 60.099827 | AC9: no labour record (before Feb-26)
A10: J/25-26/130 | B10: 1400 | C10: 2 | D10: 46001 | E10: =VLOOKUP(B10,Inputs!$A$54:$L$60,11,0) -> 40HC | F10: =SUMIFS('Data - SAP Issues'!$I$4:$I$254,'Data - SAP Issues'!$K$4:$K$254,A10,'Data - SAP Issues'!$M$4:$M$254,"Timber") -> 12445.02 | G10: =SUMIFS('Data - SAP Issues'!$I$4:$I$254,'Data - SAP Issues'!$K$4:$K$254,A10)-F10 -> 9453.2 | H10: 0 | I10: =F10+G10-H10 -> 21898.22 | J10: =SUMIFS('Data - Labour'!$M$5:$M$92,'Data - Labour'!$G$5:$G$92,A10,'Data - Labour'!$B$5:$B$92,"Mistri") -> 0 | K10: =SUMIFS('Data - Labour'!$M$5:$M$92,'Data - Labour'!$G$5:$G$92,A10,'Data - Labour'!$B$5:$B$92,"Jogali") -> 0 | L10: =IF(J10+K10>0,"Yes","No") -> No | M10: =IF(L10="Yes",J10/C10,"") | N10: =IF(L10="Yes",K10/C10,"") | O10: =IF(L10="Yes",J10,AVERAGEIFS($M$5:$M$23,$B$5:$B$23,B10)*C10) -> 7 | P10: =IF(L10="Yes",K10,AVERAGEIFS($N$5:$N$23,$B$5:$B$23,B10)*C10) -> 17.666667 | Q10: =VLOOKUP(D10,Inputs!$A$30:$C$32,2,TRUE()) -> 760 | R10: =VLOOKUP(D10,Inputs!$A$30:$C$32,3,TRUE()) -> 460 | S10: =(O10*Q10+P10*R10)/Inputs!$C$21*(1+Inputs!$C$20) -> 1848.9167 | T10: =SUMIFS('Data - Labour'!$N$5:$N$92,'Data - Labour'!$G$5:$G$92,A10) -> 0 | U10: =T10*(Q10+R10)/2/Inputs!$C$21*(1+Inputs!$C$20) -> 0 | V10: =IF(E10="40HC",ROUNDUP(C10/VLOOKUP(B10,Inputs!$A$54:$L$60,12,0),0)*VLOOKUP(D10,Inputs!$A$36:$B$38,2,TRUE()),0) -> 3000 | W10: =Inputs!$C$22 -> 1025 | X10: =I10+S10+U10+V10+W10 -> 27772.137 | Y10: =X10/C10 -> 13886.068 | Z10: =VLOOKUP(D10,Inputs!$A$66:$B$85,2,TRUE()) -> 89.53 | AA10: =Y10/Z10 -> 155.09961 | AB10: =SUMIFS('Data - SAP Issues'!$N$4:$N$254,'Data - SAP Issues'!$K$4:$K$254,A10) -> 17.776378 | AC10: no labour record (before Feb-26)
A11: J/25-26/134 | B11: 2000 | C11: 3 | D11: 46010 | E11: =VLOOKUP(B11,Inputs!$A$54:$L$60,11,0) -> 40HC | F11: =SUMIFS('Data - SAP Issues'!$I$4:$I$254,'Data - SAP Issues'!$K$4:$K$254,A11,'Data - SAP Issues'!$M$4:$M$254,"Timber") -> 17821.64 | G11: =SUMIFS('Data - SAP Issues'!$I$4:$I$254,'Data - SAP Issues'!$K$4:$K$254,A11)-F11 -> 15529.4 | H11: 0 | I11: =F11+G11-H11 -> 33351.04 | J11: =SUMIFS('Data - Labour'!$M$5:$M$92,'Data - Labour'!$G$5:$G$92,A11,'Data - Labour'!$B$5:$B$92,"Mistri") -> 0 | K11: =SUMIFS('Data - Labour'!$M$5:$M$92,'Data - Labour'!$G$5:$G$92,A11,'Data - Labour'!$B$5:$B$92,"Jogali") -> 0 | L11: =IF(J11+K11>0,"Yes","No") -> No | M11: =IF(L11="Yes",J11/C11,"") | N11: =IF(L11="Yes",K11/C11,"") | O11: =IF(L11="Yes",J11,AVERAGEIFS($M$5:$M$23,$B$5:$B$23,B11)*C11) -> 11.25 | P11: =IF(L11="Yes",K11,AVERAGEIFS($N$5:$N$23,$B$5:$B$23,B11)*C11) -> 28.55 | Q11: =VLOOKUP(D11,Inputs!$A$30:$C$32,2,TRUE()) -> 760 | R11: =VLOOKUP(D11,Inputs!$A$30:$C$32,3,TRUE()) -> 460 | S11: =(O11*Q11+P11*R11)/Inputs!$C$21*(1+Inputs!$C$20) -> 2981.4125 | T11: =SUMIFS('Data - Labour'!$N$5:$N$92,'Data - Labour'!$G$5:$G$92,A11) -> 0 | U11: =T11*(Q11+R11)/2/Inputs!$C$21*(1+Inputs!$C$20) -> 0 | V11: =IF(E11="40HC",ROUNDUP(C11/VLOOKUP(B11,Inputs!$A$54:$L$60,12,0),0)*VLOOKUP(D11,Inputs!$A$36:$B$38,2,TRUE()),0) -> 3000 | W11: =Inputs!$C$22 -> 1025 | X11: =I11+S11+U11+V11+W11 -> 40357.452 | Y11: =X11/C11 -> 13452.484 | Z11: =VLOOKUP(D11,Inputs!$A$66:$B$85,2,TRUE()) -> 89.53 | AA11: =Y11/Z11 -> 150.25672 | AB11: =SUMIFS('Data - SAP Issues'!$N$4:$N$254,'Data - SAP Issues'!$K$4:$K$254,A11) -> 25.456303 | AC11: released BOM (first packing BOM)
A12: J/25-26/139 | B12: 1600 | C12: 2 | D12: 46065 | E12: =VLOOKUP(B12,Inputs!$A$54:$L$60,11,0) -> 40HC | F12: =SUMIFS('Data - SAP Issues'!$I$4:$I$254,'Data - SAP Issues'!$K$4:$K$254,A12,'Data - SAP Issues'!$M$4:$M$254,"Timber") -> 12052.21 | G12: =SUMIFS('Data - SAP Issues'!$I$4:$I$254,'Data - SAP Issues'!$K$4:$K$254,A12)-F12 -> 10024.6 | H12: 0 | I12: =F12+G12-H12 -> 22076.81 | J12: =SUMIFS('Data - Labour'!$M$5:$M$92,'Data - Labour'!$G$5:$G$92,A12,'Data - Labour'!$B$5:$B$92,"Mistri") -> 8.5 | K12: =SUMIFS('Data - Labour'!$M$5:$M$92,'Data - Labour'!$G$5:$G$92,A12,'Data - Labour'!$B$5:$B$92,"Jogali") -> 18.5 | L12: =IF(J12+K12>0,"Yes","No") -> Yes | M12: =IF(L12="Yes",J12/C12,"") -> 4.25 | N12: =IF(L12="Yes",K12/C12,"") -> 9.25 | O12: =IF(L12="Yes",J12,AVERAGEIFS($M$5:$M$23,$B$5:$B$23,B12)*C12) -> 8.5 | P12: =IF(L12="Yes",K12,AVERAGEIFS($N$5:$N$23,$B$5:$B$23,B12)*C12) -> 18.5 | Q12: =VLOOKUP(D12,Inputs!$A$30:$C$32,2,TRUE()) -> 760 | R12: =VLOOKUP(D12,Inputs!$A$30:$C$32,3,TRUE()) -> 460 | S12: =(O12*Q12+P12*R12)/Inputs!$C$21*(1+Inputs!$C$20) -> 2058.375 | T12: =SUMIFS('Data - Labour'!$N$5:$N$92,'Data - Labour'!$G$5:$G$92,A12) -> 1 | U12: =T12*(Q12+R12)/2/Inputs!$C$21*(1+Inputs!$C$20) -> 83.875 | V12: =IF(E12="40HC",ROUNDUP(C12/VLOOKUP(B12,Inputs!$A$54:$L$60,12,0),0)*VLOOKUP(D12,Inputs!$A$36:$B$38,2,TRUE()),0) -> 3200 | W12: =Inputs!$C$22 -> 1025 | X12: =I12+S12+U12+V12+W12 -> 28444.06 | Y12: =X12/C12 -> 14222.03 | Z12: =VLOOKUP(D12,Inputs!$A$66:$B$85,2,TRUE()) -> 89.88 | AA12: =Y12/Z12 -> 158.23353 | AB12: =SUMIFS('Data - SAP Issues'!$N$4:$N$254,'Data - SAP Issues'!$K$4:$K$254,A12) -> 16.73694
A13: J/25-26/143 | B13: 1800 | C13: 2 | D13: 46072 | E13: =VLOOKUP(B13,Inputs!$A$54:$L$60,11,0) -> 40HC | F13: =SUMIFS('Data - SAP Issues'!$I$4:$I$254,'Data - SAP Issues'!$K$4:$K$254,A13,'Data - SAP Issues'!$M$4:$M$254,"Timber") -> 10478.98 | G13: =SUMIFS('Data - SAP Issues'!$I$4:$I$254,'Data - SAP Issues'!$K$4:$K$254,A13)-F13 -> 10438.2 | H13: 0 | I13: =F13+G13-H13 -> 20917.18 | J13: =SUMIFS('Data - Labour'!$M$5:$M$92,'Data - Labour'!$G$5:$G$92,A13,'Data - Labour'!$B$5:$B$92,"Mistri") -> 11 | K13: =SUMIFS('Data - Labour'!$M$5:$M$92,'Data - Labour'!$G$5:$G$92,A13,'Data - Labour'!$B$5:$B$92,"Jogali") -> 20.5 | L13: =IF(J13+K13>0,"Yes","No") -> Yes | M13: =IF(L13="Yes",J13/C13,"") -> 5.5 | N13: =IF(L13="Yes",K13/C13,"") -> 10.25 | O13: =IF(L13="Yes",J13,AVERAGEIFS($M$5:$M$23,$B$5:$B$23,B13)*C13) -> 11 | P13: =IF(L13="Yes",K13,AVERAGEIFS($N$5:$N$23,$B$5:$B$23,B13)*C13) -> 20.5 | Q13: =VLOOKUP(D13,Inputs!$A$30:$C$32,2,TRUE()) -> 760 | R13: =VLOOKUP(D13,Inputs!$A$30:$C$32,3,TRUE()) -> 460 | S13: =(O13*Q13+P13*R13)/Inputs!$C$21*(1+Inputs!$C$20) -> 2446.125 | T13: =SUMIFS('Data - Labour'!$N$5:$N$92,'Data - Labour'!$G$5:$G$92,A13) -> 0 | U13: =T13*(Q13+R13)/2/Inputs!$C$21*(1+Inputs!$C$20) -> 0 | V13: =IF(E13="40HC",ROUNDUP(C13/VLOOKUP(B13,Inputs!$A$54:$L$60,12,0),0)*VLOOKUP(D13,Inputs!$A$36:$B$38,2,TRUE()),0) -> 3200 | W13: =Inputs!$C$22 -> 1025 | X13: =I13+S13+U13+V13+W13 -> 27588.305 | Y13: =X13/C13 -> 13794.153 | Z13: =VLOOKUP(D13,Inputs!$A$66:$B$85,2,TRUE()) -> 89.88 | AA13: =Y13/Z13 -> 153.47299 | AB13: =SUMIFS('Data - SAP Issues'!$N$4:$N$254,'Data - SAP Issues'!$K$4:$K$254,A13) -> 14.552134
A14: J/25-26/145 | B14: 2400 | C14: 5 | D14: 46086 | E14: =VLOOKUP(B14,Inputs!$A$54:$L$60,11,0) -> Flat rack | F14: =SUMIFS('Data - SAP Issues'!$I$4:$I$254,'Data - SAP Issues'!$K$4:$K$254,A14,'Data - SAP Issues'!$M$4:$M$254,"Timber") -> 62918.17 | G14: =SUMIFS('Data - SAP Issues'!$I$4:$I$254,'Data - SAP Issues'!$K$4:$K$254,A14)-F14 -> 48229.4 | H14: 1128.8 | I14: =F14+G14-H14 -> 110018.77 | J14: =SUMIFS('Data - Labour'!$M$5:$M$92,'Data - Labour'!$G$5:$G$92,A14,'Data - Labour'!$B$5:$B$92,"Mistri") -> 46.5 | K14: =SUMIFS('Data - Labour'!$M$5:$M$92,'Data - Labour'!$G$5:$G$92,A14,'Data - Labour'!$B$5:$B$92,"Jogali") -> 92 | L14: =IF(J14+K14>0,"Yes","No") -> Yes | M14: =IF(L14="Yes",J14/C14,"") -> 9.3 | N14: =IF(L14="Yes",K14/C14,"") -> 18.4 | O14: =IF(L14="Yes",J14,AVERAGEIFS($M$5:$M$23,$B$5:$B$23,B14)*C14) -> 46.5 | P14: =IF(L14="Yes",K14,AVERAGEIFS($N$5:$N$23,$B$5:$B$23,B14)*C14) -> 92 | Q14: =VLOOKUP(D14,Inputs!$A$30:$C$32,2,TRUE()) -> 760 | R14: =VLOOKUP(D14,Inputs!$A$30:$C$32,3,TRUE()) -> 460 | S14: =(O14*Q14+P14*R14)/Inputs!$C$21*(1+Inputs!$C$20) -> 10678.25 | T14: =SUMIFS('Data - Labour'!$N$5:$N$92,'Data - Labour'!$G$5:$G$92,A14) -> 12 | U14: =T14*(Q14+R14)/2/Inputs!$C$21*(1+Inputs!$C$20) -> 1006.5 | V14: =IF(E14="40HC",ROUNDUP(C14/VLOOKUP(B14,Inputs!$A$54:$L$60,12,0),0)*VLOOKUP(D14,Inputs!$A$36:$B$38,2,TRUE()),0) -> 0 | W14: =Inputs!$C$22 -> 1025 | X14: =I14+S14+U14+V14+W14 -> 122728.52 | Y14: =X14/C14 -> 24545.704 | Z14: =VLOOKUP(D14,Inputs!$A$66:$B$85,2,TRUE()) -> 90.96 | AA14: =Y14/Z14 -> 269.85163 | AB14: =SUMIFS('Data - SAP Issues'!$N$4:$N$254,'Data - SAP Issues'!$K$4:$K$254,A14) -> 87.374595
A15: J/25-26/151 | B15: 2000 | C15: 5 | D15: 46100 | E15: =VLOOKUP(B15,Inputs!$A$54:$L$60,11,0) -> 40HC | F15: =SUMIFS('Data - SAP Issues'!$I$4:$I$254,'Data - SAP Issues'!$K$4:$K$254,A15,'Data - SAP Issues'!$M$4:$M$254,"Timber") -> 25212.1 | G15: =SUMIFS('Data - SAP Issues'!$I$4:$I$254,'Data - SAP Issues'!$K$4:$K$254,A15)-F15 -> 23123.8 | H15: 0 | I15: =F15+G15-H15 -> 48335.9 | J15: =SUMIFS('Data - Labour'!$M$5:$M$92,'Data - Labour'!$G$5:$G$92,A15,'Data - Labour'!$B$5:$B$92,"Mistri") -> 20 | K15: =SUMIFS('Data - Labour'!$M$5:$M$92,'Data - Labour'!$G$5:$G$92,A15,'Data - Labour'!$B$5:$B$92,"Jogali") -> 46 | L15: =IF(J15+K15>0,"Yes","No") -> Yes | M15: =IF(L15="Yes",J15/C15,"") -> 4 | N15: =IF(L15="Yes",K15/C15,"") -> 9.2 | O15: =IF(L15="Yes",J15,AVERAGEIFS($M$5:$M$23,$B$5:$B$23,B15)*C15) -> 20 | P15: =IF(L15="Yes",K15,AVERAGEIFS($N$5:$N$23,$B$5:$B$23,B15)*C15) -> 46 | Q15: =VLOOKUP(D15,Inputs!$A$30:$C$32,2,TRUE()) -> 760 | R15: =VLOOKUP(D15,Inputs!$A$30:$C$32,3,TRUE()) -> 460 | S15: =(O15*Q15+P15*R15)/Inputs!$C$21*(1+Inputs!$C$20) -> 4999.5 | T15: =SUMIFS('Data - Labour'!$N$5:$N$92,'Data - Labour'!$G$5:$G$92,A15) -> 6 | U15: =T15*(Q15+R15)/2/Inputs!$C$21*(1+Inputs!$C$20) -> 503.25 | V15: =IF(E15="40HC",ROUNDUP(C15/VLOOKUP(B15,Inputs!$A$54:$L$60,12,0),0)*VLOOKUP(D15,Inputs!$A$36:$B$38,2,TRUE()),0) -> 6400 | W15: =Inputs!$C$22 -> 1025 | X15: =I15+S15+U15+V15+W15 -> 61263.65 | Y15: =X15/C15 -> 12252.73 | Z15: =VLOOKUP(D15,Inputs!$A$66:$B$85,2,TRUE()) -> 92.63 | AA15: =Y15/Z15 -> 132.27604 | AB15: =SUMIFS('Data - SAP Issues'!$N$4:$N$254,'Data - SAP Issues'!$K$4:$K$254,A15) -> 35.012072 | AC15: released BOM (first packing BOM)
A16: J/25-26/152 | B16: 1400 | C16: 3 | D16: 46107 | E16: =VLOOKUP(B16,Inputs!$A$54:$L$60,11,0) -> 40HC | F16: =SUMIFS('Data - SAP Issues'!$I$4:$I$254,'Data - SAP Issues'!$K$4:$K$254,A16,'Data - SAP Issues'!$M$4:$M$254,"Timber") -> 13057.37 | G16: =SUMIFS('Data - SAP Issues'!$I$4:$I$254,'Data - SAP Issues'!$K$4:$K$254,A16)-F16 -> 16324.4 | H16: 680 | I16: =F16+G16-H16 -> 28701.77 | J16: =SUMIFS('Data - Labour'!$M$5:$M$92,'Data - Labour'!$G$5:$G$92,A16,'Data - Labour'!$B$5:$B$92,"Mistri") -> 10.5 | K16: =SUMIFS('Data - Labour'!$M$5:$M$92,'Data - Labour'!$G$5:$G$92,A16,'Data - Labour'!$B$5:$B$92,"Jogali") -> 26.5 | L16: =IF(J16+K16>0,"Yes","No") -> Yes | M16: =IF(L16="Yes",J16/C16,"") -> 3.5 | N16: =IF(L16="Yes",K16/C16,"") -> 8.8333333 | O16: =IF(L16="Yes",J16,AVERAGEIFS($M$5:$M$23,$B$5:$B$23,B16)*C16) -> 10.5 | P16: =IF(L16="Yes",K16,AVERAGEIFS($N$5:$N$23,$B$5:$B$23,B16)*C16) -> 26.5 | Q16: =VLOOKUP(D16,Inputs!$A$30:$C$32,2,TRUE()) -> 760 | R16: =VLOOKUP(D16,Inputs!$A$30:$C$32,3,TRUE()) -> 460 | S16: =(O16*Q16+P16*R16)/Inputs!$C$21*(1+Inputs!$C$20) -> 2773.375 | T16: =SUMIFS('Data - Labour'!$N$5:$N$92,'Data - Labour'!$G$5:$G$92,A16) -> 3 | U16: =T16*(Q16+R16)/2/Inputs!$C$21*(1+Inputs!$C$20) -> 251.625 | V16: =IF(E16="40HC",ROUNDUP(C16/VLOOKUP(B16,Inputs!$A$54:$L$60,12,0),0)*VLOOKUP(D16,Inputs!$A$36:$B$38,2,TRUE()),0) -> 3200 | W16: =Inputs!$C$22 -> 1025 | X16: =I16+S16+U16+V16+W16 -> 35951.77 | Y16: =X16/C16 -> 11983.923 | Z16: =VLOOKUP(D16,Inputs!$A$66:$B$85,2,TRUE()) -> 92.63 | AA16: =Y16/Z16 -> 129.3741 | AB16: =SUMIFS('Data - SAP Issues'!$N$4:$N$254,'Data - SAP Issues'!$K$4:$K$254,A16) -> 17.597621 | AC16: 1 day hrs not noted - 8 hrs taken
A17: J/25-26/156 | B17: 1800 | C17: 3 | D17: 46121 | E17: =VLOOKUP(B17,Inputs!$A$54:$L$60,11,0) -> 40HC | F17: =SUMIFS('Data - SAP Issues'!$I$4:$I$254,'Data - SAP Issues'!$K$4:$K$254,A17,'Data - SAP Issues'!$M$4:$M$254,"Timber") -> 17332.95 | G17: =SUMIFS('Data - SAP Issues'!$I$4:$I$254,'Data - SAP Issues'!$K$4:$K$254,A17)-F17 -> 16857 | H17: 0 | I17: =F17+G17-H17 -> 34189.95 | J17: =SUMIFS('Data - Labour'!$M$5:$M$92,'Data - Labour'!$G$5:$G$92,A17,'Data - Labour'!$B$5:$B$92,"Mistri") -> 12 | K17: =SUMIFS('Data - Labour'!$M$5:$M$92,'Data - Labour'!$G$5:$G$92,A17,'Data - Labour'!$B$5:$B$92,"Jogali") -> 30 | L17: =IF(J17+K17>0,"Yes","No") -> Yes | M17: =IF(L17="Yes",J17/C17,"") -> 4 | N17: =IF(L17="Yes",K17/C17,"") -> 10 | O17: =IF(L17="Yes",J17,AVERAGEIFS($M$5:$M$23,$B$5:$B$23,B17)*C17) -> 12 | P17: =IF(L17="Yes",K17,AVERAGEIFS($N$5:$N$23,$B$5:$B$23,B17)*C17) -> 30 | Q17: =VLOOKUP(D17,Inputs!$A$30:$C$32,2,TRUE()) -> 800 | R17: =VLOOKUP(D17,Inputs!$A$30:$C$32,3,TRUE()) -> 460 | S17: =(O17*Q17+P17*R17)/Inputs!$C$21*(1+Inputs!$C$20) -> 3217.5 | T17: =SUMIFS('Data - Labour'!$N$5:$N$92,'Data - Labour'!$G$5:$G$92,A17) -> 2 | U17: =T17*(Q17+R17)/2/Inputs!$C$21*(1+Inputs!$C$20) -> 173.25 | V17: =IF(E17="40HC",ROUNDUP(C17/VLOOKUP(B17,Inputs!$A$54:$L$60,12,0),0)*VLOOKUP(D17,Inputs!$A$36:$B$38,2,TRUE()),0) -> 3200 | W17: =Inputs!$C$22 -> 1025 | X17: =I17+S17+U17+V17+W17 -> 41805.7 | Y17: =X17/C17 -> 13935.233 | Z17: =VLOOKUP(D17,Inputs!$A$66:$B$85,2,TRUE()) -> 92.63 | AA17: =Y17/Z17 -> 150.43974 | AB17: =SUMIFS('Data - SAP Issues'!$N$4:$N$254,'Data - SAP Issues'!$K$4:$K$254,A17) -> 23.359772
A18: J/25-26/137 | B18: 3000 | C18: 3 | D18: 46129 | E18: =VLOOKUP(B18,Inputs!$A$54:$L$60,11,0) -> Flat rack | F18: =SUMIFS('Data - SAP Issues'!$I$4:$I$254,'Data - SAP Issues'!$K$4:$K$254,A18,'Data - SAP Issues'!$M$4:$M$254,"Timber") -> 36922.31 | G18: =SUMIFS('Data - SAP Issues'!$I$4:$I$254,'Data - SAP Issues'!$K$4:$K$254,A18)-F18 -> 46991.8 | H18: 0 | I18: =F18+G18-H18 -> 83914.11 | J18: =SUMIFS('Data - Labour'!$M$5:$M$92,'Data - Labour'!$G$5:$G$92,A18,'Data - Labour'!$B$5:$B$92,"Mistri") -> 32 | K18: =SUMIFS('Data - Labour'!$M$5:$M$92,'Data - Labour'!$G$5:$G$92,A18,'Data - Labour'!$B$5:$B$92,"Jogali") -> 72 | L18: =IF(J18+K18>0,"Yes","No") -> Yes | M18: =IF(L18="Yes",J18/C18,"") -> 10.666667 | N18: =IF(L18="Yes",K18/C18,"") -> 24 | O18: =IF(L18="Yes",J18,AVERAGEIFS($M$5:$M$23,$B$5:$B$23,B18)*C18) -> 32 | P18: =IF(L18="Yes",K18,AVERAGEIFS($N$5:$N$23,$B$5:$B$23,B18)*C18) -> 72 | Q18: =VLOOKUP(D18,Inputs!$A$30:$C$32,2,TRUE()) -> 800 | R18: =VLOOKUP(D18,Inputs!$A$30:$C$32,3,TRUE()) -> 460 | S18: =(O18*Q18+P18*R18)/Inputs!$C$21*(1+Inputs!$C$20) -> 8074 | T18: =SUMIFS('Data - Labour'!$N$5:$N$92,'Data - Labour'!$G$5:$G$92,A18) -> 9.5 | U18: =T18*(Q18+R18)/2/Inputs!$C$21*(1+Inputs!$C$20) -> 822.9375 | V18: =IF(E18="40HC",ROUNDUP(C18/VLOOKUP(B18,Inputs!$A$54:$L$60,12,0),0)*VLOOKUP(D18,Inputs!$A$36:$B$38,2,TRUE()),0) -> 0 | W18: =Inputs!$C$22 -> 1025 | X18: =I18+S18+U18+V18+W18 -> 93836.048 | Y18: =X18/C18 -> 31278.682 | Z18: =VLOOKUP(D18,Inputs!$A$66:$B$85,2,TRUE()) -> 93.54 | AA18: =Y18/Z18 -> 334.38831 | AB18: =SUMIFS('Data - SAP Issues'!$N$4:$N$254,'Data - SAP Issues'!$K$4:$K$254,A18) -> 50.288061 | AC18: 1 + 2 nos, 2 dispatches
A19: J/25-26/158 | B19: 2600 | C19: 4 | D19: 46135 | E19: =VLOOKUP(B19,Inputs!$A$54:$L$60,11,0) -> Flat rack | F19: =SUMIFS('Data - SAP Issues'!$I$4:$I$254,'Data - SAP Issues'!$K$4:$K$254,A19,'Data - SAP Issues'!$M$4:$M$254,"Timber") -> 53105.65 | G19: =SUMIFS('Data - SAP Issues'!$I$4:$I$254,'Data - SAP Issues'!$K$4:$K$254,A19)-F19 -> 50509.4 | H19: 0 | I19: =F19+G19-H19 -> 103615.05 | J19: =SUMIFS('Data - Labour'!$M$5:$M$92,'Data - Labour'!$G$5:$G$92,A19,'Data - Labour'!$B$5:$B$92,"Mistri") -> 31 | K19: =SUMIFS('Data - Labour'!$M$5:$M$92,'Data - Labour'!$G$5:$G$92,A19,'Data - Labour'!$B$5:$B$92,"Jogali") -> 69.5 | L19: =IF(J19+K19>0,"Yes","No") -> Yes | M19: =IF(L19="Yes",J19/C19,"") -> 7.75 | N19: =IF(L19="Yes",K19/C19,"") -> 17.375 | O19: =IF(L19="Yes",J19,AVERAGEIFS($M$5:$M$23,$B$5:$B$23,B19)*C19) -> 31 | P19: =IF(L19="Yes",K19,AVERAGEIFS($N$5:$N$23,$B$5:$B$23,B19)*C19) -> 69.5 | Q19: =VLOOKUP(D19,Inputs!$A$30:$C$32,2,TRUE()) -> 800 | R19: =VLOOKUP(D19,Inputs!$A$30:$C$32,3,TRUE()) -> 460 | S19: =(O19*Q19+P19*R19)/Inputs!$C$21*(1+Inputs!$C$20) -> 7805.875 | T19: =SUMIFS('Data - Labour'!$N$5:$N$92,'Data - Labour'!$G$5:$G$92,A19) -> 7.5 | U19: =T19*(Q19+R19)/2/Inputs!$C$21*(1+Inputs!$C$20) -> 649.6875 | V19: =IF(E19="40HC",ROUNDUP(C19/VLOOKUP(B19,Inputs!$A$54:$L$60,12,0),0)*VLOOKUP(D19,Inputs!$A$36:$B$38,2,TRUE()),0) -> 0 | W19: =Inputs!$C$22 -> 1025 | X19: =I19+S19+U19+V19+W19 -> 113095.61 | Y19: =X19/C19 -> 28273.903 | Z19: =VLOOKUP(D19,Inputs!$A$66:$B$85,2,TRUE()) -> 93.16 | AA19: =Y19/Z19 -> 303.49832 | AB19: =SUMIFS('Data - SAP Issues'!$N$4:$N$254,'Data - SAP Issues'!$K$4:$K$254,A19) -> 71.571163
A20: J/25-26/164 | B20: 2400 | C20: 3 | D20: 46156 | E20: =VLOOKUP(B20,Inputs!$A$54:$L$60,11,0) -> Flat rack | F20: =SUMIFS('Data - SAP Issues'!$I$4:$I$254,'Data - SAP Issues'!$K$4:$K$254,A20,'Data - SAP Issues'!$M$4:$M$254,"Timber") -> 30942.14 | G20: =SUMIFS('Data - SAP Issues'!$I$4:$I$254,'Data - SAP Issues'!$K$4:$K$254,A20)-F20 -> 34937.8 | H20: 0 | I20: =F20+G20-H20 -> 65879.94 | J20: =SUMIFS('Data - Labour'!$M$5:$M$92,'Data - Labour'!$G$5:$G$92,A20,'Data - Labour'!$B$5:$B$92,"Mistri") -> 31 | K20: =SUMIFS('Data - Labour'!$M$5:$M$92,'Data - Labour'!$G$5:$G$92,A20,'Data - Labour'!$B$5:$B$92,"Jogali") -> 58.5 | L20: =IF(J20+K20>0,"Yes","No") -> Yes | M20: =IF(L20="Yes",J20/C20,"") -> 10.333333 | N20: =IF(L20="Yes",K20/C20,"") -> 19.5 | O20: =IF(L20="Yes",J20,AVERAGEIFS($M$5:$M$23,$B$5:$B$23,B20)*C20) -> 31 | P20: =IF(L20="Yes",K20,AVERAGEIFS($N$5:$N$23,$B$5:$B$23,B20)*C20) -> 58.5 | Q20: =VLOOKUP(D20,Inputs!$A$30:$C$32,2,TRUE()) -> 800 | R20: =VLOOKUP(D20,Inputs!$A$30:$C$32,3,TRUE()) -> 460 | S20: =(O20*Q20+P20*R20)/Inputs!$C$21*(1+Inputs!$C$20) -> 7110.125 | T20: =SUMIFS('Data - Labour'!$N$5:$N$92,'Data - Labour'!$G$5:$G$92,A20) -> 8.5 | U20: =T20*(Q20+R20)/2/Inputs!$C$21*(1+Inputs!$C$20) -> 736.3125 | V20: =IF(E20="40HC",ROUNDUP(C20/VLOOKUP(B20,Inputs!$A$54:$L$60,12,0),0)*VLOOKUP(D20,Inputs!$A$36:$B$38,2,TRUE()),0) -> 0 | W20: =Inputs!$C$22 -> 1025 | X20: =I20+S20+U20+V20+W20 -> 74751.378 | Y20: =X20/C20 -> 24917.126 | Z20: =VLOOKUP(D20,Inputs!$A$66:$B$85,2,TRUE()) -> 95.11 | AA20: =Y20/Z20 -> 261.98219 | AB20: =SUMIFS('Data - SAP Issues'!$N$4:$N$254,'Data - SAP Issues'!$K$4:$K$254,A20) -> 41.70111
A21: J/25-26/165 | B21: 1600 | C21: 1 | D21: 46177 | E21: =VLOOKUP(B21,Inputs!$A$54:$L$60,11,0) -> 40HC | F21: =SUMIFS('Data - SAP Issues'!$I$4:$I$254,'Data - SAP Issues'!$K$4:$K$254,A21,'Data - SAP Issues'!$M$4:$M$254,"Timber") -> 5747.64 | G21: =SUMIFS('Data - SAP Issues'!$I$4:$I$254,'Data - SAP Issues'!$K$4:$K$254,A21)-F21 -> 7262.4 | H21: 0 | I21: =F21+G21-H21 -> 13010.04 | J21: =SUMIFS('Data - Labour'!$M$5:$M$92,'Data - Labour'!$G$5:$G$92,A21,'Data - Labour'!$B$5:$B$92,"Mistri") -> 5 | K21: =SUMIFS('Data - Labour'!$M$5:$M$92,'Data - Labour'!$G$5:$G$92,A21,'Data - Labour'!$B$5:$B$92,"Jogali") -> 10 | L21: =IF(J21+K21>0,"Yes","No") -> Yes | M21: =IF(L21="Yes",J21/C21,"") -> 5 | N21: =IF(L21="Yes",K21/C21,"") -> 10 | O21: =IF(L21="Yes",J21,AVERAGEIFS($M$5:$M$23,$B$5:$B$23,B21)*C21) -> 5 | P21: =IF(L21="Yes",K21,AVERAGEIFS($N$5:$N$23,$B$5:$B$23,B21)*C21) -> 10 | Q21: =VLOOKUP(D21,Inputs!$A$30:$C$32,2,TRUE()) -> 800 | R21: =VLOOKUP(D21,Inputs!$A$30:$C$32,3,TRUE()) -> 460 | S21: =(O21*Q21+P21*R21)/Inputs!$C$21*(1+Inputs!$C$20) -> 1182.5 | T21: =SUMIFS('Data - Labour'!$N$5:$N$92,'Data - Labour'!$G$5:$G$92,A21) -> 0 | U21: =T21*(Q21+R21)/2/Inputs!$C$21*(1+Inputs!$C$20) -> 0 | V21: =IF(E21="40HC",ROUNDUP(C21/VLOOKUP(B21,Inputs!$A$54:$L$60,12,0),0)*VLOOKUP(D21,Inputs!$A$36:$B$38,2,TRUE()),0) -> 3200 | W21: =Inputs!$C$22 -> 1025 | X21: =I21+S21+U21+V21+W21 -> 18417.54 | Y21: =X21/C21 -> 18417.54 | Z21: =VLOOKUP(D21,Inputs!$A$66:$B$85,2,TRUE()) -> 96.18 | AA21: =Y21/Z21 -> 191.49033 | AB21: =SUMIFS('Data - SAP Issues'!$N$4:$N$254,'Data - SAP Issues'!$K$4:$K$254,A21) -> 7.7461313 | AC21: 2 lines posted to wrong job in SAP - corrected
A22: J/25-26/167 | B22: 2600 | C22: 3 | D22: 46191 | E22: =VLOOKUP(B22,Inputs!$A$54:$L$60,11,0) -> Flat rack | F22: =SUMIFS('Data - SAP Issues'!$I$4:$I$254,'Data - SAP Issues'!$K$4:$K$254,A22,'Data - SAP Issues'!$M$4:$M$254,"Timber") -> 36018.81 | G22: =SUMIFS('Data - SAP Issues'!$I$4:$I$254,'Data - SAP Issues'!$K$4:$K$254,A22)-F22 -> 41721 | H22: 0 | I22: =F22+G22-H22 -> 77739.81 | J22: =SUMIFS('Data - Labour'!$M$5:$M$92,'Data - Labour'!$G$5:$G$92,A22,'Data - Labour'!$B$5:$B$92,"Mistri") -> 30 | K22: =SUMIFS('Data - Labour'!$M$5:$M$92,'Data - Labour'!$G$5:$G$92,A22,'Data - Labour'!$B$5:$B$92,"Jogali") -> 71 | L22: =IF(J22+K22>0,"Yes","No") -> Yes | M22: =IF(L22="Yes",J22/C22,"") -> 10 | N22: =IF(L22="Yes",K22/C22,"") -> 23.666667 | O22: =IF(L22="Yes",J22,AVERAGEIFS($M$5:$M$23,$B$5:$B$23,B22)*C22) -> 30 | P22: =IF(L22="Yes",K22,AVERAGEIFS($N$5:$N$23,$B$5:$B$23,B22)*C22) -> 71 | Q22: =VLOOKUP(D22,Inputs!$A$30:$C$32,2,TRUE()) -> 800 | R22: =VLOOKUP(D22,Inputs!$A$30:$C$32,3,TRUE()) -> 460 | S22: =(O22*Q22+P22*R22)/Inputs!$C$21*(1+Inputs!$C$20) -> 7790.75 | T22: =SUMIFS('Data - Labour'!$N$5:$N$92,'Data - Labour'!$G$5:$G$92,A22) -> 10.5 | U22: =T22*(Q22+R22)/2/Inputs!$C$21*(1+Inputs!$C$20) -> 909.5625 | V22: =IF(E22="40HC",ROUNDUP(C22/VLOOKUP(B22,Inputs!$A$54:$L$60,12,0),0)*VLOOKUP(D22,Inputs!$A$36:$B$38,2,TRUE()),0) -> 0 | W22: =Inputs!$C$22 -> 1025 | X22: =I22+S22+U22+V22+W22 -> 87465.122 | Y22: =X22/C22 -> 29155.041 | Z22: =VLOOKUP(D22,Inputs!$A$66:$B$85,2,TRUE()) -> 96.18 | AA22: =Y22/Z22 -> 303.12997 | AB22: =SUMIFS('Data - SAP Issues'!$N$4:$N$254,'Data - SAP Issues'!$K$4:$K$254,A22) -> 47.077058
A23: J/26-27/018 | B23: 2000 | C23: 6 | D23: 46226 | E23: =VLOOKUP(B23,Inputs!$A$54:$L$60,11,0) -> 40HC | F23: =SUMIFS('Data - SAP Issues'!$I$4:$I$254,'Data - SAP Issues'!$K$4:$K$254,A23,'Data - SAP Issues'!$M$4:$M$254,"Timber") -> 31436.16 | G23: =SUMIFS('Data - SAP Issues'!$I$4:$I$254,'Data - SAP Issues'!$K$4:$K$254,A23)-F23 -> 25593.2 | H23: 0 | I23: =F23+G23-H23 -> 57029.36 | J23: =SUMIFS('Data - Labour'!$M$5:$M$92,'Data - Labour'!$G$5:$G$92,A23,'Data - Labour'!$B$5:$B$92,"Mistri") -> 21 | K23: =SUMIFS('Data - Labour'!$M$5:$M$92,'Data - Labour'!$G$5:$G$92,A23,'Data - Labour'!$B$5:$B$92,"Jogali") -> 59 | L23: =IF(J23+K23>0,"Yes","No") -> Yes | M23: =IF(L23="Yes",J23/C23,"") -> 3.5 | N23: =IF(L23="Yes",K23/C23,"") -> 9.8333333 | O23: =IF(L23="Yes",J23,AVERAGEIFS($M$5:$M$23,$B$5:$B$23,B23)*C23) -> 21 | P23: =IF(L23="Yes",K23,AVERAGEIFS($N$5:$N$23,$B$5:$B$23,B23)*C23) -> 59 | Q23: =VLOOKUP(D23,Inputs!$A$30:$C$32,2,TRUE()) -> 800 | R23: =VLOOKUP(D23,Inputs!$A$30:$C$32,3,TRUE()) -> 480 | S23: =(O23*Q23+P23*R23)/Inputs!$C$21*(1+Inputs!$C$20) -> 6204 | T23: =SUMIFS('Data - Labour'!$N$5:$N$92,'Data - Labour'!$G$5:$G$92,A23) -> 7.5 | U23: =T23*(Q23+R23)/2/Inputs!$C$21*(1+Inputs!$C$20) -> 660 | V23: =IF(E23="40HC",ROUNDUP(C23/VLOOKUP(B23,Inputs!$A$54:$L$60,12,0),0)*VLOOKUP(D23,Inputs!$A$36:$B$38,2,TRUE()),0) -> 7000 | W23: =Inputs!$C$22 -> 1025 | X23: =I23+S23+U23+V23+W23 -> 71918.36 | Y23: =X23/C23 -> 11986.393 | Z23: =VLOOKUP(D23,Inputs!$A$66:$B$85,2,TRUE()) -> 95.38 | AA23: =Y23/Z23 -> 125.66988 | AB23: =SUMIFS('Data - SAP Issues'!$N$4:$N$254,'Data - SAP Issues'!$K$4:$K$254,A23) -> 41.087599 | AC23: released BOM (first packing BOM)
A25: TOTAL | C25: =SUM(C5:C23) -> 60 | F25: =SUM(F5:F23) -> 507035.87 | G25: =SUM(G5:G23) -> 501051 | H25: =SUM(H5:H23) -> 1808.8 | I25: =SUM(I5:I23) -> 1006278.1 | S25: =SUM(S5:S23) -> 98191.305 | U25: =SUM(U5:U23) -> 5797 | V25: =SUM(V5:V23) -> 41400 | W25: =SUM(W5:W23) -> 19475 | X25: =SUM(X5:X23) -> 1171141.4 | Y25: =X25/C25 -> 19519.023 | AB25: =SUM(AB5:AB23) -> 699.51758
A27: OT is paid at double rate, so OT hours add one extra ordinary rate (average of carpenter and helper). Fumigation = containers x rate for 40HC jobs.

Sheet Proposed Std
A1: Proposed packing standard per vessel - worked out from past jobs
A2: No BOM existed except for 2.0 m. Average used per vessel by size = the proposed standard, to be signed off by production.
A4: Size (mm) | B4: UoM | C4: 1400 | D4: 1600 | E4: 1800 | F4: 2000 | G4: 2400 | H4: 2600 | I4: 3000
A5: Jobs packed | C5: =COUNTIF('Job Costing'!$B$5:$B$23,C$4) -> 2 | D5: =COUNTIF('Job Costing'!$B$5:$B$23,D$4) -> 2 | E5: =COUNTIF('Job Costing'!$B$5:$B$23,E$4) -> 3 | F5: =COUNTIF('Job Costing'!$B$5:$B$23,F$4) -> 3 | G5: =COUNTIF('Job Costing'!$B$5:$B$23,G$4) -> 4 | H5: =COUNTIF('Job Costing'!$B$5:$B$23,H$4) -> 4 | I5: =COUNTIF('Job Costing'!$B$5:$B$23,I$4) -> 1
A6: Vessels packed | C6: =SUMIFS('Job Costing'!$C$5:$C$23,'Job Costing'!$B$5:$B$23,C$4) -> 5 | D6: =SUMIFS('Job Costing'!$C$5:$C$23,'Job Costing'!$B$5:$B$23,D$4) -> 3 | E6: =SUMIFS('Job Costing'!$C$5:$C$23,'Job Costing'!$B$5:$B$23,E$4) -> 9 | F6: =SUMIFS('Job Costing'!$C$5:$C$23,'Job Costing'!$B$5:$B$23,F$4) -> 14 | G6: =SUMIFS('Job Costing'!$C$5:$C$23,'Job Costing'!$B$5:$B$23,G$4) -> 14 | H6: =SUMIFS('Job Costing'!$C$5:$C$23,'Job Costing'!$B$5:$B$23,H$4) -> 12 | I6: =SUMIFS('Job Costing'!$C$5:$C$23,'Job Costing'!$B$5:$B$23,I$4) -> 3
A8: A. Average used per vessel (SAP issues / vessels)
A9: Timber | B9: cft | C9: =SUMIFS('Data - SAP Issues'!$N$4:$N$254,'Data - SAP Issues'!$L$4:$L$254,C$4)/C$6 -> 7.0747999 | D9: =SUMIFS('Data - SAP Issues'!$N$4:$N$254,'Data - SAP Issues'!$L$4:$L$254,D$4)/D$6 -> 8.1610238 | E9: =SUMIFS('Data - SAP Issues'!$N$4:$N$254,'Data - SAP Issues'!$L$4:$L$254,E$4)/E$6 -> 7.649274 | F9: =SUMIFS('Data - SAP Issues'!$N$4:$N$254,'Data - SAP Issues'!$L$4:$L$254,F$4)/F$6 -> 7.2539981 | G9: =SUMIFS('Data - SAP Issues'!$N$4:$N$254,'Data - SAP Issues'!$L$4:$L$254,G$4)/G$6 -> 15.595513 | H9: =SUMIFS('Data - SAP Issues'!$N$4:$N$254,'Data - SAP Issues'!$L$4:$L$254,H$4)/H$6 -> 16.719653 | I9: =SUMIFS('Data - SAP Issues'!$N$4:$N$254,'Data - SAP Issues'!$L$4:$L$254,I$4)/I$6 -> 16.762687 | K9: includes spares and splits seen in the issues
A10: Nails | B10: set | C10: =SUMIFS('Data - SAP Issues'!$F$4:$F$254,'Data - SAP Issues'!$L$4:$L$254,C$4,'Data - SAP Issues'!$M$4:$M$254,$A10)/C$6 -> 1.2 | D10: =SUMIFS('Data - SAP Issues'!$F$4:$F$254,'Data - SAP Issues'!$L$4:$L$254,D$4,'Data - SAP Issues'!$M$4:$M$254,$A10)/D$6 -> 1.6666667 | E10: =SUMIFS('Data - SAP Issues'!$F$4:$F$254,'Data - SAP Issues'!$L$4:$L$254,E$4,'Data - SAP Issues'!$M$4:$M$254,$A10)/E$6 -> 1.3333333 | F10: =SUMIFS('Data - SAP Issues'!$F$4:$F$254,'Data - SAP Issues'!$L$4:$L$254,F$4,'Data - SAP Issues'!$M$4:$M$254,$A10)/F$6 -> 1.0714286 | G10: =SUMIFS('Data - SAP Issues'!$F$4:$F$254,'Data - SAP Issues'!$L$4:$L$254,G$4,'Data - SAP Issues'!$M$4:$M$254,$A10)/G$6 -> 2.4285714 | H10: =SUMIFS('Data - SAP Issues'!$F$4:$F$254,'Data - SAP Issues'!$L$4:$L$254,H$4,'Data - SAP Issues'!$M$4:$M$254,$A10)/H$6 -> 2.3333333 | I10: =SUMIFS('Data - SAP Issues'!$F$4:$F$254,'Data - SAP Issues'!$L$4:$L$254,I$4,'Data - SAP Issues'!$M$4:$M$254,$A10)/I$6 -> 3
A11: Foam | B11: roll | C11: =SUMIFS('Data - SAP Issues'!$F$4:$F$254,'Data - SAP Issues'!$L$4:$L$254,C$4,'Data - SAP Issues'!$M$4:$M$254,$A11)/C$6 -> 0.6 | D11: =SUMIFS('Data - SAP Issues'!$F$4:$F$254,'Data - SAP Issues'!$L$4:$L$254,D$4,'Data - SAP Issues'!$M$4:$M$254,$A11)/D$6 -> 0.66666667 | E11: =SUMIFS('Data - SAP Issues'!$F$4:$F$254,'Data - SAP Issues'!$L$4:$L$254,E$4,'Data - SAP Issues'!$M$4:$M$254,$A11)/E$6 -> 0.55555556 | F11: =SUMIFS('Data - SAP Issues'!$F$4:$F$254,'Data - SAP Issues'!$L$4:$L$254,F$4,'Data - SAP Issues'!$M$4:$M$254,$A11)/F$6 -> 0.57142857 | G11: =SUMIFS('Data - SAP Issues'!$F$4:$F$254,'Data - SAP Issues'!$L$4:$L$254,G$4,'Data - SAP Issues'!$M$4:$M$254,$A11)/G$6 -> 1 | H11: =SUMIFS('Data - SAP Issues'!$F$4:$F$254,'Data - SAP Issues'!$L$4:$L$254,H$4,'Data - SAP Issues'!$M$4:$M$254,$A11)/H$6 -> 1.1666667 | I11: =SUMIFS('Data - SAP Issues'!$F$4:$F$254,'Data - SAP Issues'!$L$4:$L$254,I$4,'Data - SAP Issues'!$M$4:$M$254,$A11)/I$6 -> 1.3333333
A12: Ratchet belt | B12: nos | C12: =SUMIFS('Data - SAP Issues'!$F$4:$F$254,'Data - SAP Issues'!$L$4:$L$254,C$4,'Data - SAP Issues'!$M$4:$M$254,$A12)/C$6 -> 2.2 | D12: =SUMIFS('Data - SAP Issues'!$F$4:$F$254,'Data - SAP Issues'!$L$4:$L$254,D$4,'Data - SAP Issues'!$M$4:$M$254,$A12)/D$6 -> 2.3333333 | E12: =SUMIFS('Data - SAP Issues'!$F$4:$F$254,'Data - SAP Issues'!$L$4:$L$254,E$4,'Data - SAP Issues'!$M$4:$M$254,$A12)/E$6 -> 2.1111111 | F12: =SUMIFS('Data - SAP Issues'!$F$4:$F$254,'Data - SAP Issues'!$L$4:$L$254,F$4,'Data - SAP Issues'!$M$4:$M$254,$A12)/F$6 -> 2.2857143 | G12: =SUMIFS('Data - SAP Issues'!$F$4:$F$254,'Data - SAP Issues'!$L$4:$L$254,G$4,'Data - SAP Issues'!$M$4:$M$254,$A12)/G$6 -> 3.0714286 | H12: =SUMIFS('Data - SAP Issues'!$F$4:$F$254,'Data - SAP Issues'!$L$4:$L$254,H$4,'Data - SAP Issues'!$M$4:$M$254,$A12)/H$6 -> 3.5 | I12: =SUMIFS('Data - SAP Issues'!$F$4:$F$254,'Data - SAP Issues'!$L$4:$L$254,I$4,'Data - SAP Issues'!$M$4:$M$254,$A12)/I$6 -> 4
A13: Gum tape | B13: roll | C13: =SUMIFS('Data - SAP Issues'!$F$4:$F$254,'Data - SAP Issues'!$L$4:$L$254,C$4,'Data - SAP Issues'!$M$4:$M$254,$A13)/C$6 -> 0.8 | D13: =SUMIFS('Data - SAP Issues'!$F$4:$F$254,'Data - SAP Issues'!$L$4:$L$254,D$4,'Data - SAP Issues'!$M$4:$M$254,$A13)/D$6 -> 1 | E13: =SUMIFS('Data - SAP Issues'!$F$4:$F$254,'Data - SAP Issues'!$L$4:$L$254,E$4,'Data - SAP Issues'!$M$4:$M$254,$A13)/E$6 -> 1 | F13: =SUMIFS('Data - SAP Issues'!$F$4:$F$254,'Data - SAP Issues'!$L$4:$L$254,F$4,'Data - SAP Issues'!$M$4:$M$254,$A13)/F$6 -> 1 | G13: =SUMIFS('Data - SAP Issues'!$F$4:$F$254,'Data - SAP Issues'!$L$4:$L$254,G$4,'Data - SAP Issues'!$M$4:$M$254,$A13)/G$6 -> 1.6428571 | H13: =SUMIFS('Data - SAP Issues'!$F$4:$F$254,'Data - SAP Issues'!$L$4:$L$254,H$4,'Data - SAP Issues'!$M$4:$M$254,$A13)/H$6 -> 1.9166667 | I13: =SUMIFS('Data - SAP Issues'!$F$4:$F$254,'Data - SAP Issues'!$L$4:$L$254,I$4,'Data - SAP Issues'!$M$4:$M$254,$A13)/I$6 -> 2.3333333
A14: Stretch film | B14: kg | C14: =SUMIFS('Data - SAP Issues'!$F$4:$F$254,'Data - SAP Issues'!$L$4:$L$254,C$4,'Data - SAP Issues'!$M$4:$M$254,$A14)/C$6 -> 2.16 | D14: =SUMIFS('Data - SAP Issues'!$F$4:$F$254,'Data - SAP Issues'!$L$4:$L$254,D$4,'Data - SAP Issues'!$M$4:$M$254,$A14)/D$6 -> 3.5 | E14: =SUMIFS('Data - SAP Issues'!$F$4:$F$254,'Data - SAP Issues'!$L$4:$L$254,E$4,'Data - SAP Issues'!$M$4:$M$254,$A14)/E$6 -> 3.5222222 | F14: =SUMIFS('Data - SAP Issues'!$F$4:$F$254,'Data - SAP Issues'!$L$4:$L$254,F$4,'Data - SAP Issues'!$M$4:$M$254,$A14)/F$6 -> 2.7571429 | G14: =SUMIFS('Data - SAP Issues'!$F$4:$F$254,'Data - SAP Issues'!$L$4:$L$254,G$4,'Data - SAP Issues'!$M$4:$M$254,$A14)/G$6 -> 4.5714286 | H14: =SUMIFS('Data - SAP Issues'!$F$4:$F$254,'Data - SAP Issues'!$L$4:$L$254,H$4,'Data - SAP Issues'!$M$4:$M$254,$A14)/H$6 -> 5.2833333 | I14: =SUMIFS('Data - SAP Issues'!$F$4:$F$254,'Data - SAP Issues'!$L$4:$L$254,I$4,'Data - SAP Issues'!$M$4:$M$254,$A14)/I$6 -> 7.1
A15: Bubble wrap | B15: roll | C15: =SUMIFS('Data - SAP Issues'!$F$4:$F$254,'Data - SAP Issues'!$L$4:$L$254,C$4,'Data - SAP Issues'!$M$4:$M$254,$A15)/C$6 -> 0.8 | D15: =SUMIFS('Data - SAP Issues'!$F$4:$F$254,'Data - SAP Issues'!$L$4:$L$254,D$4,'Data - SAP Issues'!$M$4:$M$254,$A15)/D$6 -> 1 | E15: =SUMIFS('Data - SAP Issues'!$F$4:$F$254,'Data - SAP Issues'!$L$4:$L$254,E$4,'Data - SAP Issues'!$M$4:$M$254,$A15)/E$6 -> 0.88888889 | F15: =SUMIFS('Data - SAP Issues'!$F$4:$F$254,'Data - SAP Issues'!$L$4:$L$254,F$4,'Data - SAP Issues'!$M$4:$M$254,$A15)/F$6 -> 0.92857143 | G15: =SUMIFS('Data - SAP Issues'!$F$4:$F$254,'Data - SAP Issues'!$L$4:$L$254,G$4,'Data - SAP Issues'!$M$4:$M$254,$A15)/G$6 -> 1.6428571 | H15: =SUMIFS('Data - SAP Issues'!$F$4:$F$254,'Data - SAP Issues'!$L$4:$L$254,H$4,'Data - SAP Issues'!$M$4:$M$254,$A15)/H$6 -> 1.75 | I15: =SUMIFS('Data - SAP Issues'!$F$4:$F$254,'Data - SAP Issues'!$L$4:$L$254,I$4,'Data - SAP Issues'!$M$4:$M$254,$A15)/I$6 -> 3 | K15: 2.0 m: BOM quantity + 1 roll re-wrap after rain
A16: Ply cover | B16: nos | C16: =SUMIFS('Data - SAP Issues'!$F$4:$F$254,'Data - SAP Issues'!$L$4:$L$254,C$4,'Data - SAP Issues'!$M$4:$M$254,$A16)/C$6 -> 5.4 | D16: =SUMIFS('Data - SAP Issues'!$F$4:$F$254,'Data - SAP Issues'!$L$4:$L$254,D$4,'Data - SAP Issues'!$M$4:$M$254,$A16)/D$6 -> 5 | E16: =SUMIFS('Data - SAP Issues'!$F$4:$F$254,'Data - SAP Issues'!$L$4:$L$254,E$4,'Data - SAP Issues'!$M$4:$M$254,$A16)/E$6 -> 5.3333333 | F16: =SUMIFS('Data - SAP Issues'!$F$4:$F$254,'Data - SAP Issues'!$L$4:$L$254,F$4,'Data - SAP Issues'!$M$4:$M$254,$A16)/F$6 -> 0 | G16: =SUMIFS('Data - SAP Issues'!$F$4:$F$254,'Data - SAP Issues'!$L$4:$L$254,G$4,'Data - SAP Issues'!$M$4:$M$254,$A16)/G$6 -> 5.5714286 | H16: =SUMIFS('Data - SAP Issues'!$F$4:$F$254,'Data - SAP Issues'!$L$4:$L$254,H$4,'Data - SAP Issues'!$M$4:$M$254,$A16)/H$6 -> 5.5 | I16: =SUMIFS('Data - SAP Issues'!$F$4:$F$254,'Data - SAP Issues'!$L$4:$L$254,I$4,'Data - SAP Issues'!$M$4:$M$254,$A16)/I$6 -> 5
A17: Tarpaulin | B17: sqft | C17: =SUMIFS('Data - SAP Issues'!$F$4:$F$254,'Data - SAP Issues'!$L$4:$L$254,C$4,'Data - SAP Issues'!$M$4:$M$254,$A17)/C$6 -> 0 | D17: =SUMIFS('Data - SAP Issues'!$F$4:$F$254,'Data - SAP Issues'!$L$4:$L$254,D$4,'Data - SAP Issues'!$M$4:$M$254,$A17)/D$6 -> 0 | E17: =SUMIFS('Data - SAP Issues'!$F$4:$F$254,'Data - SAP Issues'!$L$4:$L$254,E$4,'Data - SAP Issues'!$M$4:$M$254,$A17)/E$6 -> 0 | F17: =SUMIFS('Data - SAP Issues'!$F$4:$F$254,'Data - SAP Issues'!$L$4:$L$254,F$4,'Data - SAP Issues'!$M$4:$M$254,$A17)/F$6 -> 0 | G17: =SUMIFS('Data - SAP Issues'!$F$4:$F$254,'Data - SAP Issues'!$L$4:$L$254,G$4,'Data - SAP Issues'!$M$4:$M$254,$A17)/G$6 -> 542.85714 | H17: =SUMIFS('Data - SAP Issues'!$F$4:$F$254,'Data - SAP Issues'!$L$4:$L$254,H$4,'Data - SAP Issues'!$M$4:$M$254,$A17)/H$6 -> 741.66667 | I17: =SUMIFS('Data - SAP Issues'!$F$4:$F$254,'Data - SAP Issues'!$L$4:$L$254,I$4,'Data - SAP Issues'!$M$4:$M$254,$A17)/I$6 -> 966.66667
A19: B. Standard cost per vessel at current rates (₹)
A20: Timber | C20: =C9*VLOOKUP($A20,Inputs!$A$6:$C$17,3,0) -> 5518.3439 | D20: =D9*VLOOKUP($A20,Inputs!$A$6:$C$17,3,0) -> 6365.5985 | E20: =E9*VLOOKUP($A20,Inputs!$A$6:$C$17,3,0) -> 5966.4337 | F20: =F9*VLOOKUP($A20,Inputs!$A$6:$C$17,3,0) -> 5658.1185 | G20: =G9*VLOOKUP($A20,Inputs!$A$6:$C$17,3,0) -> 12164.5 | H20: =H9*VLOOKUP($A20,Inputs!$A$6:$C$17,3,0) -> 13041.329 | I20: =I9*VLOOKUP($A20,Inputs!$A$6:$C$17,3,0) -> 13074.896
A21: Nails | C21: =C10*VLOOKUP($A21,Inputs!$A$6:$C$17,3,0) -> 118.8 | D21: =D10*VLOOKUP($A21,Inputs!$A$6:$C$17,3,0) -> 165 | E21: =E10*VLOOKUP($A21,Inputs!$A$6:$C$17,3,0) -> 132 | F21: =F10*VLOOKUP($A21,Inputs!$A$6:$C$17,3,0) -> 106.07143 | G21: =G10*VLOOKUP($A21,Inputs!$A$6:$C$17,3,0) -> 240.42857 | H21: =H10*VLOOKUP($A21,Inputs!$A$6:$C$17,3,0) -> 231 | I21: =I10*VLOOKUP($A21,Inputs!$A$6:$C$17,3,0) -> 297
A22: Foam | C22: =C11*VLOOKUP($A22,Inputs!$A$6:$C$17,3,0) -> 1350 | D22: =D11*VLOOKUP($A22,Inputs!$A$6:$C$17,3,0) -> 1500 | E22: =E11*VLOOKUP($A22,Inputs!$A$6:$C$17,3,0) -> 1250 | F22: =F11*VLOOKUP($A22,Inputs!$A$6:$C$17,3,0) -> 1285.7143 | G22: =G11*VLOOKUP($A22,Inputs!$A$6:$C$17,3,0) -> 2250 | H22: =H11*VLOOKUP($A22,Inputs!$A$6:$C$17,3,0) -> 2625 | I22: =I11*VLOOKUP($A22,Inputs!$A$6:$C$17,3,0) -> 3000
A23: Ratchet belt | C23: =C12*VLOOKUP($A23,Inputs!$A$6:$C$17,3,0) -> 2090 | D23: =D12*VLOOKUP($A23,Inputs!$A$6:$C$17,3,0) -> 2216.6667 | E23: =E12*VLOOKUP($A23,Inputs!$A$6:$C$17,3,0) -> 2005.5556 | F23: =F12*VLOOKUP($A23,Inputs!$A$6:$C$17,3,0) -> 2171.4286 | G23: =G12*VLOOKUP($A23,Inputs!$A$6:$C$17,3,0) -> 2917.8571 | H23: =H12*VLOOKUP($A23,Inputs!$A$6:$C$17,3,0) -> 3325 | I23: =I12*VLOOKUP($A23,Inputs!$A$6:$C$17,3,0) -> 3800
A24: Gum tape | C24: =C13*VLOOKUP($A24,Inputs!$A$6:$C$17,3,0) -> 67.2 | D24: =D13*VLOOKUP($A24,Inputs!$A$6:$C$17,3,0) -> 84 | E24: =E13*VLOOKUP($A24,Inputs!$A$6:$C$17,3,0) -> 84 | F24: =F13*VLOOKUP($A24,Inputs!$A$6:$C$17,3,0) -> 84 | G24: =G13*VLOOKUP($A24,Inputs!$A$6:$C$17,3,0) -> 138 | H24: =H13*VLOOKUP($A24,Inputs!$A$6:$C$17,3,0) -> 161 | I24: =I13*VLOOKUP($A24,Inputs!$A$6:$C$17,3,0) -> 196
A25: Stretch film | C25: =C14*VLOOKUP($A25,Inputs!$A$6:$C$17,3,0) -> 362.44068 | D25: =D14*VLOOKUP($A25,Inputs!$A$6:$C$17,3,0) -> 587.28814 | E25: =E14*VLOOKUP($A25,Inputs!$A$6:$C$17,3,0) -> 591.01695 | F25: =F14*VLOOKUP($A25,Inputs!$A$6:$C$17,3,0) -> 462.63923 | G25: =G14*VLOOKUP($A25,Inputs!$A$6:$C$17,3,0) -> 767.07022 | H25: =H14*VLOOKUP($A25,Inputs!$A$6:$C$17,3,0) -> 886.52542 | I25: =I14*VLOOKUP($A25,Inputs!$A$6:$C$17,3,0) -> 1191.3559
A26: Bubble wrap | C26: =C15*VLOOKUP($A26,Inputs!$A$6:$C$17,3,0) -> 568 | D26: =D15*VLOOKUP($A26,Inputs!$A$6:$C$17,3,0) -> 710 | E26: =E15*VLOOKUP($A26,Inputs!$A$6:$C$17,3,0) -> 631.11111 | F26: =F15*VLOOKUP($A26,Inputs!$A$6:$C$17,3,0) -> 659.28571 | G26: =G15*VLOOKUP($A26,Inputs!$A$6:$C$17,3,0) -> 1166.4286 | H26: =H15*VLOOKUP($A26,Inputs!$A$6:$C$17,3,0) -> 1242.5 | I26: =I15*VLOOKUP($A26,Inputs!$A$6:$C$17,3,0) -> 2130
A27: Ply cover | C27: =C16*VLOOKUP($A27,Inputs!$A$6:$C$17,3,0) -> 864 | D27: =D16*VLOOKUP($A27,Inputs!$A$6:$C$17,3,0) -> 800 | E27: =E16*VLOOKUP($A27,Inputs!$A$6:$C$17,3,0) -> 853.33333 | F27: =F16*VLOOKUP($A27,Inputs!$A$6:$C$17,3,0) -> 0 | G27: =G16*VLOOKUP($A27,Inputs!$A$6:$C$17,3,0) -> 891.42857 | H27: =H16*VLOOKUP($A27,Inputs!$A$6:$C$17,3,0) -> 880 | I27: =I16*VLOOKUP($A27,Inputs!$A$6:$C$17,3,0) -> 800
A28: Tarpaulin | C28: =C17*VLOOKUP($A28,Inputs!$A$6:$C$17,3,0) -> 0 | D28: =D17*VLOOKUP($A28,Inputs!$A$6:$C$17,3,0) -> 0 | E28: =E17*VLOOKUP($A28,Inputs!$A$6:$C$17,3,0) -> 0 | F28: =F17*VLOOKUP($A28,Inputs!$A$6:$C$17,3,0) -> 0 | G28: =G17*VLOOKUP($A28,Inputs!$A$6:$C$17,3,0) -> 2714.2857 | H28: =H17*VLOOKUP($A28,Inputs!$A$6:$C$17,3,0) -> 3708.3333 | I28: =I17*VLOOKUP($A28,Inputs!$A$6:$C$17,3,0) -> 4833.3333
A29: Material cost per vessel | C29: =SUM(C20:C28) -> 10938.785 | D29: =SUM(D20:D28) -> 12428.553 | E29: =SUM(E20:E28) -> 11513.451 | F29: =SUM(F20:F28) -> 10427.258 | G29: =SUM(G20:G28) -> 23249.999 | H29: =SUM(H20:H28) -> 26100.688 | I29: =SUM(I20:I28) -> 29322.585
A31: C. Actual vs design BOM - 2.0 m (the one size with a BOM; earlier jobs were packed before it existed)
A32: Item | B32: UoM | C32: Released BOM | D32: Average used | E32: Difference
A33: Timber | B33: cft | C33: =SUM('Data - 2.0m BOM'!H4:H14) -> 6.8479331 | D33: =F9 -> 7.2539981 | E33: =D33-C33 -> 0.406065
A34: Nails | B34: set | C34: ='Data - 2.0m BOM'!D9 -> 1 | D34: =F10 -> 1.0714286 | E34: =D34-C34 -> 0.071428571
A35: Foam | B35: roll | C35: ='Data - 2.0m BOM'!D10 -> 0.5 | D35: =F11 -> 0.57142857 | E35: =D35-C35 -> 0.071428571
A36: Ratchet belt | B36: nos | C36: ='Data - 2.0m BOM'!D11 -> 2 | D36: =F12 -> 2.2857143 | E36: =D36-C36 -> 0.28571429
A37: Gum tape | B37: roll | C37: ='Data - 2.0m BOM'!D12 -> 0.833 | D37: =F13 -> 1 | E37: =D37-C37 -> 0.167
A38: Stretch film | B38: kg | C38: ='Data - 2.0m BOM'!D13 -> 2.333 | D38: =F14 -> 2.7571429 | E38: =D38-C38 -> 0.42414286
A39: Bubble wrap | B39: roll | C39: ='Data - 2.0m BOM'!D14 -> 0.833 | D39: =F15 -> 0.92857143 | E39: =D39-C39 -> 0.095571429
A41: D. Draft BOM for release - timber pieces per vessel, by size
A42: Item | B42: Size (mm) | C42: Avg pieces / vsl | D42: Proposed pieces / vsl
A43: WOODEN BATTEN 100 X 100 X 900 LG | B43: 1400 | C43: =SUMIFS('Data - SAP Issues'!$F$4:$F$254,'Data - SAP Issues'!$L$4:$L$254,B43,'Data - SAP Issues'!$E$4:$E$254,A43)/SUMIFS('Job Costing'!$C$5:$C$23,'Job Costing'!$B$5:$B$23,B43) -> 5 | D43: =ROUND(C43,0) -> 5
A44: WOODEN BATTEN 100 X 75 X 100 LG | B44: 1400 | C44: =SUMIFS('Data - SAP Issues'!$F$4:$F$254,'Data - SAP Issues'!$L$4:$L$254,B44,'Data - SAP Issues'!$E$4:$E$254,A44)/SUMIFS('Job Costing'!$C$5:$C$23,'Job Costing'!$B$5:$B$23,B44) -> 4.2 | D44: =ROUND(C44,0) -> 4
A45: WOODEN BATTEN 150 X 150 X 300 LG | B45: 1400 | C45: =SUMIFS('Data - SAP Issues'!$F$4:$F$254,'Data - SAP Issues'!$L$4:$L$254,B45,'Data - SAP Issues'!$E$4:$E$254,A45)/SUMIFS('Job Costing'!$C$5:$C$23,'Job Costing'!$B$5:$B$23,B45) -> 4.2 | D45: =ROUND(C45,0) -> 4
A46: WOODEN BATTEN 150 X 75 X 2550 LG | B46: 1400 | C46: =SUMIFS('Data - SAP Issues'!$F$4:$F$254,'Data - SAP Issues'!$L$4:$L$254,B46,'Data - SAP Issues'!$E$4:$E$254,A46)/SUMIFS('Job Costing'!$C$5:$C$23,'Job Costing'!$B$5:$B$23,B46) -> 3.4 | D46: =ROUND(C46,0) -> 3
A47: WOODEN BATTEN 150 X 75 X 900 LG | B47: 1400 | C47: =SUMIFS('Data - SAP Issues'!$F$4:$F$254,'Data - SAP Issues'!$L$4:$L$254,B47,'Data - SAP Issues'!$E$4:$E$254,A47)/SUMIFS('Job Costing'!$C$5:$C$23,'Job Costing'!$B$5:$B$23,B47) -> 2.6 | D47: =ROUND(C47,0) -> 3
A48: WOODEN BATTEN 100 X 100 X 1050 LG | B48: 1600 | C48: =SUMIFS('Data - SAP Issues'!$F$4:$F$254,'Data - SAP Issues'!$L$4:$L$254,B48,'Data - SAP Issues'!$E$4:$E$254,A48)/SUMIFS('Job Costing'!$C$5:$C$23,'Job Costing'!$B$5:$B$23,B48) -> 5 | D48: =ROUND(C48,0) -> 5
A49: WOODEN BATTEN 100 X 75 X 100 LG | B49: 1600 | C49: =SUMIFS('Data - SAP Issues'!$F$4:$F$254,'Data - SAP Issues'!$L$4:$L$254,B49,'Data - SAP Issues'!$E$4:$E$254,A49)/SUMIFS('Job Costing'!$C$5:$C$23,'Job Costing'!$B$5:$B$23,B49) -> 5.6666667 | D49: =ROUND(C49,0) -> 6
A50: WOODEN BATTEN 150 X 150 X 300 LG | B50: 1600 | C50: =SUMIFS('Data - SAP Issues'!$F$4:$F$254,'Data - SAP Issues'!$L$4:$L$254,B50,'Data - SAP Issues'!$E$4:$E$254,A50)/SUMIFS('Job Costing'!$C$5:$C$23,'Job Costing'!$B$5:$B$23,B50) -> 4.6666667 | D50: =ROUND(C50,0) -> 5
A51: WOODEN BATTEN 150 X 75 X 1050 LG | B51: 1600 | C51: =SUMIFS('Data - SAP Issues'!$F$4:$F$254,'Data - SAP Issues'!$L$4:$L$254,B51,'Data - SAP Issues'!$E$4:$E$254,A51)/SUMIFS('Job Costing'!$C$5:$C$23,'Job Costing'!$B$5:$B$23,B51) -> 2 | D51: =ROUND(C51,0) -> 2
A52: WOODEN BATTEN 150 X 75 X 2650 LG | B52: 1600 | C52: =SUMIFS('Data - SAP Issues'!$F$4:$F$254,'Data - SAP Issues'!$L$4:$L$254,B52,'Data - SAP Issues'!$E$4:$E$254,A52)/SUMIFS('Job Costing'!$C$5:$C$23,'Job Costing'!$B$5:$B$23,B52) -> 4 | D52: =ROUND(C52,0) -> 4
A53: WOODEN BATTEN 100 X 100 X 1150 LG | B53: 1800 | C53: =SUMIFS('Data - SAP Issues'!$F$4:$F$254,'Data - SAP Issues'!$L$4:$L$254,B53,'Data - SAP Issues'!$E$4:$E$254,A53)/SUMIFS('Job Costing'!$C$5:$C$23,'Job Costing'!$B$5:$B$23,B53) -> 3.7777778 | D53: =ROUND(C53,0) -> 4
A54: WOODEN BATTEN 100 X 75 X 100 LG | B54: 1800 | C54: =SUMIFS('Data - SAP Issues'!$F$4:$F$254,'Data - SAP Issues'!$L$4:$L$254,B54,'Data - SAP Issues'!$E$4:$E$254,A54)/SUMIFS('Job Costing'!$C$5:$C$23,'Job Costing'!$B$5:$B$23,B54) -> 3.6666667 | D54: =ROUND(C54,0) -> 4
... A77: WOODEN BATTEN 200 X 200 X 400 LG | B77: 3000 | C77: =SUMIFS('Data - SAP Issues'!$F$4:$F$254,'Data - SAP Issues'!$L$4:$L$254,B77,'Data - SAP Issues'!$E$4:$E$254,A77)/SUMIFS('Job Costing'!$C$5:$C$23,'Job Costing'!$B$5:$B$23,B77) -> 5.6666667 | D77: =ROUND(C77,0) -> 6
A79: Proposed pieces = average rounded. For flat-rack sizes (2.4 m+) the saddles are heavier (200 x 200) - production to confirm.

Sheet Size Model
A1: Size model - in-house vs outsourcing, per vessel at current rates
A2: Vessels per shipment from the Dashboard. Proposed standard from 'Proposed Std'.
A4: Size (mm) | C4: 1400 | D4: 1600 | E4: 1800 | F4: 2000 | G4: 2400 | H4: 2600 | I4: 3000
A5: Ship mode | C5: =VLOOKUP(C$4,Inputs!$A$54:$L$60,11,0) -> 40HC | D5: =VLOOKUP(D$4,Inputs!$A$54:$L$60,11,0) -> 40HC | E5: =VLOOKUP(E$4,Inputs!$A$54:$L$60,11,0) -> 40HC | F5: =VLOOKUP(F$4,Inputs!$A$54:$L$60,11,0) -> 40HC | G5: =VLOOKUP(G$4,Inputs!$A$54:$L$60,11,0) -> Flat rack | H5: =VLOOKUP(H$4,Inputs!$A$54:$L$60,11,0) -> Flat rack | I5: =VLOOKUP(I$4,Inputs!$A$54:$L$60,11,0) -> Flat rack
A6: Vessels per 40HC container | C6: =VLOOKUP(C$4,Inputs!$A$54:$L$60,12,0) -> 3 | D6: =VLOOKUP(D$4,Inputs!$A$54:$L$60,12,0) -> 3 | E6: =VLOOKUP(E$4,Inputs!$A$54:$L$60,12,0) -> 3 | F6: =VLOOKUP(F$4,Inputs!$A$54:$L$60,12,0) -> 3 | G6: =VLOOKUP(G$4,Inputs!$A$54:$L$60,12,0) -> - | H6: =VLOOKUP(H$4,Inputs!$A$54:$L$60,12,0) -> - | I6: =VLOOKUP(I$4,Inputs!$A$54:$L$60,12,0) -> -
A7: Per vessel - proposed standard, current rates
A8: Timber ₹ | C8: ='Proposed Std'!C20 -> 5518.3439 | D8: ='Proposed Std'!D20 -> 6365.5985 | E8: ='Proposed Std'!E20 -> 5966.4337 | F8: ='Proposed Std'!F20 -> 5658.1185 | G8: ='Proposed Std'!G20 -> 12164.5 | H8: ='Proposed Std'!H20 -> 13041.329 | I8: ='Proposed Std'!I20 -> 13074.896
A9: Consumables ₹ | C9: ='Proposed Std'!C29-'Proposed Std'!C20 -> 5420.4407 | D9: ='Proposed Std'!D29-'Proposed Std'!D20 -> 6062.9548 | E9: ='Proposed Std'!E29-'Proposed Std'!E20 -> 5547.0169 | F9: ='Proposed Std'!F29-'Proposed Std'!F20 -> 4769.1392 | G9: ='Proposed Std'!G29-'Proposed Std'!G20 -> 11085.499 | H9: ='Proposed Std'!H29-'Proposed Std'!H20 -> 13059.359 | I9: ='Proposed Std'!I29-'Proposed Std'!I20 -> 16247.689
A10: of which nails ₹ | C10: ='Proposed Std'!C21 -> 118.8 | D10: ='Proposed Std'!D21 -> 165 | E10: ='Proposed Std'!E21 -> 132 | F10: ='Proposed Std'!F21 -> 106.07143 | G10: ='Proposed Std'!G21 -> 240.42857 | H10: ='Proposed Std'!H21 -> 231 | I10: ='Proposed Std'!I21 -> 297
A11: Material ₹ | C11: =C8+C9 -> 10938.785 | D11: =D8+D9 -> 12428.553 | E11: =E8+E9 -> 11513.451 | F11: =F8+F9 -> 10427.258 | G11: =G8+G9 -> 23249.999 | H11: =H8+H9 -> 26100.688 | I11: =I8+I9 -> 29322.585
A12: Mistri hrs per vessel | C12: =AVERAGEIFS('Job Costing'!$M$5:$M$23,'Job Costing'!$B$5:$B$23,C$4) -> 3.5 | D12: =AVERAGEIFS('Job Costing'!$M$5:$M$23,'Job Costing'!$B$5:$B$23,D$4) -> 4.625 | E12: =AVERAGEIFS('Job Costing'!$M$5:$M$23,'Job Costing'!$B$5:$B$23,E$4) -> 4.75 | F12: =AVERAGEIFS('Job Costing'!$M$5:$M$23,'Job Costing'!$B$5:$B$23,F$4) -> 3.75 | G12: =AVERAGEIFS('Job Costing'!$M$5:$M$23,'Job Costing'!$B$5:$B$23,G$4) -> 9.8166667 | H12: =AVERAGEIFS('Job Costing'!$M$5:$M$23,'Job Costing'!$B$5:$B$23,H$4) -> 8.875 | I12: =AVERAGEIFS('Job Costing'!$M$5:$M$23,'Job Costing'!$B$5:$B$23,I$4) -> 10.666667 | K12: average of jobs with a labour record
A13: Jogali hrs per vessel | C13: =AVERAGEIFS('Job Costing'!$N$5:$N$23,'Job Costing'!$B$5:$B$23,C$4) -> 8.8333333 | D13: =AVERAGEIFS('Job Costing'!$N$5:$N$23,'Job Costing'!$B$5:$B$23,D$4) -> 9.625 | E13: =AVERAGEIFS('Job Costing'!$N$5:$N$23,'Job Costing'!$B$5:$B$23,E$4) -> 10.125 | F13: =AVERAGEIFS('Job Costing'!$N$5:$N$23,'Job Costing'!$B$5:$B$23,F$4) -> 9.5166667 | G13: =AVERAGEIFS('Job Costing'!$N$5:$N$23,'Job Costing'!$B$5:$B$23,G$4) -> 18.95 | H13: =AVERAGEIFS('Job Costing'!$N$5:$N$23,'Job Costing'!$B$5:$B$23,H$4) -> 20.520833 | I13: =AVERAGEIFS('Job Costing'!$N$5:$N$23,'Job Costing'!$B$5:$B$23,I$4) -> 24
A14: Labour ₹ | C14: =(C12*Inputs!$C$16+C13*Inputs!$C$17)/Inputs!$C$21*(1+Inputs!$C$20) -> 968 | D14: =(D12*Inputs!$C$16+D13*Inputs!$C$17)/Inputs!$C$21*(1+Inputs!$C$20) -> 1144 | E14: =(E12*Inputs!$C$16+E13*Inputs!$C$17)/Inputs!$C$21*(1+Inputs!$C$20) -> 1190.75 | F14: =(F12*Inputs!$C$16+F13*Inputs!$C$17)/Inputs!$C$21*(1+Inputs!$C$20) -> 1040.6 | G14: =(G12*Inputs!$C$16+G13*Inputs!$C$17)/Inputs!$C$21*(1+Inputs!$C$20) -> 2330.5333 | H14: =(H12*Inputs!$C$16+H13*Inputs!$C$17)/Inputs!$C$21*(1+Inputs!$C$20) -> 2330.625 | I14: =(I12*Inputs!$C$16+I13*Inputs!$C$17)/Inputs!$C$21*(1+Inputs!$C$20) -> 2757.3333
A15: of which wrapping (jogali) ₹ | C15: =C13*Inputs!$C$17/Inputs!$C$21*(1+Inputs!$C$20) -> 583 | D15: =D13*Inputs!$C$17/Inputs!$C$21*(1+Inputs!$C$20) -> 635.25 | E15: =E13*Inputs!$C$17/Inputs!$C$21*(1+Inputs!$C$20) -> 668.25 | F15: =F13*Inputs!$C$17/Inputs!$C$21*(1+Inputs!$C$20) -> 628.1 | G15: =G13*Inputs!$C$17/Inputs!$C$21*(1+Inputs!$C$20) -> 1250.7 | H15: =H13*Inputs!$C$17/Inputs!$C$21*(1+Inputs!$C$20) -> 1354.375 | I15: =I13*Inputs!$C$17/Inputs!$C$21*(1+Inputs!$C$20) -> 1584
A16: Per shipment
A17: Vessels per shipment | C17: =Dashboard!$D$7 -> 4 | D17: =Dashboard!$D$7 -> 4 | E17: =Dashboard!$D$7 -> 4 | F17: =Dashboard!$D$7 -> 4 | G17: =Dashboard!$D$7 -> 4 | H17: =Dashboard!$D$7 -> 4 | I17: =Dashboard!$D$7 -> 4
A18: Fumigation per shipment ₹ | C18: =IF(C5="40HC",ROUNDUP(C17/C6,0)*Inputs!$C$15,0) -> 7000 | D18: =IF(D5="40HC",ROUNDUP(D17/D6,0)*Inputs!$C$15,0) -> 7000 | E18: =IF(E5="40HC",ROUNDUP(E17/E6,0)*Inputs!$C$15,0) -> 7000 | F18: =IF(F5="40HC",ROUNDUP(F17/F6,0)*Inputs!$C$15,0) -> 7000 | G18: =IF(G5="40HC",ROUNDUP(G17/G6,0)*Inputs!$C$15,0) -> 0 | H18: =IF(H5="40HC",ROUNDUP(H17/H6,0)*Inputs!$C$15,0) -> 0 | I18: =IF(I5="40HC",ROUNDUP(I17/I6,0)*Inputs!$C$15,0) -> 0
A19: Supervision + marking per shipment ₹ | C19: =Inputs!$C$22 -> 1025 | D19: =Inputs!$C$22 -> 1025 | E19: =Inputs!$C$22 -> 1025 | F19: =Inputs!$C$22 -> 1025 | G19: =Inputs!$C$22 -> 1025 | H19: =Inputs!$C$22 -> 1025 | I19: =Inputs!$C$22 -> 1025
A20: Fixed cost per vessel ₹ | C20: =(C18+C19)/C17 -> 2006.25 | D20: =(D18+D19)/D17 -> 2006.25 | E20: =(E18+E19)/E17 -> 2006.25 | F20: =(F18+F19)/F17 -> 2006.25 | G20: =(G18+G19)/G17 -> 256.25 | H20: =(H18+H19)/H17 -> 256.25 | I20: =(I18+I19)/I17 -> 256.25
A21: In-house
A22: Cash cost per vessel | C22: =C11+C14+C20 -> 13913.035 | D22: =D11+D14+D20 -> 15578.803 | E22: =E11+E14+E20 -> 14710.451 | F22: =F11+F14+F20 -> 13474.108 | G22: =G11+G14+G20 -> 25836.782 | H22: =H11+H14+H20 -> 28687.563 | I22: =I11+I14+I20 -> 32336.168
A23: Packing-bay days per shipment | C23: =ROUNDUP(C17*(C12+C13)/Inputs!$C$23,0) -> 3 | D23: =ROUNDUP(D17*(D12+D13)/Inputs!$C$23,0) -> 3 | E23: =ROUNDUP(E17*(E12+E13)/Inputs!$C$23,0) -> 3 | F23: =ROUNDUP(F17*(F12+F13)/Inputs!$C$23,0) -> 3 | G23: =ROUNDUP(G17*(G12+G13)/Inputs!$C$23,0) -> 5 | H23: =ROUNDUP(H17*(H12+H13)/Inputs!$C$23,0) -> 5 | I23: =ROUNDUP(I17*(I12+I13)/Inputs!$C$23,0) -> 6
A24: Total per vessel (incl. bay value) | C24: =C22+C23*Inputs!$C$26/C17 -> 13913.035 | D24: =D22+D23*Inputs!$C$26/D17 -> 15578.803 | E24: =E22+E23*Inputs!$C$26/E17 -> 14710.451 | F24: =F22+F23*Inputs!$C$26/F17 -> 13474.108 | G24: =G22+G23*Inputs!$C$26/G17 -> 25836.782 | H24: =H22+H23*Inputs!$C$26/H17 -> 28687.563 | I24: =I22+I23*Inputs!$C$26/I17 -> 32336.168
A25: PK-A - contractor labour only (our material)
A26: Quote per vessel | C26: =VLOOKUP(C$4,Inputs!$A$41:$D$47,2,0) -> 800 | D26: =VLOOKUP(D$4,Inputs!$A$41:$D$47,2,0) -> 900 | E26: =VLOOKUP(E$4,Inputs!$A$41:$D$47,2,0) -> 1100 | F26: =VLOOKUP(F$4,Inputs!$A$41:$D$47,2,0) -> 1000 | G26: =VLOOKUP(G$4,Inputs!$A$41:$D$47,2,0) -> 2200 | H26: =VLOOKUP(H$4,Inputs!$A$41:$D$47,2,0) -> 2300 | I26: =VLOOKUP(I$4,Inputs!$A$41:$D$47,2,0) -> 2700
A27: Cash cost per vessel | C27: =C11+C26+Inputs!$C$48/C17+C20 -> 14370.035 | D27: =D11+D26+Inputs!$C$48/D17+D20 -> 15959.803 | E27: =E11+E26+Inputs!$C$48/E17+E20 -> 15244.701 | F27: =F11+F26+Inputs!$C$48/F17+F20 -> 14058.508 | G27: =G11+G26+Inputs!$C$48/G17+G20 -> 26331.249 | H27: =H11+H26+Inputs!$C$48/H17+H20 -> 29281.938 | I27: =I11+I26+Inputs!$C$48/I17+I20 -> 32903.835
A28: Total per vessel (incl. bay value) | C28: =C27+C23*Inputs!$C$26/C17 -> 14370.035 | D28: =D27+D23*Inputs!$C$26/D17 -> 15959.803 | E28: =E27+E23*Inputs!$C$26/E17 -> 15244.701 | F28: =F27+F23*Inputs!$C$26/F17 -> 14058.508 | G28: =G27+G23*Inputs!$C$26/G17 -> 26331.249 | H28: =H27+H23*Inputs!$C$26/H17 -> 29281.938 | I28: =I27+I23*Inputs!$C$26/I17 -> 32903.835
A29: PK-B - buy ready-made skids, we wrap
A30: Skid quote per vessel | C30: =VLOOKUP(C$4,Inputs!$A$41:$D$47,3,0) -> 6400 | D30: =VLOOKUP(D$4,Inputs!$A$41:$D$47,3,0) -> 6850 | E30: =VLOOKUP(E$4,Inputs!$A$41:$D$47,3,0) -> 7350 | F30: =VLOOKUP(F$4,Inputs!$A$41:$D$47,3,0) -> 7200 | G30: =VLOOKUP(G$4,Inputs!$A$41:$D$47,3,0) -> 15050 | H30: =VLOOKUP(H$4,Inputs!$A$41:$D$47,3,0) -> 15900 | I30: =VLOOKUP(I$4,Inputs!$A$41:$D$47,3,0) -> 17350
A31: Cash cost per vessel | C31: =C30+C9-C10+C15+ROUNDUP(C17/Inputs!$C$25,0)*Inputs!$C$49/C17+C20 -> 15190.891 | D31: =D30+D9-D10+D15+ROUNDUP(D17/Inputs!$C$25,0)*Inputs!$C$49/D17+D20 -> 16289.455 | E31: =E30+E9-E10+E15+ROUNDUP(E17/Inputs!$C$25,0)*Inputs!$C$49/E17+E20 -> 16339.517 | F31: =F30+F9-F10+F15+ROUNDUP(F17/Inputs!$C$25,0)*Inputs!$C$49/F17+F20 -> 15397.418 | G31: =G30+G9-G10+G15+ROUNDUP(G17/Inputs!$C$25,0)*Inputs!$C$49/G17+G20 -> 28302.02 | H31: =H30+H9-H10+H15+ROUNDUP(H17/Inputs!$C$25,0)*Inputs!$C$49/H17+H20 -> 31238.984 | I31: =I30+I9-I10+I15+ROUNDUP(I17/Inputs!$C$25,0)*Inputs!$C$49/I17+I20 -> 36040.939
A32: Packing-bay days per shipment | C32: =ROUNDUP(C17*C13/Inputs!$C$23,0) -> 2 | D32: =ROUNDUP(D17*D13/Inputs!$C$23,0) -> 2 | E32: =ROUNDUP(E17*E13/Inputs!$C$23,0) -> 2 | F32: =ROUNDUP(F17*F13/Inputs!$C$23,0) -> 2 | G32: =ROUNDUP(G17*G13/Inputs!$C$23,0) -> 4 | H32: =ROUNDUP(H17*H13/Inputs!$C$23,0) -> 4 | I32: =ROUNDUP(I17*I13/Inputs!$C$23,0) -> 4 | K32: only wrapping happens in our bay
A33: Total per vessel (incl. bay value) | C33: =C31+C32*Inputs!$C$26/C17 -> 15190.891 | D33: =D31+D32*Inputs!$C$26/D17 -> 16289.455 | E33: =E31+E32*Inputs!$C$26/E17 -> 16339.517 | F33: =F31+F32*Inputs!$C$26/F17 -> 15397.418 | G33: =G31+G32*Inputs!$C$26/G17 -> 28302.02 | H33: =H31+H32*Inputs!$C$26/H17 -> 31238.984 | I33: =I31+I32*Inputs!$C$26/I17 -> 36040.939
A34: PK-C - turnkey packer (their crew, our bay)
A35: Quote per vessel | C35: =VLOOKUP(C$4,Inputs!$A$41:$D$47,4,0) -> NQ = not quoted (PK-C does not take jobs below 1.8 m) | D35: =VLOOKUP(D$4,Inputs!$A$41:$D$47,4,0) -> NQ | E35: =VLOOKUP(E$4,Inputs!$A$41:$D$47,4,0) -> 15000 | F35: =VLOOKUP(F$4,Inputs!$A$41:$D$47,4,0) -> 14000 | G35: =VLOOKUP(G$4,Inputs!$A$41:$D$47,4,0) -> 31000 | H35: =VLOOKUP(H$4,Inputs!$A$41:$D$47,4,0) -> 33000 | I35: =VLOOKUP(I$4,Inputs!$A$41:$D$47,4,0) -> 37500
A36: Cash cost per vessel | C36: =IF(ISNUMBER(C35),C35+Inputs!$C$50/C17+C20,"NQ") -> NQ | D36: =IF(ISNUMBER(D35),D35+Inputs!$C$50/D17+D20,"NQ") -> NQ | E36: =IF(ISNUMBER(E35),E35+Inputs!$C$50/E17+E20,"NQ") -> 18881.25 | F36: =IF(ISNUMBER(F35),F35+Inputs!$C$50/F17+F20,"NQ") -> 17881.25 | G36: =IF(ISNUMBER(G35),G35+Inputs!$C$50/G17+G20,"NQ") -> 33131.25 | H36: =IF(ISNUMBER(H35),H35+Inputs!$C$50/H17+H20,"NQ") -> 35131.25 | I36: =IF(ISNUMBER(I35),I35+Inputs!$C$50/I17+I20,"NQ") -> 39631.25
A37: Packing-bay days per shipment | C37: =IF(ISNUMBER(C35),ROUNDUP(C17*(C12+C13)/Inputs!$C$24,0),"NQ") -> NQ | D37: =IF(ISNUMBER(D35),ROUNDUP(D17*(D12+D13)/Inputs!$C$24,0),"NQ") -> NQ | E37: =IF(ISNUMBER(E35),ROUNDUP(E17*(E12+E13)/Inputs!$C$24,0),"NQ") -> 2 | F37: =IF(ISNUMBER(F35),ROUNDUP(F17*(F12+F13)/Inputs!$C$24,0),"NQ") -> 2 | G37: =IF(ISNUMBER(G35),ROUNDUP(G17*(G12+G13)/Inputs!$C$24,0),"NQ") -> 3 | H37: =IF(ISNUMBER(H35),ROUNDUP(H17*(H12+H13)/Inputs!$C$24,0),"NQ") -> 3 | I37: =IF(ISNUMBER(I35),ROUNDUP(I17*(I12+I13)/Inputs!$C$24,0),"NQ") -> 4
A38: Total per vessel (incl. bay value) | C38: =IF(ISNUMBER(C35),C36+C37*Inputs!$C$26/C17,"NQ") -> NQ | D38: =IF(ISNUMBER(D35),D36+D37*Inputs!$C$26/D17,"NQ") -> NQ | E38: =IF(ISNUMBER(E35),E36+E37*Inputs!$C$26/E17,"NQ") -> 18881.25 | F38: =IF(ISNUMBER(F35),F36+F37*Inputs!$C$26/F17,"NQ") -> 17881.25 | G38: =IF(ISNUMBER(G35),G36+G37*Inputs!$C$26/G17,"NQ") -> 33131.25 | H38: =IF(ISNUMBER(H35),H36+H37*Inputs!$C$26/H17,"NQ") -> 35131.25 | I38: =IF(ISNUMBER(I35),I36+I37*Inputs!$C$26/I17,"NQ") -> 39631.25
A39: Decision
A40: Lowest cost per vessel | C40: =MIN(C24,C28,C33,C38) -> 13913.035 | D40: =MIN(D24,D28,D33,D38) -> 15578.803 | E40: =MIN(E24,E28,E33,E38) -> 14710.451 | F40: =MIN(F24,F28,F33,F38) -> 13474.108 | G40: =MIN(G24,G28,G33,G38) -> 25836.782 | H40: =MIN(H24,H28,H33,H38) -> 28687.563 | I40: =MIN(I24,I28,I33,I38) -> 32336.168 | K40: MIN skips NQ
A41: Cheapest option | C41: =IF(C40=C24,"In-house",IF(C40=C33,"Buy skids (PK-B)",IF(C40=C38,"Turnkey (PK-C)","Contractor (PK-A)"))) -> In-house | D41: =IF(D40=D24,"In-house",IF(D40=D33,"Buy skids (PK-B)",IF(D40=D38,"Turnkey (PK-C)","Contractor (PK-A)"))) -> In-house | E41: =IF(E40=E24,"In-house",IF(E40=E33,"Buy skids (PK-B)",IF(E40=E38,"Turnkey (PK-C)","Contractor (PK-A)"))) -> In-house | F41: =IF(F40=F24,"In-house",IF(F40=F33,"Buy skids (PK-B)",IF(F40=F38,"Turnkey (PK-C)","Contractor (PK-A)"))) -> In-house | G41: =IF(G40=G24,"In-house",IF(G40=G33,"Buy skids (PK-B)",IF(G40=G38,"Turnkey (PK-C)","Contractor (PK-A)"))) -> In-house | H41: =IF(H40=H24,"In-house",IF(H40=H33,"Buy skids (PK-B)",IF(H40=H38,"Turnkey (PK-C)","Contractor (PK-A)"))) -> In-house | I41: =IF(I40=I24,"In-house",IF(I40=I33,"Buy skids (PK-B)",IF(I40=I38,"Turnkey (PK-C)","Contractor (PK-A)"))) -> In-house
A42: Bay-day value at which buying skids pays ₹ | C42: =IF(C23>C32,(C31-C22)*C17/(C23-C32),"never") -> 5111.4244 | D42: =IF(D23>D32,(D31-D22)*D17/(D23-D32),"never") -> 2842.6059 | E42: =IF(E23>E32,(E31-E22)*E17/(E23-E32),"never") -> 6516.2653 | F42: =IF(F23>F32,(F31-F22)*F17/(F23-F32),"never") -> 7693.2401 | G42: =IF(G23>G32,(G31-G22)*G17/(G23-G32),"never") -> 9860.9527 | H42: =IF(H23>H32,(H31-H22)*H17/(H23-H32),"never") -> 10205.683 | I42: =IF(I23>I32,(I31-I22)*I17/(I23-I32),"never") -> 7409.5418 | K42: extra cash per shipment / bay-days saved
A43: Turnkey quote vs our own cost (x) | C43: =IF(ISNUMBER(C35),C35/(C11+C14),"NQ") -> NQ | D43: =IF(ISNUMBER(D35),D35/(D11+D14),"NQ") -> NQ | E43: =IF(ISNUMBER(E35),E35/(E11+E14),"NQ") -> 1.1807118 | F43: =IF(ISNUMBER(F35),F35/(F11+F14),"NQ") -> 1.2208034 | G43: =IF(ISNUMBER(G35),G35/(G11+G14),"NQ") -> 1.2118591 | H43: =IF(ISNUMBER(H35),H35/(H11+H14),"NQ") -> 1.1606921 | I43: =IF(ISNUMBER(I35),I35/(I11+I14),"NQ") -> 1.1689556
A44: History and billed charge
A45: Actual cost per vessel (job history) | B45: Actual (history) | C45: =SUMIFS('Job Costing'!$X$5:$X$23,'Job Costing'!$B$5:$B$23,C$4)/SUMIFS('Job Costing'!$C$5:$C$23,'Job Costing'!$B$5:$B$23,C$4) -> 12744.781 | D45: =SUMIFS('Job Costing'!$X$5:$X$23,'Job Costing'!$B$5:$B$23,D$4)/SUMIFS('Job Costing'!$C$5:$C$23,'Job Costing'!$B$5:$B$23,D$4) -> 15620.533 | E45: =SUMIFS('Job Costing'!$X$5:$X$23,'Job Costing'!$B$5:$B$23,E$4)/SUMIFS('Job Costing'!$C$5:$C$23,'Job Costing'!$B$5:$B$23,E$4) -> 13641.552 | F45: =SUMIFS('Job Costing'!$X$5:$X$23,'Job Costing'!$B$5:$B$23,F$4)/SUMIFS('Job Costing'!$C$5:$C$23,'Job Costing'!$B$5:$B$23,F$4) -> 12395.676 | G45: =SUMIFS('Job Costing'!$X$5:$X$23,'Job Costing'!$B$5:$B$23,G$4)/SUMIFS('Job Costing'!$C$5:$C$23,'Job Costing'!$B$5:$B$23,G$4) -> 24341.999 | H45: =SUMIFS('Job Costing'!$X$5:$X$23,'Job Costing'!$B$5:$B$23,H$4)/SUMIFS('Job Costing'!$C$5:$C$23,'Job Costing'!$B$5:$B$23,H$4) -> 27468.201 | I45: =SUMIFS('Job Costing'!$X$5:$X$23,'Job Costing'!$B$5:$B$23,I$4)/SUMIFS('Job Costing'!$C$5:$C$23,'Job Costing'!$B$5:$B$23,I$4) -> 31278.682
A46: Billed packaging USD per vessel (illustrative) | C46: =IFERROR(VLOOKUP(C$4,Inputs!$A$91:$B$92,2,0)*Inputs!$C$93/100,"") | D46: =IFERROR(VLOOKUP(D$4,Inputs!$A$91:$B$92,2,0)*Inputs!$C$93/100,"") | E46: =IFERROR(VLOOKUP(E$4,Inputs!$A$91:$B$92,2,0)*Inputs!$C$93/100,"") | F46: =IFERROR(VLOOKUP(F$4,Inputs!$A$91:$B$92,2,0)*Inputs!$C$93/100,"") | G46: =IFERROR(VLOOKUP(G$4,Inputs!$A$91:$B$92,2,0)*Inputs!$C$93/100,"") -> 600 | H46: =IFERROR(VLOOKUP(H$4,Inputs!$A$91:$B$92,2,0)*Inputs!$C$93/100,"") -> 636 | I46: =IFERROR(VLOOKUP(I$4,Inputs!$A$91:$B$92,2,0)*Inputs!$C$93/100,"")
A47: Billed ₹ at today's USD-INR | C47: =IF(C46="","",C46*Inputs!$C$88) | D47: =IF(D46="","",D46*Inputs!$C$88) | E47: =IF(E46="","",E46*Inputs!$C$88) | F47: =IF(F46="","",F46*Inputs!$C$88) | G47: =IF(G46="","",G46*Inputs!$C$88) -> 57534 | H47: =IF(H46="","",H46*Inputs!$C$88) -> 60986.04 | I47: =IF(I46="","",I46*Inputs!$C$88)
A48: Margin per vessel ₹ | C48: =IF(C46="","",C47-C22) | D48: =IF(D46="","",D47-D22) | E48: =IF(E46="","",E47-E22) | F48: =IF(F46="","",F47-F22) | G48: =IF(G46="","",G47-G22) -> 31697.218 | H48: =IF(H46="","",H47-H22) -> 32298.477 | I48: =IF(I46="","",I47-I22)
A50: Chart data (Dashboard)
B51: Timber | C51: =C8 -> 5518.3439 | D51: =D8 -> 6365.5985 | E51: =E8 -> 5966.4337 | F51: =F8 -> 5658.1185 | G51: =G8 -> 12164.5 | H51: =H8 -> 13041.329 | I51: =I8 -> 13074.896
B52: Consumables | C52: =C9 -> 5420.4407 | D52: =D9 -> 6062.9548 | E52: =E9 -> 5547.0169 | F52: =F9 -> 4769.1392 | G52: =G9 -> 11085.499 | H52: =H9 -> 13059.359 | I52: =I9 -> 16247.689
B53: Labour | C53: =C14 -> 968 | D53: =D14 -> 1144 | E53: =E14 -> 1190.75 | F53: =F14 -> 1040.6 | G53: =G14 -> 2330.5333 | H53: =H14 -> 2330.625 | I53: =I14 -> 2757.3333
B54: Fumigation + supervision | C54: =C20 -> 2006.25 | D54: =D20 -> 2006.25 | E54: =E20 -> 2006.25 | F54: =F20 -> 2006.25 | G54: =G20 -> 256.25 | H54: =H20 -> 256.25 | I54: =I20 -> 256.25
B56: In-house | C56: =C24 -> 13913.035 | D56: =D24 -> 15578.803 | E56: =E24 -> 14710.451 | F56: =F24 -> 13474.108 | G56: =G24 -> 25836.782 | H56: =H24 -> 28687.563 | I56: =I24 -> 32336.168
B57: Contractor labour (PK-A) | C57: =C28 -> 14370.035 | D57: =D28 -> 15959.803 | E57: =E28 -> 15244.701 | F57: =F28 -> 14058.508 | G57: =G28 -> 26331.249 | H57: =H28 -> 29281.938 | I57: =I28 -> 32903.835
B58: Buy skids (PK-B) | C58: =C33 -> 15190.891 | D58: =D33 -> 16289.455 | E58: =E33 -> 16339.517 | F58: =F33 -> 15397.418 | G58: =G33 -> 28302.02 | H58: =H33 -> 31238.984 | I58: =I33 -> 36040.939
B59: Turnkey (PK-C) | C59: =IF(ISNUMBER(C38),C38,"") | D59: =IF(ISNUMBER(D38),D38,"") | E59: =IF(ISNUMBER(E38),E38,"") -> 18881.25 | F59: =IF(ISNUMBER(F38),F38,"") -> 17881.25 | G59: =IF(ISNUMBER(G38),G38,"") -> 33131.25 | H59: =IF(ISNUMBER(H38),H38,"") -> 35131.25 | I59: =IF(ISNUMBER(I38),I38,"") -> 39631.25

Sheet Outsourcing
A1: Outsourcing check - selected size, cost per vessel by shipment size
A2: Size chosen on the Dashboard. Values pulled from Size Model with HLOOKUP.
A4: Selected size (mm) | B4: =Dashboard!$D$6 -> 2400
A5: Ship mode | B5: =HLOOKUP($B$4,'Size Model'!$C$4:$I$60,2,0) -> Flat rack
A6: Vessels per 40HC | B6: =HLOOKUP($B$4,'Size Model'!$C$4:$I$60,3,0) -> -
A7: Consumables ₹ | B7: =HLOOKUP($B$4,'Size Model'!$C$4:$I$60,6,0) -> 11085.499
A8: Nails ₹ | B8: =HLOOKUP($B$4,'Size Model'!$C$4:$I$60,7,0) -> 240.42857
A9: Material ₹ | B9: =HLOOKUP($B$4,'Size Model'!$C$4:$I$60,8,0) -> 23249.999
A10: Mistri hrs / vsl | B10: =HLOOKUP($B$4,'Size Model'!$C$4:$I$60,9,0) -> 9.8166667
A11: Jogali hrs / vsl | B11: =HLOOKUP($B$4,'Size Model'!$C$4:$I$60,10,0) -> 18.95
A12: Labour ₹ | B12: =HLOOKUP($B$4,'Size Model'!$C$4:$I$60,11,0) -> 2330.5333
A13: Wrapping labour ₹ | B13: =HLOOKUP($B$4,'Size Model'!$C$4:$I$60,12,0) -> 1250.7
A14: PK-A quote | B14: =HLOOKUP($B$4,'Size Model'!$C$4:$I$60,23,0) -> 2200
A15: PK-B skid quote | B15: =HLOOKUP($B$4,'Size Model'!$C$4:$I$60,27,0) -> 15050
A16: PK-C quote | B16: =HLOOKUP($B$4,'Size Model'!$C$4:$I$60,32,0) -> 31000
G17: Extra cost per vessel vs in-house (chart) - N/A = not quoted
A18: Vessels per shipment | B18: Fumigation ₹ | C18: In-house | D18: Contractor labour | E18: Buy skids | F18: Turnkey | G18: Contractor labour (PK-A) | H18: Buy skids (PK-B) | I18: Turnkey (PK-C)
A19: 1 | B19: =IF($B$5="40HC",ROUNDUP(A19/$B$6,0)*Inputs!$C$15,0) -> 0 | C19: =$B$9+$B$12+(B19+Inputs!$C$22)/A19+ROUNDUP(A19*($B$10+$B$11)/Inputs!$C$23,0)*Inputs!$C$26/A19 -> 26605.532 | D19: =$B$9+$B$14+(Inputs!$C$48+B19+Inputs!$C$22)/A19+ROUNDUP(A19*($B$10+$B$11)/Inputs!$C$23,0)*Inputs!$C$26/A19 -> 28974.999 | E19: =$B$15+$B$7-$B$8+$B$13+(ROUNDUP(A19/Inputs!$C$25,0)*Inputs!$C$49+B19+Inputs!$C$22)/A19+ROUNDUP(A19*$B$11/Inputs!$C$23,0)*Inputs!$C$26/A19 -> 29970.77 | F19: =IF(ISNUMBER($B$16),$B$16+(Inputs!$C$50+B19+Inputs!$C$22)/A19+ROUNDUP(A19*($B$10+$B$11)/Inputs!$C$24,0)*Inputs!$C$26/A19,"not quoted") -> 39525 | G19: =D19-C19 -> 2369.4667 | H19: =E19-C19 -> 3365.2382 | I19: =IF(ISNUMBER(F19),F19-C19,NA()) -> 12919.468
A20: 2 | B20: =IF($B$5="40HC",ROUNDUP(A20/$B$6,0)*Inputs!$C$15,0) -> 0 | C20: =$B$9+$B$12+(B20+Inputs!$C$22)/A20+ROUNDUP(A20*($B$10+$B$11)/Inputs!$C$23,0)*Inputs!$C$26/A20 -> 26093.032 | D20: =$B$9+$B$14+(Inputs!$C$48+B20+Inputs!$C$22)/A20+ROUNDUP(A20*($B$10+$B$11)/Inputs!$C$23,0)*Inputs!$C$26/A20 -> 27212.499 | E20: =$B$15+$B$7-$B$8+$B$13+(ROUNDUP(A20/Inputs!$C$25,0)*Inputs!$C$49+B20+Inputs!$C$22)/A20+ROUNDUP(A20*$B$11/Inputs!$C$23,0)*Inputs!$C$26/A20 -> 28558.27 | F20: =IF(ISNUMBER($B$16),$B$16+(Inputs!$C$50+B20+Inputs!$C$22)/A20+ROUNDUP(A20*($B$10+$B$11)/Inputs!$C$24,0)*Inputs!$C$26/A20,"not quoted") -> 35262.5 | G20: =D20-C20 -> 1119.4667 | H20: =E20-C20 -> 2465.2382 | I20: =IF(ISNUMBER(F20),F20-C20,NA()) -> 9169.468
A21: 3 | B21: =IF($B$5="40HC",ROUNDUP(A21/$B$6,0)*Inputs!$C$15,0) -> 0 | C21: =$B$9+$B$12+(B21+Inputs!$C$22)/A21+ROUNDUP(A21*($B$10+$B$11)/Inputs!$C$23,0)*Inputs!$C$26/A21 -> 25922.199 | D21: =$B$9+$B$14+(Inputs!$C$48+B21+Inputs!$C$22)/A21+ROUNDUP(A21*($B$10+$B$11)/Inputs!$C$23,0)*Inputs!$C$26/A21 -> 26624.999 | E21: =$B$15+$B$7-$B$8+$B$13+(ROUNDUP(A21/Inputs!$C$25,0)*Inputs!$C$49+B21+Inputs!$C$22)/A21+ROUNDUP(A21*$B$11/Inputs!$C$23,0)*Inputs!$C$26/A21 -> 28087.437 | F21: =IF(ISNUMBER($B$16),$B$16+(Inputs!$C$50+B21+Inputs!$C$22)/A21+ROUNDUP(A21*($B$10+$B$11)/Inputs!$C$24,0)*Inputs!$C$26/A21,"not quoted") -> 33841.667 | G21: =D21-C21 -> 702.8 | H21: =E21-C21 -> 2165.2382 | I21: =IF(ISNUMBER(F21),F21-C21,NA()) -> 7919.468
A22: 4 | B22: =IF($B$5="40HC",ROUNDUP(A22/$B$6,0)*Inputs!$C$15,0) -> 0 | C22: =$B$9+$B$12+(B22+Inputs!$C$22)/A22+ROUNDUP(A22*($B$10+$B$11)/Inputs!$C$23,0)*Inputs!$C$26/A22 -> 25836.782 | D22: =$B$9+$B$14+(Inputs!$C$48+B22+Inputs!$C$22)/A22+ROUNDUP(A22*($B$10+$B$11)/Inputs!$C$23,0)*Inputs!$C$26/A22 -> 26331.249 | E22: =$B$15+$B$7-$B$8+$B$13+(ROUNDUP(A22/Inputs!$C$25,0)*Inputs!$C$49+B22+Inputs!$C$22)/A22+ROUNDUP(A22*$B$11/Inputs!$C$23,0)*Inputs!$C$26/A22 -> 28302.02 | F22: =IF(ISNUMBER($B$16),$B$16+(Inputs!$C$50+B22+Inputs!$C$22)/A22+ROUNDUP(A22*($B$10+$B$11)/Inputs!$C$24,0)*Inputs!$C$26/A22,"not quoted") -> 33131.25 | G22: =D22-C22 -> 494.46667 | H22: =E22-C22 -> 2465.2382 | I22: =IF(ISNUMBER(F22),F22-C22,NA()) -> 7294.468
A23: 5 | B23: =IF($B$5="40HC",ROUNDUP(A23/$B$6,0)*Inputs!$C$15,0) -> 0 | C23: =$B$9+$B$12+(B23+Inputs!$C$22)/A23+ROUNDUP(A23*($B$10+$B$11)/Inputs!$C$23,0)*Inputs!$C$26/A23 -> 25785.532 | D23: =$B$9+$B$14+(Inputs!$C$48+B23+Inputs!$C$22)/A23+ROUNDUP(A23*($B$10+$B$11)/Inputs!$C$23,0)*Inputs!$C$26/A23 -> 26154.999 | E23: =$B$15+$B$7-$B$8+$B$13+(ROUNDUP(A23/Inputs!$C$25,0)*Inputs!$C$49+B23+Inputs!$C$22)/A23+ROUNDUP(A23*$B$11/Inputs!$C$23,0)*Inputs!$C$26/A23 -> 28070.77 | F23: =IF(ISNUMBER($B$16),$B$16+(Inputs!$C$50+B23+Inputs!$C$22)/A23+ROUNDUP(A23*($B$10+$B$11)/Inputs!$C$24,0)*Inputs!$C$26/A23,"not quoted") -> 32705 | G23: =D23-C23 -> 369.46667 | H23: =E23-C23 -> 2285.2382 | I23: =IF(ISNUMBER(F23),F23-C23,NA()) -> 6919.468
A24: 6 | B24: =IF($B$5="40HC",ROUNDUP(A24/$B$6,0)*Inputs!$C$15,0) -> 0 | C24: =$B$9+$B$12+(B24+Inputs!$C$22)/A24+ROUNDUP(A24*($B$10+$B$11)/Inputs!$C$23,0)*Inputs!$C$26/A24 -> 25751.365 | D24: =$B$9+$B$14+(Inputs!$C$48+B24+Inputs!$C$22)/A24+ROUNDUP(A24*($B$10+$B$11)/Inputs!$C$23,0)*Inputs!$C$26/A24 -> 26037.499 | E24: =$B$15+$B$7-$B$8+$B$13+(ROUNDUP(A24/Inputs!$C$25,0)*Inputs!$C$49+B24+Inputs!$C$22)/A24+ROUNDUP(A24*$B$11/Inputs!$C$23,0)*Inputs!$C$26/A24 -> 27916.604 | F24: =IF(ISNUMBER($B$16),$B$16+(Inputs!$C$50+B24+Inputs!$C$22)/A24+ROUNDUP(A24*($B$10+$B$11)/Inputs!$C$24,0)*Inputs!$C$26/A24,"not quoted") -> 32420.833 | G24: =D24-C24 -> 286.13333 | H24: =E24-C24 -> 2165.2382 | I24: =IF(ISNUMBER(F24),F24-C24,NA()) -> 6669.468
A25: 7 | B25: =IF($B$5="40HC",ROUNDUP(A25/$B$6,0)*Inputs!$C$15,0) -> 0 | C25: =$B$9+$B$12+(B25+Inputs!$C$22)/A25+ROUNDUP(A25*($B$10+$B$11)/Inputs!$C$23,0)*Inputs!$C$26/A25 -> 25726.961 | D25: =$B$9+$B$14+(Inputs!$C$48+B25+Inputs!$C$22)/A25+ROUNDUP(A25*($B$10+$B$11)/Inputs!$C$23,0)*Inputs!$C$26/A25 -> 25953.57 | E25: =$B$15+$B$7-$B$8+$B$13+(ROUNDUP(A25/Inputs!$C$25,0)*Inputs!$C$49+B25+Inputs!$C$22)/A25+ROUNDUP(A25*$B$11/Inputs!$C$23,0)*Inputs!$C$26/A25 -> 28063.627 | F25: =IF(ISNUMBER($B$16),$B$16+(Inputs!$C$50+B25+Inputs!$C$22)/A25+ROUNDUP(A25*($B$10+$B$11)/Inputs!$C$24,0)*Inputs!$C$26/A25,"not quoted") -> 32217.857 | G25: =D25-C25 -> 226.60952 | H25: =E25-C25 -> 2336.6667 | I25: =IF(ISNUMBER(F25),F25-C25,NA()) -> 6490.8965
A26: 8 | B26: =IF($B$5="40HC",ROUNDUP(A26/$B$6,0)*Inputs!$C$15,0) -> 0 | C26: =$B$9+$B$12+(B26+Inputs!$C$22)/A26+ROUNDUP(A26*($B$10+$B$11)/Inputs!$C$23,0)*Inputs!$C$26/A26 -> 25708.657 | D26: =$B$9+$B$14+(Inputs!$C$48+B26+Inputs!$C$22)/A26+ROUNDUP(A26*($B$10+$B$11)/Inputs!$C$23,0)*Inputs!$C$26/A26 -> 25890.624 | E26: =$B$15+$B$7-$B$8+$B$13+(ROUNDUP(A26/Inputs!$C$25,0)*Inputs!$C$49+B26+Inputs!$C$22)/A26+ROUNDUP(A26*$B$11/Inputs!$C$23,0)*Inputs!$C$26/A26 -> 27948.895 | F26: =IF(ISNUMBER($B$16),$B$16+(Inputs!$C$50+B26+Inputs!$C$22)/A26+ROUNDUP(A26*($B$10+$B$11)/Inputs!$C$24,0)*Inputs!$C$26/A26,"not quoted") -> 32065.625 | G26: =D26-C26 -> 181.96667 | H26: =E26-C26 -> 2240.2382 | I26: =IF(ISNUMBER(F26),F26-C26,NA()) -> 6356.968
A27: 9 | B27: =IF($B$5="40HC",ROUNDUP(A27/$B$6,0)*Inputs!$C$15,0) -> 0 | C27: =$B$9+$B$12+(B27+Inputs!$C$22)/A27+ROUNDUP(A27*($B$10+$B$11)/Inputs!$C$23,0)*Inputs!$C$26/A27 -> 25694.421 | D27: =$B$9+$B$14+(Inputs!$C$48+B27+Inputs!$C$22)/A27+ROUNDUP(A27*($B$10+$B$11)/Inputs!$C$23,0)*Inputs!$C$26/A27 -> 25841.665 | E27: =$B$15+$B$7-$B$8+$B$13+(ROUNDUP(A27/Inputs!$C$25,0)*Inputs!$C$49+B27+Inputs!$C$22)/A27+ROUNDUP(A27*$B$11/Inputs!$C$23,0)*Inputs!$C$26/A27 -> 27859.659 | F27: =IF(ISNUMBER($B$16),$B$16+(Inputs!$C$50+B27+Inputs!$C$22)/A27+ROUNDUP(A27*($B$10+$B$11)/Inputs!$C$24,0)*Inputs!$C$26/A27,"not quoted") -> 31947.222 | G27: =D27-C27 -> 147.24444 | H27: =E27-C27 -> 2165.2382 | I27: =IF(ISNUMBER(F27),F27-C27,NA()) -> 6252.8013
A28: 10 | B28: =IF($B$5="40HC",ROUNDUP(A28/$B$6,0)*Inputs!$C$15,0) -> 0 | C28: =$B$9+$B$12+(B28+Inputs!$C$22)/A28+ROUNDUP(A28*($B$10+$B$11)/Inputs!$C$23,0)*Inputs!$C$26/A28 -> 25683.032 | D28: =$B$9+$B$14+(Inputs!$C$48+B28+Inputs!$C$22)/A28+ROUNDUP(A28*($B$10+$B$11)/Inputs!$C$23,0)*Inputs!$C$26/A28 -> 25802.499 | E28: =$B$15+$B$7-$B$8+$B$13+(ROUNDUP(A28/Inputs!$C$25,0)*Inputs!$C$49+B28+Inputs!$C$22)/A28+ROUNDUP(A28*$B$11/Inputs!$C$23,0)*Inputs!$C$26/A28 -> 27968.27 | F28: =IF(ISNUMBER($B$16),$B$16+(Inputs!$C$50+B28+Inputs!$C$22)/A28+ROUNDUP(A28*($B$10+$B$11)/Inputs!$C$24,0)*Inputs!$C$26/A28,"not quoted") -> 31852.5 | G28: =D28-C28 -> 119.46667 | H28: =E28-C28 -> 2285.2382 | I28: =IF(ISNUMBER(F28),F28-C28,NA()) -> 6169.468

Sheet Data - SAP Issues
A1: SAP Goods Issue export - packing items, Oct-25 to Aug-26 (pasted as values)
A2: Grey = SAP columns as exported. Green = columns I added.
A3: DocNum | B3: DocDate | C3: Ref2 (job in SAP) | D3: ItemCode | E3: Dscription | F3: Quantity | G3: UomCode | H3: Price | I3: LineTotal | J3: Comments | K3: Job (checked) | L3: Size (mm) | M3: Rate item | N3: Timber cft
A4: 11832 | B4: 45938 | C4: J/25-26/135 | D4: 1900162 | E4: AIR BUBBLE WRAP | F4: 6 | G4: ROLL | H4: 640 | I4: 3840 | K4: J/25-26/135 | L4: =VLOOKUP(K4,'Job Costing'!$A$5:$B$23,2,0) -> 2600 | M4: =VLOOKUP(D4,'Data - Items'!$A$4:$I$35,9,0) -> Bubble wrap | N4: =IF(M4="Timber",F4*VLOOKUP(D4,'Data - Items'!$A$4:$H$35,8,0),0) -> 0
A5: 11832 | B5: 45938 | C5: J/25-26/135 | D5: 1900158 | E5: GUM TAPE 3" | F5: 6 | G5: NOS | H5: 78 | I5: 468 | K5: J/25-26/135 | L5: =VLOOKUP(K5,'Job Costing'!$A$5:$B$23,2,0) -> 2600 | M5: =VLOOKUP(D5,'Data - Items'!$A$4:$I$35,9,0) -> Gum tape | N5: =IF(M5="Timber",F5*VLOOKUP(D5,'Data - Items'!$A$4:$H$35,8,0),0) -> 0
A6: 11832 | B6: 45938 | C6: J/25-26/135 | D6: 1900223 | E6: HDPE TARPAULIN 200 GSM | F6: 1600 | G6: SQFT | H6: 5 | I6: 8000 | K6: J/25-26/135 | L6: =VLOOKUP(K6,'Job Costing'!$A$5:$B$23,2,0) -> 2600 | M6: =VLOOKUP(D6,'Data - Items'!$A$4:$I$35,9,0) -> Tarpaulin | N6: =IF(M6="Timber",F6*VLOOKUP(D6,'Data - Items'!$A$4:$H$35,8,0),0) -> 0
A7: 11832 | B7: 45938 | C7: J/25-26/135 | D7: 1900144 | E7: KINI FOAM 12 MM THK X 1400 MM WD | F7: 4 | G7: ROLL | H7: 2100 | I7: 8400 | K7: J/25-26/135 | L7: =VLOOKUP(K7,'Job Costing'!$A$5:$B$23,2,0) -> 2600 | M7: =VLOOKUP(D7,'Data - Items'!$A$4:$I$35,9,0) -> Foam | N7: =IF(M7="Timber",F7*VLOOKUP(D7,'Data - Items'!$A$4:$H$35,8,0),0) -> 0
A8: 11832 | B8: 45938 | C8: J/25-26/135 | D8: 1900137 | E8: NAILS (AS REQUIRED) | F8: 8 | G8: SETS | H8: 90 | I8: 720 | K8: J/25-26/135 | L8: =VLOOKUP(K8,'Job Costing'!$A$5:$B$23,2,0) -> 2600 | M8: =VLOOKUP(D8,'Data - Items'!$A$4:$I$35,9,0) -> Nails | N8: =IF(M8="Timber",F8*VLOOKUP(D8,'Data - Items'!$A$4:$H$35,8,0),0) -> 0
A9: 11832 | B9: 45938 | C9: J/25-26/135 | D9: 1900222 | E9: PLY COVER 12 MM (MANHOLE/NOZZLE) | F9: 18 | G9: NOS | H9: 160 | I9: 2880 | K9: J/25-26/135 | L9: =VLOOKUP(K9,'Job Costing'!$A$5:$B$23,2,0) -> 2600 | M9: =VLOOKUP(D9,'Data - Items'!$A$4:$I$35,9,0) -> Ply cover | N9: =IF(M9="Timber",F9*VLOOKUP(D9,'Data - Items'!$A$4:$H$35,8,0),0) -> 0
A10: 11832 | B10: 45938 | C10: J/25-26/135 | D10: 1900151 | E10: RATCHET LASHING BELT 8 M LG X 50 MM WD WITH LOCK | F10: 8 | G10: NOS | H10: 880 | I10: 7040 | K10: J/25-26/135 | L10: =VLOOKUP(K10,'Job Costing'!$A$5:$B$23,2,0) -> 2600 | M10: =VLOOKUP(D10,'Data - Items'!$A$4:$I$35,9,0) -> Ratchet belt | N10: =IF(M10="Timber",F10*VLOOKUP(D10,'Data - Items'!$A$4:$H$35,8,0),0) -> 0
A11: 11832 | B11: 45938 | C11: J/25-26/135 | D11: 1900160 | E11: STRETCH FILM 50 MICRON | F11: 13.9 | G11: KG | H11: 158 | I11: 2196.2 | K11: J/25-26/135 | L11: =VLOOKUP(K11,'Job Costing'!$A$5:$B$23,2,0) -> 2600 | M11: =VLOOKUP(D11,'Data - Items'!$A$4:$I$35,9,0) -> Stretch film | N11: =IF(M11="Timber",F11*VLOOKUP(D11,'Data - Items'!$A$4:$H$35,8,0),0) -> 0
A12: 11832 | B12: 45938 | C12: J/25-26/135 | D12: 1900205 | E12: WOODEN BATTEN 100 X 100 X 1700 LG | F12: 19 | G12: NOS | H12: 420.24 | I12: 7984.56 | K12: J/25-26/135 | L12: =VLOOKUP(K12,'Job Costing'!$A$5:$B$23,2,0) -> 2600 | M12: =VLOOKUP(D12,'Data - Items'!$A$4:$I$35,9,0) -> Timber | N12: =IF(M12="Timber",F12*VLOOKUP(D12,'Data - Items'!$A$4:$H$35,8,0),0) -> 11.40513
A13: 11832 | B13: 45938 | C13: J/25-26/135 | D13: 1900130 | E13: WOODEN BATTEN 100 X 75 X 100 LG | F13: 21 | G13: NOS | H13: 18.54 | I13: 389.34 | K13: J/25-26/135 | L13: =VLOOKUP(K13,'Job Costing'!$A$5:$B$23,2,0) -> 2600 | M13: =VLOOKUP(D13,'Data - Items'!$A$4:$I$35,9,0) -> Timber | N13: =IF(M13="Timber",F13*VLOOKUP(D13,'Data - Items'!$A$4:$H$35,8,0),0) -> 0.5561325
A14: 11832 | B14: 45938 | C14: J/25-26/135 | D14: 1900208 | E14: WOODEN BATTEN 150 X 75 X 1700 LG | F14: 8 | G14: NOS | H14: 472.78 | I14: 3782.24 | K14: J/25-26/135 | L14: =VLOOKUP(K14,'Job Costing'!$A$5:$B$23,2,0) -> 2600 | M14: =VLOOKUP(D14,'Data - Items'!$A$4:$I$35,9,0) -> Timber | N14: =IF(M14="Timber",F14*VLOOKUP(D14,'Data - Items'!$A$4:$H$35,8,0),0) -> 5.40243
A15: 11832 | B15: 45938 | C15: J/25-26/135 | D15: 1900198 | E15: WOODEN BATTEN 150 X 75 X 3750 LG | F15: 11 | G15: NOS | H15: 1042.89 | I15: 11471.79 | K15: J/25-26/135 | L15: =VLOOKUP(K15,'Job Costing'!$A$5:$B$23,2,0) -> 2600 | M15: =VLOOKUP(D15,'Data - Items'!$A$4:$I$35,9,0) -> Timber | N15: =IF(M15="Timber",F15*VLOOKUP(D15,'Data - Items'!$A$4:$H$35,8,0),0) -> 16.386047
... A54: 11883 | B54: 45978 | C54: J/25-26/122 | D54: 1900196 | E54: WOODEN BATTEN 200 X 200 X 400 LG | F54: 13 | G54: NOS | H54: 395.52 | I54: 5141.76 | K54: J/25-26/122 | L54: =VLOOKUP(K54,'Job Costing'!$A$5:$B$23,2,0) -> 2600 | M54: =VLOOKUP(D54,'Data - Items'!$A$4:$I$35,9,0) -> Timber | N54: =IF(M54="Timber",F54*VLOOKUP(D54,'Data - Items'!$A$4:$H$35,8,0),0) -> 7.34448
A55: 11896 | B55: 45979 | C55: J/25-26/122 | D55: 1900198 | E55: WOODEN BATTEN 150 X 75 X 3750 LG | F55: 3 | G55: NOS | H55: 1042.89 | I55: 3128.67 | J55: ADDL ISSUE - BATTEN SPLIT DURING NAILING | K55: J/25-26/122 | L55: =VLOOKUP(K55,'Job Costing'!$A$5:$B$23,2,0) -> 2600 | M55: =VLOOKUP(D55,'Data - Items'!$A$4:$I$35,9,0) -> Timber | N55: =IF(M55="Timber",F55*VLOOKUP(D55,'Data - Items'!$A$4:$H$35,8,0),0) -> 4.4689219
A56: 11910 | B56: 45987 | C56: J/25-26/124 | D56: 1900162 | E56: AIR BUBBLE WRAP | F56: 7 | G56: ROLL | H56: 640 | I56: 4480 | K56: J/25-26/124 | L56: =VLOOKUP(K56,'Job Costing'!$A$5:$B$23,2,0) -> 2400 | M56: =VLOOKUP(D56,'Data - Items'!$A$4:$I$35,9,0) -> Bubble wrap | N56: =IF(M56="Timber",F56*VLOOKUP(D56,'Data - Items'!$A$4:$H$35,8,0),0) -> 0
A57: 11910 | B57: 45987 | C57: J/25-26/124 | D57: 1900158 | E57: GUM TAPE 3" | F57: 6 | G57: NOS | H57: 78 | I57: 468 | K57: J/25-26/124 | L57: =VLOOKUP(K57,'Job Costing'!$A$5:$B$23,2,0) -> 2400 | M57: =VLOOKUP(D57,'Data - Items'!$A$4:$I$35,9,0) -> Gum tape | N57: =IF(M57="Timber",F57*VLOOKUP(D57,'Data - Items'!$A$4:$H$35,8,0),0) -> 0
A58: 11910 | B58: 45987 | C58: J/25-26/124 | D58: 1900223 | E58: HDPE TARPAULIN 200 GSM | F58: 2200 | G58: SQFT | H58: 5 | I58: 11000 | K58: J/25-26/124 | L58: =VLOOKUP(K58,'Job Costing'!$A$5:$B$23,2,0) -> 2400 | M58: =VLOOKUP(D58,'Data - Items'!$A$4:$I$35,9,0) -> Tarpaulin | N58: =IF(M58="Timber",F58*VLOOKUP(D58,'Data - Items'!$A$4:$H$35,8,0),0) -> 0
A59: 11910 | B59: 45987 | C59: J/25-26/124 | D59: 1900144 | E59: KINI FOAM 12 MM THK X 1400 MM WD | F59: 4 | G59: ROLL | H59: 2100 | I59: 8400 | K59: J/25-26/124 | L59: =VLOOKUP(K59,'Job Costing'!$A$5:$B$23,2,0) -> 2400 | M59: =VLOOKUP(D59,'Data - Items'!$A$4:$I$35,9,0) -> Foam | N59: =IF(M59="Timber",F59*VLOOKUP(D59,'Data - Items'!$A$4:$H$35,8,0),0) -> 0
A60: 11910 | B60: 45987 | C60: J/25-26/124 | D60: 1900137 | E60: NAILS (AS REQUIRED) | F60: 10 | G60: SETS | H60: 90 | I60: 900 | K60: J/25-26/124 | L60: =VLOOKUP(K60,'Job Costing'!$A$5:$B$23,2,0) -> 2400 | M60: =VLOOKUP(D60,'Data - Items'!$A$4:$I$35,9,0) -> Nails | N60: =IF(M60="Timber",F60*VLOOKUP(D60,'Data - Items'!$A$4:$H$35,8,0),0) -> 0
A61: 11910 | B61: 45987 | C61: J/25-26/124 | D61: 1900222 | E61: PLY COVER 12 MM (MANHOLE/NOZZLE) | F61: 18 | G61: NOS | H61: 160 | I61: 2880 | K61: J/25-26/124 | L61: =VLOOKUP(K61,'Job Costing'!$A$5:$B$23,2,0) -> 2400 | M61: =VLOOKUP(D61,'Data - Items'!$A$4:$I$35,9,0) -> Ply cover | N61: =IF(M61="Timber",F61*VLOOKUP(D61,'Data - Items'!$A$4:$H$35,8,0),0) -> 0
A62: 11910 | B62: 45987 | C62: J/25-26/124 | D62: 1900151 | E62: RATCHET LASHING BELT 8 M LG X 50 MM WD WITH LOCK | F62: 14 | G62: NOS | H62: 900 | I62: 12600 | K62: J/25-26/124 | L62: =VLOOKUP(K62,'Job Costing'!$A$5:$B$23,2,0) -> 2400 | M62: =VLOOKUP(D62,'Data - Items'!$A$4:$I$35,9,0) -> Ratchet belt | N62: =IF(M62="Timber",F62*VLOOKUP(D62,'Data - Items'!$A$4:$H$35,8,0),0) -> 0
A63: 11910 | B63: 45987 | C63: J/25-26/124 | D63: 1900160 | E63: STRETCH FILM 50 MICRON | F63: 13.6 | G63: KG | H63: 158 | I63: 2148.8 | K63: J/25-26/124 | L63: =VLOOKUP(K63,'Job Costing'!$A$5:$B$23,2,0) -> 2400 | M63: =VLOOKUP(D63,'Data - Items'!$A$4:$I$35,9,0) -> Stretch film | N63: =IF(M63="Timber",F63*VLOOKUP(D63,'Data - Items'!$A$4:$H$35,8,0),0) -> 0
A64: 11910 | B64: 45987 | C64: J/25-26/124 | D64: 1900192 | E64: WOODEN BATTEN 100 X 100 X 1550 LG | F64: 27 | G64: NOS | H64: 383.16 | I64: 10345.32 | K64: J/25-26/124 | L64: =VLOOKUP(K64,'Job Costing'!$A$5:$B$23,2,0) -> 2400 | M64: =VLOOKUP(D64,'Data - Items'!$A$4:$I$35,9,0) -> Timber | N64: =IF(M64="Timber",F64*VLOOKUP(D64,'Data - Items'!$A$4:$H$35,8,0),0) -> 14.777235
A65: 11910 | B65: 45987 | C65: J/25-26/124 | D65: 1900130 | E65: WOODEN BATTEN 100 X 75 X 100 LG | F65: 20 | G65: NOS | H65: 18.54 | I65: 370.8 | K65: J/25-26/124 | L65: =VLOOKUP(K65,'Job Costing'!$A$5:$B$23,2,0) -> 2400 | M65: =VLOOKUP(D65,'Data - Items'!$A$4:$I$35,9,0) -> Timber | N65: =IF(M65="Timber",F65*VLOOKUP(D65,'Data - Items'!$A$4:$H$35,8,0),0) -> 0.52965
A66: 11910 | B66: 45987 | C66: J/25-26/124 | D66: 1900194 | E66: WOODEN BATTEN 150 X 75 X 1550 LG | F66: 15 | G66: NOS | H66: 431.06 | I66: 6465.9 | K66: J/25-26/124 | L66: =VLOOKUP(K66,'Job Costing'!$A$5:$B$23,2,0) -> 2400 | M66: =VLOOKUP(D66,'Data - Items'!$A$4:$I$35,9,0) -> Timber | N66: =IF(M66="Timber",F66*VLOOKUP(D66,'Data - Items'!$A$4:$H$35,8,0),0) -> 9.2357719
A67: 11910 | B67: 45987 | C67: J/25-26/124 | D67: 1900190 | E67: WOODEN BATTEN 150 X 75 X 3550 LG | F67: 16 | G67: NOS | H67: 987.27 | I67: 15796.32 | K67: J/25-26/124 | L67: =VLOOKUP(K67,'Job Costing'!$A$5:$B$23,2,0) -> 2400 | M67: =VLOOKUP(D67,'Data - Items'!$A$4:$I$35,9,0) -> Timber | N67: =IF(M67="Timber",F67*VLOOKUP(D67,'Data - Items'!$A$4:$H$35,8,0),0) -> 22.56309
... A91: 11948 | B91: 46009 | C91: J/25-26/134 | D91: 1900114 | E91: WOODEN BATTEN 150 X 75 X 2450 LG | F91: 11 | G91: NOS | H91: 681.35 | I91: 7494.85 | K91: J/25-26/134 | L91: =VLOOKUP(K91,'Job Costing'!$A$5:$B$23,2,0) -> 2000 | M91: =VLOOKUP(D91,'Data - Items'!$A$4:$I$35,9,0) -> Timber | N91: =IF(M91="Timber",F91*VLOOKUP(D91,'Data - Items'!$A$4:$H$35,8,0),0) -> 10.705551
A92: 11954 | B92: 46010 | C92: J/25-26/134 | D92: 1900114 | E92: WOODEN BATTEN 150 X 75 X 2450 LG | F92: 2 | G92: NOS | H92: 681.35 | I92: 1362.7 | J92: ADDL ISSUE - BATTEN SPLIT DURING NAILING | K92: J/25-26/134 | L92: =VLOOKUP(K92,'Job Costing'!$A$5:$B$23,2,0) -> 2000 | M92: =VLOOKUP(D92,'Data - Items'!$A$4:$I$35,9,0) -> Timber | N92: =IF(M92="Timber",F92*VLOOKUP(D92,'Data - Items'!$A$4:$H$35,8,0),0) -> 1.9464637
A93: 11971 | B93: 46064 | C93: J/25-26/139 | D93: 1900162 | E93: AIR BUBBLE WRAP | F93: 2 | G93: ROLL | H93: 640 | I93: 1280 | K93: J/25-26/139 | L93: =VLOOKUP(K93,'Job Costing'!$A$5:$B$23,2,0) -> 1600 | M93: =VLOOKUP(D93,'Data - Items'!$A$4:$I$35,9,0) -> Bubble wrap | N93: =IF(M93="Timber",F93*VLOOKUP(D93,'Data - Items'!$A$4:$H$35,8,0),0) -> 0
A94: 11971 | B94: 46064 | C94: J/25-26/139 | D94: 1900158 | E94: GUM TAPE 3" | F94: 2 | G94: NOS | H94: 78 | I94: 156 | K94: J/25-26/139 | L94: =VLOOKUP(K94,'Job Costing'!$A$5:$B$23,2,0) -> 1600 | M94: =VLOOKUP(D94,'Data - Items'!$A$4:$I$35,9,0) -> Gum tape | N94: =IF(M94="Timber",F94*VLOOKUP(D94,'Data - Items'!$A$4:$H$35,8,0),0) -> 0
A95: 11971 | B95: 46064 | C95: J/25-26/139 | D95: 1900144 | E95: KINI FOAM 12 MM THK X 1400 MM WD | F95: 1 | G95: ROLL | H95: 2100 | I95: 2100 | K95: J/25-26/139 | L95: =VLOOKUP(K95,'Job Costing'!$A$5:$B$23,2,0) -> 1600 | M95: =VLOOKUP(D95,'Data - Items'!$A$4:$I$35,9,0) -> Foam | N95: =IF(M95="Timber",F95*VLOOKUP(D95,'Data - Items'!$A$4:$H$35,8,0),0) -> 0
A96: 11971 | B96: 46064 | C96: J/25-26/139 | D96: 1900137 | E96: NAILS (AS REQUIRED) | F96: 3 | G96: SETS | H96: 90 | I96: 270 | K96: J/25-26/139 | L96: =VLOOKUP(K96,'Job Costing'!$A$5:$B$23,2,0) -> 1600 | M96: =VLOOKUP(D96,'Data - Items'!$A$4:$I$35,9,0) -> Nails | N96: =IF(M96="Timber",F96*VLOOKUP(D96,'Data - Items'!$A$4:$H$35,8,0),0) -> 0
A97: 11971 | B97: 46064 | C97: J/25-26/139 | D97: 1900222 | E97: PLY COVER 12 MM (MANHOLE/NOZZLE) | F97: 9 | G97: NOS | H97: 160 | I97: 1440 | K97: J/25-26/139 | L97: =VLOOKUP(K97,'Job Costing'!$A$5:$B$23,2,0) -> 1600 | M97: =VLOOKUP(D97,'Data - Items'!$A$4:$I$35,9,0) -> Ply cover | N97: =IF(M97="Timber",F97*VLOOKUP(D97,'Data - Items'!$A$4:$H$35,8,0),0) -> 0
A98: 11971 | B98: 46064 | C98: J/25-26/139 | D98: 1900151 | E98: RATCHET LASHING BELT 8 M LG X 50 MM WD WITH LOCK | F98: 4 | G98: NOS | H98: 900 | I98: 3600 | K98: J/25-26/139 | L98: =VLOOKUP(K98,'Job Costing'!$A$5:$B$23,2,0) -> 1600 | M98: =VLOOKUP(D98,'Data - Items'!$A$4:$I$35,9,0) -> Ratchet belt | N98: =IF(M98="Timber",F98*VLOOKUP(D98,'Data - Items'!$A$4:$H$35,8,0),0) -> 0
A99: 11971 | B99: 46064 | C99: J/25-26/139 | D99: 1900160 | E99: STRETCH FILM 50 MICRON | F99: 7.1 | G99: KG | H99: 166 | I99: 1178.6 | K99: J/25-26/139 | L99: =VLOOKUP(K99,'Job Costing'!$A$5:$B$23,2,0) -> 1600 | M99: =VLOOKUP(D99,'Data - Items'!$A$4:$I$35,9,0) -> Stretch film | N99: =IF(M99="Timber",F99*VLOOKUP(D99,'Data - Items'!$A$4:$H$35,8,0),0) -> 0
A100: 11971 | B100: 46064 | C100: J/25-26/139 | D100: 1900180 | E100: WOODEN BATTEN 100 X 100 X 1050 LG | F100: 10 | G100: NOS | H100: 266.98 | I100: 2669.8 | K100: J/25-26/139 | L100: =VLOOKUP(K100,'Job Costing'!$A$5:$B$23,2,0) -> 1600 | M100: =VLOOKUP(D100,'Data - Items'!$A$4:$I$35,9,0) -> Timber | N100: =IF(M100="Timber",F100*VLOOKUP(D100,'Data - Items'!$A$4:$H$35,8,0),0) -> 3.70755
A101: 11971 | B101: 46064 | C101: J/25-26/139 | D101: 1900130 | E101: WOODEN BATTEN 100 X 75 X 100 LG | F101: 12 | G101: NOS | H101: 19.07 | I101: 228.84 | K101: J/25-26/139 | L101: =VLOOKUP(K101,'Job Costing'!$A$5:$B$23,2,0) -> 1600 | M101: =VLOOKUP(D101,'Data - Items'!$A$4:$I$35,9,0) -> Timber | N101: =IF(M101="Timber",F101*VLOOKUP(D101,'Data - Items'!$A$4:$H$35,8,0),0) -> 0.31779
A102: 11971 | B102: 46064 | C102: J/25-26/139 | D102: 1900127 | E102: WOODEN BATTEN 150 X 150 X 300 LG | F102: 11 | G102: NOS | H102: 171.63 | I102: 1887.93 | K102: J/25-26/139 | L102: =VLOOKUP(K102,'Job Costing'!$A$5:$B$23,2,0) -> 1600 | M102: =VLOOKUP(D102,'Data - Items'!$A$4:$I$35,9,0) -> Timber | N102: =IF(M102="Timber",F102*VLOOKUP(D102,'Data - Items'!$A$4:$H$35,8,0),0) -> 2.6217675
A103: 11971 | B103: 46064 | C103: J/25-26/139 | D103: 1900183 | E103: WOODEN BATTEN 150 X 75 X 1050 LG | F103: 4 | G103: NOS | H103: 300.35 | I103: 1201.4 | K103: J/25-26/139 | L103: =VLOOKUP(K103,'Job Costing'!$A$5:$B$23,2,0) -> 1600 | M103: =VLOOKUP(D103,'Data - Items'!$A$4:$I$35,9,0) -> Timber | N103: =IF(M103="Timber",F103*VLOOKUP(D103,'Data - Items'!$A$4:$H$35,8,0),0) -> 1.6683975
A104: 11971 | B104: 46064 | C104: J/25-26/139 | D104: 1900179 | E104: WOODEN BATTEN 150 X 75 X 2650 LG | F104: 8 | G104: NOS | H104: 758.03 | I104: 6064.24 | K104: J/25-26/139 | L104: =VLOOKUP(K104,'Job Costing'!$A$5:$B$23,2,0) -> 1600 | M104: =VLOOKUP(D104,'Data - Items'!$A$4:$I$35,9,0) -> Timber | N104: =IF(M104="Timber",F104*VLOOKUP(D104,'Data - Items'!$A$4:$H$35,8,0),0) -> 8.421435
... A142: 12027 | B142: 46085 | C142: J/25-26/145 | D142: 1900196 | E142: WOODEN BATTEN 200 X 200 X 400 LG | F142: 39 | G142: NOS | H142: 406.83 | I142: 15866.37 | K142: J/25-26/145 | L142: =VLOOKUP(K142,'Job Costing'!$A$5:$B$23,2,0) -> 2400 | M142: =VLOOKUP(D142,'Data - Items'!$A$4:$I$35,9,0) -> Timber | N142: =IF(M142="Timber",F142*VLOOKUP(D142,'Data - Items'!$A$4:$H$35,8,0),0) -> 22.03344
A143: 12045 | B143: 46099 | D143: 1900162 | E143: AIR BUBBLE WRAP | F143: 4 | G143: ROLL | H143: 680 | I143: 2720 | J143: PKG J/25-26/151 | K143: J/25-26/151 | L143: =VLOOKUP(K143,'Job Costing'!$A$5:$B$23,2,0) -> 2000 | M143: =VLOOKUP(D143,'Data - Items'!$A$4:$I$35,9,0) -> Bubble wrap | N143: =IF(M143="Timber",F143*VLOOKUP(D143,'Data - Items'!$A$4:$H$35,8,0),0) -> 0
A144: 12045 | B144: 46099 | D144: 1900158 | E144: GUM TAPE 3" | F144: 5 | G144: NOS | H144: 78 | I144: 390 | J144: PKG J/25-26/151 | K144: J/25-26/151 | L144: =VLOOKUP(K144,'Job Costing'!$A$5:$B$23,2,0) -> 2000 | M144: =VLOOKUP(D144,'Data - Items'!$A$4:$I$35,9,0) -> Gum tape | N144: =IF(M144="Timber",F144*VLOOKUP(D144,'Data - Items'!$A$4:$H$35,8,0),0) -> 0
A145: 12045 | B145: 46099 | D145: 1900144 | E145: KINI FOAM 12 MM THK X 1400 MM WD | F145: 3 | G145: ROLL | H145: 2100 | I145: 6300 | J145: PKG J/25-26/151 | K145: J/25-26/151 | L145: =VLOOKUP(K145,'Job Costing'!$A$5:$B$23,2,0) -> 2000 | M145: =VLOOKUP(D145,'Data - Items'!$A$4:$I$35,9,0) -> Foam | N145: =IF(M145="Timber",F145*VLOOKUP(D145,'Data - Items'!$A$4:$H$35,8,0),0) -> 0
A146: 12045 | B146: 46099 | D146: 1900137 | E146: NAILS (AS REQUIRED) | F146: 6 | G146: SETS | H146: 90 | I146: 540 | J146: PKG J/25-26/151 | K146: J/25-26/151 | L146: =VLOOKUP(K146,'Job Costing'!$A$5:$B$23,2,0) -> 2000 | M146: =VLOOKUP(D146,'Data - Items'!$A$4:$I$35,9,0) -> Nails | N146: =IF(M146="Timber",F146*VLOOKUP(D146,'Data - Items'!$A$4:$H$35,8,0),0) -> 0
A147: 12045 | B147: 46099 | D147: 1900151 | E147: RATCHET LASHING BELT 8 M LG X 50 MM WD WITH LOCK | F147: 12 | G147: NOS | H147: 900 | I147: 10800 | J147: PKG J/25-26/151 | K147: J/25-26/151 | L147: =VLOOKUP(K147,'Job Costing'!$A$5:$B$23,2,0) -> 2000 | M147: =VLOOKUP(D147,'Data - Items'!$A$4:$I$35,9,0) -> Ratchet belt | N147: =IF(M147="Timber",F147*VLOOKUP(D147,'Data - Items'!$A$4:$H$35,8,0),0) -> 0
A148: 12045 | B148: 46099 | D148: 1900160 | E148: STRETCH FILM 50 MICRON | F148: 14.3 | G148: KG | H148: 166 | I148: 2373.8 | J148: PKG J/25-26/151 | K148: J/25-26/151 | L148: =VLOOKUP(K148,'Job Costing'!$A$5:$B$23,2,0) -> 2000 | M148: =VLOOKUP(D148,'Data - Items'!$A$4:$I$35,9,0) -> Stretch film | N148: =IF(M148="Timber",F148*VLOOKUP(D148,'Data - Items'!$A$4:$H$35,8,0),0) -> 0
A149: 12045 | B149: 46099 | D149: 1900117 | E149: WOODEN BATTEN 100 X 100 X 1300 LG | F149: 19 | G149: NOS | H149: 330.55 | I149: 6280.45 | J149: PKG J/25-26/151 | K149: J/25-26/151 | L149: =VLOOKUP(K149,'Job Costing'!$A$5:$B$23,2,0) -> 2000 | M149: =VLOOKUP(D149,'Data - Items'!$A$4:$I$35,9,0) -> Timber | N149: =IF(M149="Timber",F149*VLOOKUP(D149,'Data - Items'!$A$4:$H$35,8,0),0) -> 8.72157
A150: 12045 | B150: 46099 | D150: 1900130 | E150: WOODEN BATTEN 100 X 75 X 100 LG | F150: 20 | G150: NOS | H150: 19.07 | I150: 381.4 | J150: PKG J/25-26/151 | K150: J/25-26/151 | L150: =VLOOKUP(K150,'Job Costing'!$A$5:$B$23,2,0) -> 2000 | M150: =VLOOKUP(D150,'Data - Items'!$A$4:$I$35,9,0) -> Timber | N150: =IF(M150="Timber",F150*VLOOKUP(D150,'Data - Items'!$A$4:$H$35,8,0),0) -> 0.52965
A151: 12045 | B151: 46099 | D151: 1900127 | E151: WOODEN BATTEN 150 X 150 X 300 LG | F151: 23 | G151: NOS | H151: 171.63 | I151: 3947.49 | J151: PKG J/25-26/151 | K151: J/25-26/151 | L151: =VLOOKUP(K151,'Job Costing'!$A$5:$B$23,2,0) -> 2000 | M151: =VLOOKUP(D151,'Data - Items'!$A$4:$I$35,9,0) -> Timber | N151: =IF(M151="Timber",F151*VLOOKUP(D151,'Data - Items'!$A$4:$H$35,8,0),0) -> 5.4818775
A152: 12045 | B152: 46099 | D152: 1900124 | E152: WOODEN BATTEN 150 X 75 X 1300 LG | F152: 11 | G152: NOS | H152: 371.86 | I152: 4090.46 | J152: PKG J/25-26/151 | K152: J/25-26/151 | L152: =VLOOKUP(K152,'Job Costing'!$A$5:$B$23,2,0) -> 2000 | M152: =VLOOKUP(D152,'Data - Items'!$A$4:$I$35,9,0) -> Timber | N152: =IF(M152="Timber",F152*VLOOKUP(D152,'Data - Items'!$A$4:$H$35,8,0),0) -> 5.6804963
A153: 12045 | B153: 46099 | D153: 1900114 | E153: WOODEN BATTEN 150 X 75 X 2450 LG | F153: 15 | G153: NOS | H153: 700.82 | I153: 10512.3 | J153: PKG J/25-26/151 | K153: J/25-26/151 | L153: =VLOOKUP(K153,'Job Costing'!$A$5:$B$23,2,0) -> 2000 | M153: =VLOOKUP(D153,'Data - Items'!$A$4:$I$35,9,0) -> Timber | N153: =IF(M153="Timber",F153*VLOOKUP(D153,'Data - Items'!$A$4:$H$35,8,0),0) -> 14.598478
A154: 12053 | B154: 46106 | C154: J/25-26/152 | D154: 1900162 | E154: AIR BUBBLE WRAP | F154: 2 | G154: ROLL | H154: 680 | I154: 1360 | K154: J/25-26/152 | L154: =VLOOKUP(K154,'Job Costing'!$A$5:$B$23,2,0) -> 1400 | M154: =VLOOKUP(D154,'Data - Items'!$A$4:$I$35,9,0) -> Bubble wrap | N154: =IF(M154="Timber",F154*VLOOKUP(D154,'Data - Items'!$A$4:$H$35,8,0),0) -> 0
A155: 12053 | B155: 46106 | C155: J/25-26/152 | D155: 1900158 | E155: GUM TAPE 3" | F155: 2 | G155: NOS | H155: 78 | I155: 156 | K155: J/25-26/152 | L155: =VLOOKUP(K155,'Job Costing'!$A$5:$B$23,2,0) -> 1400 | M155: =VLOOKUP(D155,'Data - Items'!$A$4:$I$35,9,0) -> Gum tape | N155: =IF(M155="Timber",F155*VLOOKUP(D155,'Data - Items'!$A$4:$H$35,8,0),0) -> 0
A156: 12053 | B156: 46106 | C156: J/25-26/152 | D156: 1900144 | E156: KINI FOAM 12 MM THK X 1400 MM WD | F156: 2 | G156: ROLL | H156: 2100 | I156: 4200 | K156: J/25-26/152 | L156: =VLOOKUP(K156,'Job Costing'!$A$5:$B$23,2,0) -> 1400 | M156: =VLOOKUP(D156,'Data - Items'!$A$4:$I$35,9,0) -> Foam | N156: =IF(M156="Timber",F156*VLOOKUP(D156,'Data - Items'!$A$4:$H$35,8,0),0) -> 0
A157: 12053 | B157: 46106 | C157: J/25-26/152 | D157: 1900137 | E157: NAILS (AS REQUIRED) | F157: 4 | G157: SETS | H157: 90 | I157: 360 | K157: J/25-26/152 | L157: =VLOOKUP(K157,'Job Costing'!$A$5:$B$23,2,0) -> 1400 | M157: =VLOOKUP(D157,'Data - Items'!$A$4:$I$35,9,0) -> Nails | N157: =IF(M157="Timber",F157*VLOOKUP(D157,'Data - Items'!$A$4:$H$35,8,0),0) -> 0
A158: 12053 | B158: 46106 | C158: J/25-26/152 | D158: 1900222 | E158: PLY COVER 12 MM (MANHOLE/NOZZLE) | F158: 17 | G158: NOS | H158: 160 | I158: 2720 | K158: J/25-26/152 | L158: =VLOOKUP(K158,'Job Costing'!$A$5:$B$23,2,0) -> 1400 | M158: =VLOOKUP(D158,'Data - Items'!$A$4:$I$35,9,0) -> Ply cover | N158: =IF(M158="Timber",F158*VLOOKUP(D158,'Data - Items'!$A$4:$H$35,8,0),0) -> 0
A159: 12053 | B159: 46106 | C159: J/25-26/152 | D159: 1900151 | E159: RATCHET LASHING BELT 8 M LG X 50 MM WD WITH LOCK | F159: 7 | G159: NOS | H159: 900 | I159: 6300 | K159: J/25-26/152 | L159: =VLOOKUP(K159,'Job Costing'!$A$5:$B$23,2,0) -> 1400 | M159: =VLOOKUP(D159,'Data - Items'!$A$4:$I$35,9,0) -> Ratchet belt | N159: =IF(M159="Timber",F159*VLOOKUP(D159,'Data - Items'!$A$4:$H$35,8,0),0) -> 0
A160: 12053 | B160: 46106 | C160: J/25-26/152 | D160: 1900160 | E160: STRETCH FILM 50 MICRON | F160: 7.4 | G160: KG | H160: 166 | I160: 1228.4 | K160: J/25-26/152 | L160: =VLOOKUP(K160,'Job Costing'!$A$5:$B$23,2,0) -> 1400 | M160: =VLOOKUP(D160,'Data - Items'!$A$4:$I$35,9,0) -> Stretch film | N160: =IF(M160="Timber",F160*VLOOKUP(D160,'Data - Items'!$A$4:$H$35,8,0),0) -> 0
A161: 12053 | B161: 46106 | C161: J/25-26/152 | D161: 1900171 | E161: WOODEN BATTEN 100 X 100 X 900 LG | F161: 12 | G161: NOS | H161: 235.8 | I161: 2829.6 | K161: J/25-26/152 | L161: =VLOOKUP(K161,'Job Costing'!$A$5:$B$23,2,0) -> 1400 | M161: =VLOOKUP(D161,'Data - Items'!$A$4:$I$35,9,0) -> Timber | N161: =IF(M161="Timber",F161*VLOOKUP(D161,'Data - Items'!$A$4:$H$35,8,0),0) -> 3.81348
A162: 12053 | B162: 46106 | C162: J/25-26/152 | D162: 1900130 | E162: WOODEN BATTEN 100 X 75 X 100 LG | F162: 12 | G162: NOS | H162: 19.65 | I162: 235.8 | K162: J/25-26/152 | L162: =VLOOKUP(K162,'Job Costing'!$A$5:$B$23,2,0) -> 1400 | M162: =VLOOKUP(D162,'Data - Items'!$A$4:$I$35,9,0) -> Timber | N162: =IF(M162="Timber",F162*VLOOKUP(D162,'Data - Items'!$A$4:$H$35,8,0),0) -> 0.31779
A163: 12053 | B163: 46106 | C163: J/25-26/152 | D163: 1900127 | E163: WOODEN BATTEN 150 X 150 X 300 LG | F163: 12 | G163: NOS | H163: 176.85 | I163: 2122.2 | K163: J/25-26/152 | L163: =VLOOKUP(K163,'Job Costing'!$A$5:$B$23,2,0) -> 1400 | M163: =VLOOKUP(D163,'Data - Items'!$A$4:$I$35,9,0) -> Timber | N163: =IF(M163="Timber",F163*VLOOKUP(D163,'Data - Items'!$A$4:$H$35,8,0),0) -> 2.86011
A164: 12053 | B164: 46106 | C164: J/25-26/152 | D164: 1900169 | E164: WOODEN BATTEN 150 X 75 X 2550 LG | F164: 8 | G164: NOS | H164: 751.61 | I164: 6012.88 | K164: J/25-26/152 | L164: =VLOOKUP(K164,'Job Costing'!$A$5:$B$23,2,0) -> 1400 | M164: =VLOOKUP(D164,'Data - Items'!$A$4:$I$35,9,0) -> Timber | N164: =IF(M164="Timber",F164*VLOOKUP(D164,'Data - Items'!$A$4:$H$35,8,0),0) -> 8.103645
A165: 12053 | B165: 46106 | C165: J/25-26/152 | D165: 1900178 | E165: WOODEN BATTEN 150 X 75 X 900 LG | F165: 7 | G165: NOS | H165: 265.27 | I165: 1856.89 | K165: J/25-26/152 | L165: =VLOOKUP(K165,'Job Costing'!$A$5:$B$23,2,0) -> 1400 | M165: =VLOOKUP(D165,'Data - Items'!$A$4:$I$35,9,0) -> Timber | N165: =IF(M165="Timber",F165*VLOOKUP(D165,'Data - Items'!$A$4:$H$35,8,0),0) -> 2.5025962
... A216: 12128 | B216: 46155 | C216: J/25-26/164 | D216: 1900196 | E216: WOODEN BATTEN 200 X 200 X 400 LG | F216: 14 | G216: NOS | H216: 419.2 | I216: 5868.8 | K216: J/25-26/164 | L216: =VLOOKUP(K216,'Job Costing'!$A$5:$B$23,2,0) -> 2400 | M216: =VLOOKUP(D216,'Data - Items'!$A$4:$I$35,9,0) -> Timber | N216: =IF(M216="Timber",F216*VLOOKUP(D216,'Data - Items'!$A$4:$H$35,8,0),0) -> 7.90944
A217: 12134 | B217: 46156 | C217: J/25-26/164 | D217: 1900144 | E217: KINI FOAM 12 MM THK X 1400 MM WD | F217: 1 | G217: ROLL | H217: 2100 | I217: 2100 | J217: SHORT ISSUED EARLIER | K217: J/25-26/164 | L217: =VLOOKUP(K217,'Job Costing'!$A$5:$B$23,2,0) -> 2400 | M217: =VLOOKUP(D217,'Data - Items'!$A$4:$I$35,9,0) -> Foam | N217: =IF(M217="Timber",F217*VLOOKUP(D217,'Data - Items'!$A$4:$H$35,8,0),0) -> 0
A218: 12142 | B218: 46176 | C218: J/25-26/165 | D218: 1900162 | E218: AIR BUBBLE WRAP | F218: 1 | G218: ROLL | H218: 680 | I218: 680 | K218: J/25-26/165 | L218: =VLOOKUP(K218,'Job Costing'!$A$5:$B$23,2,0) -> 1600 | M218: =VLOOKUP(D218,'Data - Items'!$A$4:$I$35,9,0) -> Bubble wrap | N218: =IF(M218="Timber",F218*VLOOKUP(D218,'Data - Items'!$A$4:$H$35,8,0),0) -> 0
A219: 12142 | B219: 46176 | C219: J/25-26/165 | D219: 1900158 | E219: GUM TAPE 3" | F219: 1 | G219: NOS | H219: 78 | I219: 78 | K219: J/25-26/165 | L219: =VLOOKUP(K219,'Job Costing'!$A$5:$B$23,2,0) -> 1600 | M219: =VLOOKUP(D219,'Data - Items'!$A$4:$I$35,9,0) -> Gum tape | N219: =IF(M219="Timber",F219*VLOOKUP(D219,'Data - Items'!$A$4:$H$35,8,0),0) -> 0
A220: 12142 | B220: 46176 | C220: J/25-26/165 | D220: 1900144 | E220: KINI FOAM 12 MM THK X 1400 MM WD | F220: 1 | G220: ROLL | H220: 2100 | I220: 2100 | K220: J/25-26/165 | L220: =VLOOKUP(K220,'Job Costing'!$A$5:$B$23,2,0) -> 1600 | M220: =VLOOKUP(D220,'Data - Items'!$A$4:$I$35,9,0) -> Foam | N220: =IF(M220="Timber",F220*VLOOKUP(D220,'Data - Items'!$A$4:$H$35,8,0),0) -> 0
A221: 12142 | B221: 46176 | C221: J/25-26/165 | D221: 1900137 | E221: NAILS (AS REQUIRED) | F221: 2 | G221: SETS | H221: 90 | I221: 180 | K221: J/25-26/165 | L221: =VLOOKUP(K221,'Job Costing'!$A$5:$B$23,2,0) -> 1600 | M221: =VLOOKUP(D221,'Data - Items'!$A$4:$I$35,9,0) -> Nails | N221: =IF(M221="Timber",F221*VLOOKUP(D221,'Data - Items'!$A$4:$H$35,8,0),0) -> 0
A222: 12142 | B222: 46176 | C222: J/25-26/165 | D222: 1900222 | E222: PLY COVER 12 MM (MANHOLE/NOZZLE) | F222: 6 | G222: NOS | H222: 160 | I222: 960 | K222: J/25-26/165 | L222: =VLOOKUP(K222,'Job Costing'!$A$5:$B$23,2,0) -> 1600 | M222: =VLOOKUP(D222,'Data - Items'!$A$4:$I$35,9,0) -> Ply cover | N222: =IF(M222="Timber",F222*VLOOKUP(D222,'Data - Items'!$A$4:$H$35,8,0),0) -> 0
A223: 12142 | B223: 46176 | C223: J/25-26/165 | D223: 1900151 | E223: RATCHET LASHING BELT 8 M LG X 50 MM WD WITH LOCK | F223: 3 | G223: NOS | H223: 900 | I223: 2700 | K223: J/25-26/165 | L223: =VLOOKUP(K223,'Job Costing'!$A$5:$B$23,2,0) -> 1600 | M223: =VLOOKUP(D223,'Data - Items'!$A$4:$I$35,9,0) -> Ratchet belt | N223: =IF(M223="Timber",F223*VLOOKUP(D223,'Data - Items'!$A$4:$H$35,8,0),0) -> 0
A224: 12142 | B224: 46176 | C224: J/25-26/165 | D224: 1900160 | E224: STRETCH FILM 50 MICRON | F224: 3.4 | G224: KG | H224: 166 | I224: 564.4 | K224: J/25-26/165 | L224: =VLOOKUP(K224,'Job Costing'!$A$5:$B$23,2,0) -> 1600 | M224: =VLOOKUP(D224,'Data - Items'!$A$4:$I$35,9,0) -> Stretch film | N224: =IF(M224="Timber",F224*VLOOKUP(D224,'Data - Items'!$A$4:$H$35,8,0),0) -> 0
A225: 12142 | B225: 46176 | C225: J/25-26/164 | D225: 1900180 | E225: WOODEN BATTEN 100 X 100 X 1050 LG | F225: 5 | G225: NOS | H225: 275.1 | I225: 1375.5 | K225: J/25-26/165 | L225: =VLOOKUP(K225,'Job Costing'!$A$5:$B$23,2,0) -> 1600 | M225: =VLOOKUP(D225,'Data - Items'!$A$4:$I$35,9,0) -> Timber | N225: =IF(M225="Timber",F225*VLOOKUP(D225,'Data - Items'!$A$4:$H$35,8,0),0) -> 1.853775
A226: 12142 | B226: 46176 | C226: J/25-26/165 | D226: 1900130 | E226: WOODEN BATTEN 100 X 75 X 100 LG | F226: 5 | G226: NOS | H226: 19.65 | I226: 98.25 | K226: J/25-26/165 | L226: =VLOOKUP(K226,'Job Costing'!$A$5:$B$23,2,0) -> 1600 | M226: =VLOOKUP(D226,'Data - Items'!$A$4:$I$35,9,0) -> Timber | N226: =IF(M226="Timber",F226*VLOOKUP(D226,'Data - Items'!$A$4:$H$35,8,0),0) -> 0.1324125
A227: 12142 | B227: 46176 | C227: J/25-26/165 | D227: 1900127 | E227: WOODEN BATTEN 150 X 150 X 300 LG | F227: 3 | G227: NOS | H227: 176.85 | I227: 530.55 | K227: J/25-26/165 | L227: =VLOOKUP(K227,'Job Costing'!$A$5:$B$23,2,0) -> 1600 | M227: =VLOOKUP(D227,'Data - Items'!$A$4:$I$35,9,0) -> Timber | N227: =IF(M227="Timber",F227*VLOOKUP(D227,'Data - Items'!$A$4:$H$35,8,0),0) -> 0.7150275
A228: 12142 | B228: 46176 | C228: J/25-26/164 | D228: 1900183 | E228: WOODEN BATTEN 150 X 75 X 1050 LG | F228: 2 | G228: NOS | H228: 309.49 | I228: 618.98 | K228: J/25-26/165 | L228: =VLOOKUP(K228,'Job Costing'!$A$5:$B$23,2,0) -> 1600 | M228: =VLOOKUP(D228,'Data - Items'!$A$4:$I$35,9,0) -> Timber | N228: =IF(M228="Timber",F228*VLOOKUP(D228,'Data - Items'!$A$4:$H$35,8,0),0) -> 0.83419875
A229: 12142 | B229: 46176 | C229: J/25-26/165 | D229: 1900179 | E229: WOODEN BATTEN 150 X 75 X 2650 LG | F229: 4 | G229: NOS | H229: 781.09 | I229: 3124.36 | K229: J/25-26/165 | L229: =VLOOKUP(K229,'Job Costing'!$A$5:$B$23,2,0) -> 1600 | M229: =VLOOKUP(D229,'Data - Items'!$A$4:$I$35,9,0) -> Timber | N229: =IF(M229="Timber",F229*VLOOKUP(D229,'Data - Items'!$A$4:$H$35,8,0),0) -> 4.2107175
... A253: 12186 | B253: 46225 | C253: J/26-27/018 | D253: 1900114 | E253: WOODEN BATTEN 150 X 75 X 2450 LG | F253: 18 | G253: NOS | H253: 744.62 | I253: 13403.16 | K253: J/26-27/018 | L253: =VLOOKUP(K253,'Job Costing'!$A$5:$B$23,2,0) -> 2000 | M253: =VLOOKUP(D253,'Data - Items'!$A$4:$I$35,9,0) -> Timber | N253: =IF(M253="Timber",F253*VLOOKUP(D253,'Data - Items'!$A$4:$H$35,8,0),0) -> 17.518174
A254: 12202 | B254: 46229 | C254: J/26-27/018 | D254: 1900162 | E254: AIR BUBBLE WRAP | F254: 1 | G254: ROLL | H254: 680 | I254: 680 | J254: RE-WRAP 2 VSL (RAIN) | K254: J/26-27/018 | L254: =VLOOKUP(K254,'Job Costing'!$A$5:$B$23,2,0) -> 2000 | M254: =VLOOKUP(D254,'Data - Items'!$A$4:$I$35,9,0) -> Bubble wrap | N254: =IF(M254="Timber",F254*VLOOKUP(D254,'Data - Items'!$A$4:$H$35,8,0),0) -> 0

Sheet Data - Labour
A1: Packing labour log - contractor (kept from Feb-26), pasted as values
A2: Before Feb-26 no labour record was kept.
A4: Date | B4: Category | C4: Nos | D4: Hrs/head | E4: OT hrs (tot) | F4: Man-hrs | G4: Job | H4: Work done | I4: Remarks | J4: Date (fixed) | K4: Hrs (fixed) | L4: Include? | M4: Man-hrs | N4: OT hrs
A5: 46064 | B5: Mistri | C5: 1 | D5: 8.5 | E5: 0.5 | F5: 8.5 | G5: J/25-26/139 | H5: Pallet / saddle making | J5: =IF(B5="","",IF(ISNUMBER(A5),A5,DATE(2000+VALUE(RIGHT(A5,2)),VALUE(MID(A5,4,2)),VALUE(LEFT(A5,2))))) -> 46064 | K5: =IF(B5="","",D5) -> 8.5 | L5: =IF(AND(OR(B5="Mistri",B5="Jogali"),G5<>""),"Y","N") -> Y | M5: =IF(L5="Y",C5*K5,0) -> 8.5 | N5: =IF(L5="Y",E5,0) -> 0.5
A6: 46064 | B6: Jogali | C6: 1 | D6: 8.5 | E6: 0.5 | F6: 8.5 | G6: J/25-26/139 | H6: helping mistri / shifting | J6: =IF(B6="","",IF(ISNUMBER(A6),A6,DATE(2000+VALUE(RIGHT(A6,2)),VALUE(MID(A6,4,2)),VALUE(LEFT(A6,2))))) -> 46064 | K6: =IF(B6="","",D6) -> 8.5 | L6: =IF(AND(OR(B6="Mistri",B6="Jogali"),G6<>""),"Y","N") -> Y | M6: =IF(L6="Y",C6*K6,0) -> 8.5 | N6: =IF(L6="Y",E6,0) -> 0.5
A7: 46065 | B7: Jogali | C7: 2 | D7: 5 | F7: 10 | G7: J/25-26/139 | H7: Foam / bubble / stretch + lashing | J7: =IF(B7="","",IF(ISNUMBER(A7),A7,DATE(2000+VALUE(RIGHT(A7,2)),VALUE(MID(A7,4,2)),VALUE(LEFT(A7,2))))) -> 46065 | K7: =IF(B7="","",D7) -> 5 | L7: =IF(AND(OR(B7="Mistri",B7="Jogali"),G7<>""),"Y","N") -> Y | M7: =IF(L7="Y",C7*K7,0) -> 10 | N7: =IF(L7="Y",E7,0) -> 0
A8: 46065 | B8: Jogali | C8: 2 | D8: 8 | F8: 16 | H8: misc - production help | J8: =IF(B8="","",IF(ISNUMBER(A8),A8,DATE(2000+VALUE(RIGHT(A8,2)),VALUE(MID(A8,4,2)),VALUE(LEFT(A8,2))))) -> 46065 | K8: =IF(B8="","",D8) -> 8 | L8: =IF(AND(OR(B8="Mistri",B8="Jogali"),G8<>""),"Y","N") -> N | M8: =IF(L8="Y",C8*K8,0) -> 0 | N8: =IF(L8="Y",E8,0) -> 0
A9: 46071 | B9: Mistri | C9: 2 | D9: 5.5 | F9: 11 | G9: J/25-26/143 | H9: Pallet / saddle making | I9: rain - work stopped 2 hrs | J9: =IF(B9="","",IF(ISNUMBER(A9),A9,DATE(2000+VALUE(RIGHT(A9,2)),VALUE(MID(A9,4,2)),VALUE(LEFT(A9,2))))) -> 46071 | K9: =IF(B9="","",D9) -> 5.5 | L9: =IF(AND(OR(B9="Mistri",B9="Jogali"),G9<>""),"Y","N") -> Y | M9: =IF(L9="Y",C9*K9,0) -> 11 | N9: =IF(L9="Y",E9,0) -> 0
A10: 46071 | B10: Jogali | C10: 1 | D10: 5.5 | F10: 5.5 | G10: J/25-26/143 | H10: helping mistri / shifting | J10: =IF(B10="","",IF(ISNUMBER(A10),A10,DATE(2000+VALUE(RIGHT(A10,2)),VALUE(MID(A10,4,2)),VALUE(LEFT(A10,2))))) -> 46071 | K10: =IF(B10="","",D10) -> 5.5 | L10: =IF(AND(OR(B10="Mistri",B10="Jogali"),G10<>""),"Y","N") -> Y | M10: =IF(L10="Y",C10*K10,0) -> 5.5 | N10: =IF(L10="Y",E10,0) -> 0
A11: 46072 | B11: Jogali | C11: 2 | D11: 7.5 | F11: 15 | G11: J/25-26/143 | H11: Foam / bubble / stretch + lashing | J11: =IF(B11="","",IF(ISNUMBER(A11),A11,DATE(2000+VALUE(RIGHT(A11,2)),VALUE(MID(A11,4,2)),VALUE(LEFT(A11,2))))) -> 46072 | K11: =IF(B11="","",D11) -> 7.5 | L11: =IF(AND(OR(B11="Mistri",B11="Jogali"),G11<>""),"Y","N") -> Y | M11: =IF(L11="Y",C11*K11,0) -> 15 | N11: =IF(L11="Y",E11,0) -> 0
A12: 46078 | B12: Mistri | C12: 2 | D12: 5.5 | F12: 11 | G12: J/25-26/137 | H12: Pallet / saddle making | J12: =IF(B12="","",IF(ISNUMBER(A12),A12,DATE(2000+VALUE(RIGHT(A12,2)),VALUE(MID(A12,4,2)),VALUE(LEFT(A12,2))))) -> 46078 | K12: =IF(B12="","",D12) -> 5.5 | L12: =IF(AND(OR(B12="Mistri",B12="Jogali"),G12<>""),"Y","N") -> Y | M12: =IF(L12="Y",C12*K12,0) -> 11 | N12: =IF(L12="Y",E12,0) -> 0
A13: 46078 | B13: Jogali | C13: 1 | D13: 5.5 | F13: 5.5 | G13: J/25-26/137 | H13: helping mistri / shifting | J13: =IF(B13="","",IF(ISNUMBER(A13),A13,DATE(2000+VALUE(RIGHT(A13,2)),VALUE(MID(A13,4,2)),VALUE(LEFT(A13,2))))) -> 46078 | K13: =IF(B13="","",D13) -> 5.5 | L13: =IF(AND(OR(B13="Mistri",B13="Jogali"),G13<>""),"Y","N") -> Y | M13: =IF(L13="Y",C13*K13,0) -> 5.5 | N13: =IF(L13="Y",E13,0) -> 0
A14: 46079 | B14: Jogali | C14: 2 | D14: 8.5 | E14: 1 | F14: 17 | G14: J/25-26/137 | H14: Foam / bubble / stretch + lashing + tarpaulin | J14: =IF(B14="","",IF(ISNUMBER(A14),A14,DATE(2000+VALUE(RIGHT(A14,2)),VALUE(MID(A14,4,2)),VALUE(LEFT(A14,2))))) -> 46079 | K14: =IF(B14="","",D14) -> 8.5 | L14: =IF(AND(OR(B14="Mistri",B14="Jogali"),G14<>""),"Y","N") -> Y | M14: =IF(L14="Y",C14*K14,0) -> 17 | N14: =IF(L14="Y",E14,0) -> 1
A15: 46081 | B15: Mistri | C15: 3 | D15: 9.5 | E15: 4.5 | F15: 28.5 | G15: J/25-26/145 | H15: Pallet / saddle making | I15: rain - work stopped 2 hrs | J15: =IF(B15="","",IF(ISNUMBER(A15),A15,DATE(2000+VALUE(RIGHT(A15,2)),VALUE(MID(A15,4,2)),VALUE(LEFT(A15,2))))) -> 46081 | K15: =IF(B15="","",D15) -> 9.5 | L15: =IF(AND(OR(B15="Mistri",B15="Jogali"),G15<>""),"Y","N") -> Y | M15: =IF(L15="Y",C15*K15,0) -> 28.5 | N15: =IF(L15="Y",E15,0) -> 4.5
A16: 46081 | B16: Jogali | C16: 1 | D16: 9.5 | E16: 1.5 | F16: 9.5 | G16: J/25-26/145 | H16: helping mistri / shifting | J16: =IF(B16="","",IF(ISNUMBER(A16),A16,DATE(2000+VALUE(RIGHT(A16,2)),VALUE(MID(A16,4,2)),VALUE(LEFT(A16,2))))) -> 46081 | K16: =IF(B16="","",D16) -> 9.5 | L16: =IF(AND(OR(B16="Mistri",B16="Jogali"),G16<>""),"Y","N") -> Y | M16: =IF(L16="Y",C16*K16,0) -> 9.5 | N16: =IF(L16="Y",E16,0) -> 1.5
A17: Total Feb-26 | E17: 8 | F17: 146 | J17: =IF(B17="","",IF(ISNUMBER(A17),A17,DATE(2000+VALUE(RIGHT(A17,2)),VALUE(MID(A17,4,2)),VALUE(LEFT(A17,2))))) | K17: =IF(B17="","",D17) | L17: =IF(AND(OR(B17="Mistri",B17="Jogali"),G17<>""),"Y","N") -> N | M17: =IF(L17="Y",C17*K17,0) -> 0 | N17: =IF(L17="Y",E17,0) -> 0
A19: 02.03.26 | B19: Mistri | C19: 3 | D19: 6 | F19: 18 | G19: J/25-26/145 | H19: Pallet / saddle making | J19: =IF(B19="","",IF(ISNUMBER(A19),A19,DATE(2000+VALUE(RIGHT(A19,2)),VALUE(MID(A19,4,2)),VALUE(LEFT(A19,2))))) -> 46083 | K19: =IF(B19="","",D19) -> 6 | L19: =IF(AND(OR(B19="Mistri",B19="Jogali"),G19<>""),"Y","N") -> Y | M19: =IF(L19="Y",C19*K19,0) -> 18 | N19: =IF(L19="Y",E19,0) -> 0
A20: 46083 | B20: Jogali | C20: 1 | D20: 6 | F20: 6 | G20: J/25-26/145 | H20: helping mistri / shifting | J20: =IF(B20="","",IF(ISNUMBER(A20),A20,DATE(2000+VALUE(RIGHT(A20,2)),VALUE(MID(A20,4,2)),VALUE(LEFT(A20,2))))) -> 46083 | K20: =IF(B20="","",D20) -> 6 | L20: =IF(AND(OR(B20="Mistri",B20="Jogali"),G20<>""),"Y","N") -> Y | M20: =IF(L20="Y",C20*K20,0) -> 6 | N20: =IF(L20="Y",E20,0) -> 0
A21: 46084 | B21: Jogali | C21: 3 | D21: 9 | E21: 3 | F21: 27 | G21: J/25-26/145 | H21: Foam / bubble / stretch + lashing + tarpaulin | J21: =IF(B21="","",IF(ISNUMBER(A21),A21,DATE(2000+VALUE(RIGHT(A21,2)),VALUE(MID(A21,4,2)),VALUE(LEFT(A21,2))))) -> 46084 | K21: =IF(B21="","",D21) -> 9 | L21: =IF(AND(OR(B21="Mistri",B21="Jogali"),G21<>""),"Y","N") -> Y | M21: =IF(L21="Y",C21*K21,0) -> 27 | N21: =IF(L21="Y",E21,0) -> 3
A22: 46085 | B22: Jogali | C22: 3 | D22: 9 | E22: 3 | F22: 27 | G22: J/25-26/145 | H22: Foam / bubble / stretch + lashing + tarpaulin | J22: =IF(B22="","",IF(ISNUMBER(A22),A22,DATE(2000+VALUE(RIGHT(A22,2)),VALUE(MID(A22,4,2)),VALUE(LEFT(A22,2))))) -> 46085 | K22: =IF(B22="","",D22) -> 9 | L22: =IF(AND(OR(B22="Mistri",B22="Jogali"),G22<>""),"Y","N") -> Y | M22: =IF(L22="Y",C22*K22,0) -> 27 | N22: =IF(L22="Y",E22,0) -> 3
A23: 46086 | B23: Jogali | C23: 3 | D23: 7.5 | F23: 22.5 | G23: J/25-26/145 | H23: Foam / bubble / stretch + lashing + tarpaulin | J23: =IF(B23="","",IF(ISNUMBER(A23),A23,DATE(2000+VALUE(RIGHT(A23,2)),VALUE(MID(A23,4,2)),VALUE(LEFT(A23,2))))) -> 46086 | K23: =IF(B23="","",D23) -> 7.5 | L23: =IF(AND(OR(B23="Mistri",B23="Jogali"),G23<>""),"Y","N") -> Y | M23: =IF(L23="Y",C23*K23,0) -> 22.5 | N23: =IF(L23="Y",E23,0) -> 0
A24: 46086 | B24: Jogali | C24: 2 | D24: 8 | F24: 16 | H24: timber unloading | J24: =IF(B24="","",IF(ISNUMBER(A24),A24,DATE(2000+VALUE(RIGHT(A24,2)),VALUE(MID(A24,4,2)),VALUE(LEFT(A24,2))))) -> 46086 | K24: =IF(B24="","",D24) -> 8 | L24: =IF(AND(OR(B24="Mistri",B24="Jogali"),G24<>""),"Y","N") -> N | M24: =IF(L24="Y",C24*K24,0) -> 0 | N24: =IF(L24="Y",E24,0) -> 0
A25: 16.03.26 | B25: Mistri | C25: 2 | D25: 9 | E25: 2 | F25: 18 | G25: J/25-26/151 | H25: Pallet / saddle making | J25: =IF(B25="","",IF(ISNUMBER(A25),A25,DATE(2000+VALUE(RIGHT(A25,2)),VALUE(MID(A25,4,2)),VALUE(LEFT(A25,2))))) -> 46097 | K25: =IF(B25="","",D25) -> 9 | L25: =IF(AND(OR(B25="Mistri",B25="Jogali"),G25<>""),"Y","N") -> Y | M25: =IF(L25="Y",C25*K25,0) -> 18 | N25: =IF(L25="Y",E25,0) -> 2
A26: 46097 | B26: Jogali | C26: 1 | D26: 9 | E26: 1 | F26: 9 | G26: J/25-26/151 | H26: helping mistri / shifting | J26: =IF(B26="","",IF(ISNUMBER(A26),A26,DATE(2000+VALUE(RIGHT(A26,2)),VALUE(MID(A26,4,2)),VALUE(LEFT(A26,2))))) -> 46097 | K26: =IF(B26="","",D26) -> 9 | L26: =IF(AND(OR(B26="Mistri",B26="Jogali"),G26<>""),"Y","N") -> Y | M26: =IF(L26="Y",C26*K26,0) -> 9 | N26: =IF(L26="Y",E26,0) -> 1
A27: 17.03.26 | B27: Mistri | C27: 2 | D27: 1 | F27: 2 | G27: J/25-26/151 | H27: Pallet / saddle making | J27: =IF(B27="","",IF(ISNUMBER(A27),A27,DATE(2000+VALUE(RIGHT(A27,2)),VALUE(MID(A27,4,2)),VALUE(LEFT(A27,2))))) -> 46098 | K27: =IF(B27="","",D27) -> 1 | L27: =IF(AND(OR(B27="Mistri",B27="Jogali"),G27<>""),"Y","N") -> Y | M27: =IF(L27="Y",C27*K27,0) -> 2 | N27: =IF(L27="Y",E27,0) -> 0
A28: 46098 | B28: Jogali | C28: 1 | D28: 1 | F28: 1 | G28: J/25-26/151 | H28: helping mistri / shifting | J28: =IF(B28="","",IF(ISNUMBER(A28),A28,DATE(2000+VALUE(RIGHT(A28,2)),VALUE(MID(A28,4,2)),VALUE(LEFT(A28,2))))) -> 46098 | K28: =IF(B28="","",D28) -> 1 | L28: =IF(AND(OR(B28="Mistri",B28="Jogali"),G28<>""),"Y","N") -> Y | M28: =IF(L28="Y",C28*K28,0) -> 1 | N28: =IF(L28="Y",E28,0) -> 0
A29: 46099 | B29: Jogali | C29: 3 | D29: 9 | E29: 3 | F29: 27 | G29: J/25-26/151 | H29: Foam / bubble / stretch + lashing | J29: =IF(B29="","",IF(ISNUMBER(A29),A29,DATE(2000+VALUE(RIGHT(A29,2)),VALUE(MID(A29,4,2)),VALUE(LEFT(A29,2))))) -> 46099 | K29: =IF(B29="","",D29) -> 9 | L29: =IF(AND(OR(B29="Mistri",B29="Jogali"),G29<>""),"Y","N") -> Y | M29: =IF(L29="Y",C29*K29,0) -> 27 | N29: =IF(L29="Y",E29,0) -> 3
A30: 46100 | B30: Jogali | C30: 3 | D30: 3 | F30: 9 | G30: J/25-26/151 | H30: Foam / bubble / stretch + lashing | J30: =IF(B30="","",IF(ISNUMBER(A30),A30,DATE(2000+VALUE(RIGHT(A30,2)),VALUE(MID(A30,4,2)),VALUE(LEFT(A30,2))))) -> 46100 | K30: =IF(B30="","",D30) -> 3 | L30: =IF(AND(OR(B30="Mistri",B30="Jogali"),G30<>""),"Y","N") -> Y | M30: =IF(L30="Y",C30*K30,0) -> 9 | N30: =IF(L30="Y",E30,0) -> 0
A31: 46105 | B31: Mistri | C31: 1 | D31: 9.5 | E31: 1.5 | F31: 9.5 | G31: J/25-26/152 | H31: Pallet / saddle making | J31: =IF(B31="","",IF(ISNUMBER(A31),A31,DATE(2000+VALUE(RIGHT(A31,2)),VALUE(MID(A31,4,2)),VALUE(LEFT(A31,2))))) -> 46105 | K31: =IF(B31="","",D31) -> 9.5 | L31: =IF(AND(OR(B31="Mistri",B31="Jogali"),G31<>""),"Y","N") -> Y | M31: =IF(L31="Y",C31*K31,0) -> 9.5 | N31: =IF(L31="Y",E31,0) -> 1.5
A32: 46105 | B32: Jogali | C32: 1 | D32: 9.5 | E32: 1.5 | F32: 9.5 | G32: J/25-26/152 | H32: helping mistri / shifting | J32: =IF(B32="","",IF(ISNUMBER(A32),A32,DATE(2000+VALUE(RIGHT(A32,2)),VALUE(MID(A32,4,2)),VALUE(LEFT(A32,2))))) -> 46105 | K32: =IF(B32="","",D32) -> 9.5 | L32: =IF(AND(OR(B32="Mistri",B32="Jogali"),G32<>""),"Y","N") -> Y | M32: =IF(L32="Y",C32*K32,0) -> 9.5 | N32: =IF(L32="Y",E32,0) -> 1.5
A33: 46106 | B33: Mistri | C33: 1 | D33: 1 | F33: 1 | G33: J/25-26/152 | H33: Pallet / saddle making | J33: =IF(B33="","",IF(ISNUMBER(A33),A33,DATE(2000+VALUE(RIGHT(A33,2)),VALUE(MID(A33,4,2)),VALUE(LEFT(A33,2))))) -> 46106 | K33: =IF(B33="","",D33) -> 1 | L33: =IF(AND(OR(B33="Mistri",B33="Jogali"),G33<>""),"Y","N") -> Y | M33: =IF(L33="Y",C33*K33,0) -> 1 | N33: =IF(L33="Y",E33,0) -> 0
A34: 46106 | B34: Jogali | C34: 1 | D34: 1 | F34: 1 | G34: J/25-26/152 | H34: helping mistri / shifting | J34: =IF(B34="","",IF(ISNUMBER(A34),A34,DATE(2000+VALUE(RIGHT(A34,2)),VALUE(MID(A34,4,2)),VALUE(LEFT(A34,2))))) -> 46106 | K34: =IF(B34="","",D34) -> 1 | L34: =IF(AND(OR(B34="Mistri",B34="Jogali"),G34<>""),"Y","N") -> Y | M34: =IF(L34="Y",C34*K34,0) -> 1 | N34: =IF(L34="Y",E34,0) -> 0
A35: 46107 | B35: Jogali | C35: 2 | F35: 0 | G35: J/25-26/152 | H35: Foam / bubble / stretch + lashing | I35: sup. on leave - hrs not noted | J35: =IF(B35="","",IF(ISNUMBER(A35),A35,DATE(2000+VALUE(RIGHT(A35,2)),VALUE(MID(A35,4,2)),VALUE(LEFT(A35,2))))) -> 46107 | K35: 8 | L35: =IF(AND(OR(B35="Mistri",B35="Jogali"),G35<>""),"Y","N") -> Y | M35: =IF(L35="Y",C35*K35,0) -> 16 | N35: =IF(L35="Y",E35,0) -> 0
A36: Total Mar-26 | E36: 15 | F36: 203.5 | J36: =IF(B36="","",IF(ISNUMBER(A36),A36,DATE(2000+VALUE(RIGHT(A36,2)),VALUE(MID(A36,4,2)),VALUE(LEFT(A36,2))))) | K36: =IF(B36="","",D36) | L36: =IF(AND(OR(B36="Mistri",B36="Jogali"),G36<>""),"Y","N") -> N | M36: =IF(L36="Y",C36*K36,0) -> 0 | N36: =IF(L36="Y",E36,0) -> 0
A38: 46119 | B38: Mistri | C38: 2 | D38: 6 | F38: 12 | G38: J/25-26/156 | H38: Pallet / saddle making | J38: =IF(B38="","",IF(ISNUMBER(A38),A38,DATE(2000+VALUE(RIGHT(A38,2)),VALUE(MID(A38,4,2)),VALUE(LEFT(A38,2))))) -> 46119 | K38: =IF(B38="","",D38) -> 6 | L38: =IF(AND(OR(B38="Mistri",B38="Jogali"),G38<>""),"Y","N") -> Y | M38: =IF(L38="Y",C38*K38,0) -> 12 | N38: =IF(L38="Y",E38,0) -> 0
A39: 46119 | B39: Jogali | C39: 1 | D39: 6 | F39: 6 | G39: J/25-26/156 | H39: helping mistri / shifting | J39: =IF(B39="","",IF(ISNUMBER(A39),A39,DATE(2000+VALUE(RIGHT(A39,2)),VALUE(MID(A39,4,2)),VALUE(LEFT(A39,2))))) -> 46119 | K39: =IF(B39="","",D39) -> 6 | L39: =IF(AND(OR(B39="Mistri",B39="Jogali"),G39<>""),"Y","N") -> Y | M39: =IF(L39="Y",C39*K39,0) -> 6 | N39: =IF(L39="Y",E39,0) -> 0
A40: 46120 | B40: Jogali | C40: 2 | D40: 9 | E40: 2 | F40: 18 | G40: J/25-26/156 | H40: Foam / bubble / stretch + lashing | J40: =IF(B40="","",IF(ISNUMBER(A40),A40,DATE(2000+VALUE(RIGHT(A40,2)),VALUE(MID(A40,4,2)),VALUE(LEFT(A40,2))))) -> 46120 | K40: =IF(B40="","",D40) -> 9 | L40: =IF(AND(OR(B40="Mistri",B40="Jogali"),G40<>""),"Y","N") -> Y | M40: =IF(L40="Y",C40*K40,0) -> 18 | N40: =IF(L40="Y",E40,0) -> 2
A41: 46121 | B41: Jogali | C41: 2 | D41: 3 | F41: 6 | G41: J/25-26/156 | H41: Foam / bubble / stretch + lashing | J41: =IF(B41="","",IF(ISNUMBER(A41),A41,DATE(2000+VALUE(RIGHT(A41,2)),VALUE(MID(A41,4,2)),VALUE(LEFT(A41,2))))) -> 46121 | K41: =IF(B41="","",D41) -> 3 | L41: =IF(AND(OR(B41="Mistri",B41="Jogali"),G41<>""),"Y","N") -> Y | M41: =IF(L41="Y",C41*K41,0) -> 6 | N41: =IF(L41="Y",E41,0) -> 0
A42: 46121 | B42: Jogali | C42: 2 | D42: 8 | F42: 16 | H42: timber unloading | J42: =IF(B42="","",IF(ISNUMBER(A42),A42,DATE(2000+VALUE(RIGHT(A42,2)),VALUE(MID(A42,4,2)),VALUE(LEFT(A42,2))))) -> 46121 | K42: =IF(B42="","",D42) -> 8 | L42: =IF(AND(OR(B42="Mistri",B42="Jogali"),G42<>""),"Y","N") -> N | M42: =IF(L42="Y",C42*K42,0) -> 0 | N42: =IF(L42="Y",E42,0) -> 0
A43: 46125 | B43: Mistri | C43: 2 | D43: 9.5 | E43: 3 | F43: 19 | G43: J/25-26/137 | H43: Pallet / saddle making | I43: rain - work stopped 2 hrs | J43: =IF(B43="","",IF(ISNUMBER(A43),A43,DATE(2000+VALUE(RIGHT(A43,2)),VALUE(MID(A43,4,2)),VALUE(LEFT(A43,2))))) -> 46125 | K43: =IF(B43="","",D43) -> 9.5 | L43: =IF(AND(OR(B43="Mistri",B43="Jogali"),G43<>""),"Y","N") -> Y | M43: =IF(L43="Y",C43*K43,0) -> 19 | N43: =IF(L43="Y",E43,0) -> 3
A44: 46125 | B44: Jogali | C44: 1 | D44: 9.5 | E44: 1.5 | F44: 9.5 | G44: J/25-26/137 | H44: helping mistri / shifting | J44: =IF(B44="","",IF(ISNUMBER(A44),A44,DATE(2000+VALUE(RIGHT(A44,2)),VALUE(MID(A44,4,2)),VALUE(LEFT(A44,2))))) -> 46125 | K44: =IF(B44="","",D44) -> 9.5 | L44: =IF(AND(OR(B44="Mistri",B44="Jogali"),G44<>""),"Y","N") -> Y | M44: =IF(L44="Y",C44*K44,0) -> 9.5 | N44: =IF(L44="Y",E44,0) -> 1.5
A45: 46126 | B45: Mistri | C45: 2 | D45: 1 | F45: 2 | G45: J/25-26/137 | H45: Pallet / saddle making | J45: =IF(B45="","",IF(ISNUMBER(A45),A45,DATE(2000+VALUE(RIGHT(A45,2)),VALUE(MID(A45,4,2)),VALUE(LEFT(A45,2))))) -> 46126 | K45: =IF(B45="","",D45) -> 1 | L45: =IF(AND(OR(B45="Mistri",B45="Jogali"),G45<>""),"Y","N") -> Y | M45: =IF(L45="Y",C45*K45,0) -> 2 | N45: =IF(L45="Y",E45,0) -> 0
A46: 46126 | B46: Jogali | C46: 1 | D46: 1 | F46: 1 | G46: J/25-26/137 | H46: helping mistri / shifting | J46: =IF(B46="","",IF(ISNUMBER(A46),A46,DATE(2000+VALUE(RIGHT(A46,2)),VALUE(MID(A46,4,2)),VALUE(LEFT(A46,2))))) -> 46126 | K46: =IF(B46="","",D46) -> 1 | L46: =IF(AND(OR(B46="Mistri",B46="Jogali"),G46<>""),"Y","N") -> Y | M46: =IF(L46="Y",C46*K46,0) -> 1 | N46: =IF(L46="Y",E46,0) -> 0
A47: 46127 | B47: Jogali | C47: 2 | D47: 9 | E47: 2 | F47: 18 | G47: J/25-26/137 | H47: Foam / bubble / stretch + lashing + tarpaulin | J47: =IF(B47="","",IF(ISNUMBER(A47),A47,DATE(2000+VALUE(RIGHT(A47,2)),VALUE(MID(A47,4,2)),VALUE(LEFT(A47,2))))) -> 46127 | K47: =IF(B47="","",D47) -> 9 | L47: =IF(AND(OR(B47="Mistri",B47="Jogali"),G47<>""),"Y","N") -> Y | M47: =IF(L47="Y",C47*K47,0) -> 18 | N47: =IF(L47="Y",E47,0) -> 2
A48: 46128 | B48: Jogali | C48: 2 | D48: 9 | E48: 2 | F48: 18 | G48: J/25-26/137 | H48: Foam / bubble / stretch + lashing + tarpaulin | J48: =IF(B48="","",IF(ISNUMBER(A48),A48,DATE(2000+VALUE(RIGHT(A48,2)),VALUE(MID(A48,4,2)),VALUE(LEFT(A48,2))))) -> 46128 | K48: =IF(B48="","",D48) -> 9 | L48: =IF(AND(OR(B48="Mistri",B48="Jogali"),G48<>""),"Y","N") -> Y | M48: =IF(L48="Y",C48*K48,0) -> 18 | N48: =IF(L48="Y",E48,0) -> 2
A49: 46129 | B49: Jogali | C49: 2 | D49: 1.5 | F49: 3 | G49: J/25-26/137 | H49: Foam / bubble / stretch + lashing + tarpaulin | J49: =IF(B49="","",IF(ISNUMBER(A49),A49,DATE(2000+VALUE(RIGHT(A49,2)),VALUE(MID(A49,4,2)),VALUE(LEFT(A49,2))))) -> 46129 | K49: =IF(B49="","",D49) -> 1.5 | L49: =IF(AND(OR(B49="Mistri",B49="Jogali"),G49<>""),"Y","N") -> Y | M49: =IF(L49="Y",C49*K49,0) -> 3 | N49: =IF(L49="Y",E49,0) -> 0
A50: 46130 | B50: Mistri | C50: 2 | D50: 9.5 | E50: 3 | F50: 19 | G50: J/25-26/158 | H50: Pallet / saddle making | J50: =IF(B50="","",IF(ISNUMBER(A50),A50,DATE(2000+VALUE(RIGHT(A50,2)),VALUE(MID(A50,4,2)),VALUE(LEFT(A50,2))))) -> 46130 | K50: =IF(B50="","",D50) -> 9.5 | L50: =IF(AND(OR(B50="Mistri",B50="Jogali"),G50<>""),"Y","N") -> Y | M50: =IF(L50="Y",C50*K50,0) -> 19 | N50: =IF(L50="Y",E50,0) -> 3
A51: 46130 | B51: Jogali | C51: 1 | D51: 9.5 | E51: 1.5 | F51: 9.5 | G51: J/25-26/158 | H51: helping mistri / shifting | J51: =IF(B51="","",IF(ISNUMBER(A51),A51,DATE(2000+VALUE(RIGHT(A51,2)),VALUE(MID(A51,4,2)),VALUE(LEFT(A51,2))))) -> 46130 | K51: =IF(B51="","",D51) -> 9.5 | L51: =IF(AND(OR(B51="Mistri",B51="Jogali"),G51<>""),"Y","N") -> Y | M51: =IF(L51="Y",C51*K51,0) -> 9.5 | N51: =IF(L51="Y",E51,0) -> 1.5
A52: 46132 | B52: Mistri | C52: 2 | D52: 6 | F52: 12 | G52: J/25-26/158 | H52: Pallet / saddle making | J52: =IF(B52="","",IF(ISNUMBER(A52),A52,DATE(2000+VALUE(RIGHT(A52,2)),VALUE(MID(A52,4,2)),VALUE(LEFT(A52,2))))) -> 46132 | K52: =IF(B52="","",D52) -> 6 | L52: =IF(AND(OR(B52="Mistri",B52="Jogali"),G52<>""),"Y","N") -> Y | M52: =IF(L52="Y",C52*K52,0) -> 12 | N52: =IF(L52="Y",E52,0) -> 0
A53: 46132 | B53: Jogali | C53: 1 | D53: 6 | F53: 6 | G53: J/25-26/158 | H53: helping mistri / shifting | J53: =IF(B53="","",IF(ISNUMBER(A53),A53,DATE(2000+VALUE(RIGHT(A53,2)),VALUE(MID(A53,4,2)),VALUE(LEFT(A53,2))))) -> 46132 | K53: =IF(B53="","",D53) -> 6 | L53: =IF(AND(OR(B53="Mistri",B53="Jogali"),G53<>""),"Y","N") -> Y | M53: =IF(L53="Y",C53*K53,0) -> 6 | N53: =IF(L53="Y",E53,0) -> 0
A54: 46133 | B54: Jogali | C54: 3 | D54: 9 | E54: 3 | F54: 27 | G54: J/25-26/158 | H54: Foam / bubble / stretch + lashing + tarpaulin | J54: =IF(B54="","",IF(ISNUMBER(A54),A54,DATE(2000+VALUE(RIGHT(A54,2)),VALUE(MID(A54,4,2)),VALUE(LEFT(A54,2))))) -> 46133 | K54: =IF(B54="","",D54) -> 9 | L54: =IF(AND(OR(B54="Mistri",B54="Jogali"),G54<>""),"Y","N") -> Y | M54: =IF(L54="Y",C54*K54,0) -> 27 | N54: =IF(L54="Y",E54,0) -> 3
A55: 46134 | B55: Jogali | C55: 3 | D55: 8 | F55: 24 | G55: J/25-26/158 | H55: Foam / bubble / stretch + lashing + tarpaulin | J55: =IF(B55="","",IF(ISNUMBER(A55),A55,DATE(2000+VALUE(RIGHT(A55,2)),VALUE(MID(A55,4,2)),VALUE(LEFT(A55,2))))) -> 46134 | K55: =IF(B55="","",D55) -> 8 | L55: =IF(AND(OR(B55="Mistri",B55="Jogali"),G55<>""),"Y","N") -> Y | M55: =IF(L55="Y",C55*K55,0) -> 24 | N55: =IF(L55="Y",E55,0) -> 0
A56: 46135 | B56: Jogali | C56: 3 | D56: 1 | F56: 3 | G56: J/25-26/158 | H56: Foam / bubble / stretch + lashing + tarpaulin | J56: =IF(B56="","",IF(ISNUMBER(A56),A56,DATE(2000+VALUE(RIGHT(A56,2)),VALUE(MID(A56,4,2)),VALUE(LEFT(A56,2))))) -> 46135 | K56: =IF(B56="","",D56) -> 1 | L56: =IF(AND(OR(B56="Mistri",B56="Jogali"),G56<>""),"Y","N") -> Y | M56: =IF(L56="Y",C56*K56,0) -> 3 | N56: =IF(L56="Y",E56,0) -> 0
A57: Total Apr-26 | E57: 18 | F57: 229 | J57: =IF(B57="","",IF(ISNUMBER(A57),A57,DATE(2000+VALUE(RIGHT(A57,2)),VALUE(MID(A57,4,2)),VALUE(LEFT(A57,2))))) | K57: =IF(B57="","",D57) | L57: =IF(AND(OR(B57="Mistri",B57="Jogali"),G57<>""),"Y","N") -> N | M57: =IF(L57="Y",C57*K57,0) -> 0 | N57: =IF(L57="Y",E57,0) -> 0
A59: 46151 | B59: Mistri | C59: 2 | D59: 9.5 | E59: 3 | F59: 19 | G59: J/25-26/164 | H59: Pallet / saddle making | I59: rain - work stopped 2 hrs | J59: =IF(B59="","",IF(ISNUMBER(A59),A59,DATE(2000+VALUE(RIGHT(A59,2)),VALUE(MID(A59,4,2)),VALUE(LEFT(A59,2))))) -> 46151 | K59: =IF(B59="","",D59) -> 9.5 | L59: =IF(AND(OR(B59="Mistri",B59="Jogali"),G59<>""),"Y","N") -> Y | M59: =IF(L59="Y",C59*K59,0) -> 19 | N59: =IF(L59="Y",E59,0) -> 3
A60: 46151 | B60: Jogali | C60: 1 | D60: 9.5 | E60: 1.5 | F60: 9.5 | G60: J/25-26/164 | H60: helping mistri / shifting | J60: =IF(B60="","",IF(ISNUMBER(A60),A60,DATE(2000+VALUE(RIGHT(A60,2)),VALUE(MID(A60,4,2)),VALUE(LEFT(A60,2))))) -> 46151 | K60: =IF(B60="","",D60) -> 9.5 | L60: =IF(AND(OR(B60="Mistri",B60="Jogali"),G60<>""),"Y","N") -> Y | M60: =IF(L60="Y",C60*K60,0) -> 9.5 | N60: =IF(L60="Y",E60,0) -> 1.5
A61: 46153 | B61: Mistri | C61: 2 | D61: 6 | F61: 12 | G61: J/25-26/164 | H61: Pallet / saddle making | J61: =IF(B61="","",IF(ISNUMBER(A61),A61,DATE(2000+VALUE(RIGHT(A61,2)),VALUE(MID(A61,4,2)),VALUE(LEFT(A61,2))))) -> 46153 | K61: =IF(B61="","",D61) -> 6 | L61: =IF(AND(OR(B61="Mistri",B61="Jogali"),G61<>""),"Y","N") -> Y | M61: =IF(L61="Y",C61*K61,0) -> 12 | N61: =IF(L61="Y",E61,0) -> 0
A62: 46153 | B62: Jogali | C62: 1 | D62: 6 | F62: 6 | G62: J/25-26/164 | H62: helping mistri / shifting | J62: =IF(B62="","",IF(ISNUMBER(A62),A62,DATE(2000+VALUE(RIGHT(A62,2)),VALUE(MID(A62,4,2)),VALUE(LEFT(A62,2))))) -> 46153 | K62: =IF(B62="","",D62) -> 6 | L62: =IF(AND(OR(B62="Mistri",B62="Jogali"),G62<>""),"Y","N") -> Y | M62: =IF(L62="Y",C62*K62,0) -> 6 | N62: =IF(L62="Y",E62,0) -> 0
A63: 46154 | B63: Jogali | C63: 2 | D63: 9 | E63: 2 | F63: 18 | G63: J/25-26/164 | H63: Foam / bubble / stretch + lashing + tarpaulin | J63: =IF(B63="","",IF(ISNUMBER(A63),A63,DATE(2000+VALUE(RIGHT(A63,2)),VALUE(MID(A63,4,2)),VALUE(LEFT(A63,2))))) -> 46154 | K63: =IF(B63="","",D63) -> 9 | L63: =IF(AND(OR(B63="Mistri",B63="Jogali"),G63<>""),"Y","N") -> Y | M63: =IF(L63="Y",C63*K63,0) -> 18 | N63: =IF(L63="Y",E63,0) -> 2
A64: 46155 | B64: Jogali | C64: 2 | D64: 9 | E64: 2 | F64: 18 | G64: J/25-26/164 | H64: Foam / bubble / stretch + lashing + tarpaulin | J64: =IF(B64="","",IF(ISNUMBER(A64),A64,DATE(2000+VALUE(RIGHT(A64,2)),VALUE(MID(A64,4,2)),VALUE(LEFT(A64,2))))) -> 46155 | K64: =IF(B64="","",D64) -> 9 | L64: =IF(AND(OR(B64="Mistri",B64="Jogali"),G64<>""),"Y","N") -> Y | M64: =IF(L64="Y",C64*K64,0) -> 18 | N64: =IF(L64="Y",E64,0) -> 2
A65: 46156 | B65: Jogali | C65: 2 | D65: 3.5 | F65: 7 | G65: J/25-26/164 | H65: Foam / bubble / stretch + lashing + tarpaulin | J65: =IF(B65="","",IF(ISNUMBER(A65),A65,DATE(2000+VALUE(RIGHT(A65,2)),VALUE(MID(A65,4,2)),VALUE(LEFT(A65,2))))) -> 46156 | K65: =IF(B65="","",D65) -> 3.5 | L65: =IF(AND(OR(B65="Mistri",B65="Jogali"),G65<>""),"Y","N") -> Y | M65: =IF(L65="Y",C65*K65,0) -> 7 | N65: =IF(L65="Y",E65,0) -> 0
A66: Total May-26 | E66: 8.5 | F66: 89.5 | J66: =IF(B66="","",IF(ISNUMBER(A66),A66,DATE(2000+VALUE(RIGHT(A66,2)),VALUE(MID(A66,4,2)),VALUE(LEFT(A66,2))))) | K66: =IF(B66="","",D66) | L66: =IF(AND(OR(B66="Mistri",B66="Jogali"),G66<>""),"Y","N") -> N | M66: =IF(L66="Y",C66*K66,0) -> 0 | N66: =IF(L66="Y",E66,0) -> 0
A68: 46176 | B68: Mistri | C68: 1 | D68: 5 | F68: 5 | G68: J/25-26/165 | H68: Pallet / saddle making | J68: =IF(B68="","",IF(ISNUMBER(A68),A68,DATE(2000+VALUE(RIGHT(A68,2)),VALUE(MID(A68,4,2)),VALUE(LEFT(A68,2))))) -> 46176 | K68: =IF(B68="","",D68) -> 5 | L68: =IF(AND(OR(B68="Mistri",B68="Jogali"),G68<>""),"Y","N") -> Y | M68: =IF(L68="Y",C68*K68,0) -> 5 | N68: =IF(L68="Y",E68,0) -> 0
A69: 46176 | B69: Jogali | C69: 1 | D69: 5 | F69: 5 | G69: J/25-26/165 | H69: helping mistri / shifting | J69: =IF(B69="","",IF(ISNUMBER(A69),A69,DATE(2000+VALUE(RIGHT(A69,2)),VALUE(MID(A69,4,2)),VALUE(LEFT(A69,2))))) -> 46176 | K69: =IF(B69="","",D69) -> 5 | L69: =IF(AND(OR(B69="Mistri",B69="Jogali"),G69<>""),"Y","N") -> Y | M69: =IF(L69="Y",C69*K69,0) -> 5 | N69: =IF(L69="Y",E69,0) -> 0
A70: 46177 | B70: Jogali | C70: 2 | D70: 2.5 | F70: 5 | G70: J/25-26/165 | H70: Foam / bubble / stretch + lashing | J70: =IF(B70="","",IF(ISNUMBER(A70),A70,DATE(2000+VALUE(RIGHT(A70,2)),VALUE(MID(A70,4,2)),VALUE(LEFT(A70,2))))) -> 46177 | K70: =IF(B70="","",D70) -> 2.5 | L70: =IF(AND(OR(B70="Mistri",B70="Jogali"),G70<>""),"Y","N") -> Y | M70: =IF(L70="Y",C70*K70,0) -> 5 | N70: =IF(L70="Y",E70,0) -> 0
A71: 46185 | B71: Mistri | C71: 2 | D71: 9.5 | E71: 3 | F71: 19 | G71: J/25-26/167 | H71: Pallet / saddle making | I71: rain - work stopped 2 hrs | J71: =IF(B71="","",IF(ISNUMBER(A71),A71,DATE(2000+VALUE(RIGHT(A71,2)),VALUE(MID(A71,4,2)),VALUE(LEFT(A71,2))))) -> 46185 | K71: =IF(B71="","",D71) -> 9.5 | L71: =IF(AND(OR(B71="Mistri",B71="Jogali"),G71<>""),"Y","N") -> Y | M71: =IF(L71="Y",C71*K71,0) -> 19 | N71: =IF(L71="Y",E71,0) -> 3
A72: 46185 | B72: Jogali | C72: 1 | D72: 9.5 | E72: 1.5 | F72: 9.5 | G72: J/25-26/167 | H72: helping mistri / shifting | J72: =IF(B72="","",IF(ISNUMBER(A72),A72,DATE(2000+VALUE(RIGHT(A72,2)),VALUE(MID(A72,4,2)),VALUE(LEFT(A72,2))))) -> 46185 | K72: =IF(B72="","",D72) -> 9.5 | L72: =IF(AND(OR(B72="Mistri",B72="Jogali"),G72<>""),"Y","N") -> Y | M72: =IF(L72="Y",C72*K72,0) -> 9.5 | N72: =IF(L72="Y",E72,0) -> 1.5
A73: 46186 | B73: Mistri | C73: 2 | D73: 5.5 | F73: 11 | G73: J/25-26/167 | H73: Pallet / saddle making | J73: =IF(B73="","",IF(ISNUMBER(A73),A73,DATE(2000+VALUE(RIGHT(A73,2)),VALUE(MID(A73,4,2)),VALUE(LEFT(A73,2))))) -> 46186 | K73: =IF(B73="","",D73) -> 5.5 | L73: =IF(AND(OR(B73="Mistri",B73="Jogali"),G73<>""),"Y","N") -> Y | M73: =IF(L73="Y",C73*K73,0) -> 11 | N73: =IF(L73="Y",E73,0) -> 0
A74: 46186 | B74: Jogali | C74: 1 | D74: 5.5 | F74: 5.5 | G74: J/25-26/167 | H74: helping mistri / shifting | J74: =IF(B74="","",IF(ISNUMBER(A74),A74,DATE(2000+VALUE(RIGHT(A74,2)),VALUE(MID(A74,4,2)),VALUE(LEFT(A74,2))))) -> 46186 | K74: =IF(B74="","",D74) -> 5.5 | L74: =IF(AND(OR(B74="Mistri",B74="Jogali"),G74<>""),"Y","N") -> Y | M74: =IF(L74="Y",C74*K74,0) -> 5.5 | N74: =IF(L74="Y",E74,0) -> 0
A75: 46188 | B75: Jogali | C75: 2 | D75: 9 | E75: 2 | F75: 18 | G75: J/25-26/167 | H75: Foam / bubble / stretch + lashing + tarpaulin | J75: =IF(B75="","",IF(ISNUMBER(A75),A75,DATE(2000+VALUE(RIGHT(A75,2)),VALUE(MID(A75,4,2)),VALUE(LEFT(A75,2))))) -> 46188 | K75: =IF(B75="","",D75) -> 9 | L75: =IF(AND(OR(B75="Mistri",B75="Jogali"),G75<>""),"Y","N") -> Y | M75: =IF(L75="Y",C75*K75,0) -> 18 | N75: =IF(L75="Y",E75,0) -> 2
A76: 46189 | B76: Jogali | C76: 2 | D76: 9 | E76: 2 | F76: 18 | G76: J/25-26/167 | H76: Foam / bubble / stretch + lashing + tarpaulin | J76: =IF(B76="","",IF(ISNUMBER(A76),A76,DATE(2000+VALUE(RIGHT(A76,2)),VALUE(MID(A76,4,2)),VALUE(LEFT(A76,2))))) -> 46189 | K76: =IF(B76="","",D76) -> 9 | L76: =IF(AND(OR(B76="Mistri",B76="Jogali"),G76<>""),"Y","N") -> Y | M76: =IF(L76="Y",C76*K76,0) -> 18 | N76: =IF(L76="Y",E76,0) -> 2
A77: 46190 | B77: Jogali | C77: 2 | D77: 9 | E77: 2 | F77: 18 | G77: J/25-26/167 | H77: Foam / bubble / stretch + lashing + tarpaulin | J77: =IF(B77="","",IF(ISNUMBER(A77),A77,DATE(2000+VALUE(RIGHT(A77,2)),VALUE(MID(A77,4,2)),VALUE(LEFT(A77,2))))) -> 46190 | K77: =IF(B77="","",D77) -> 9 | L77: =IF(AND(OR(B77="Mistri",B77="Jogali"),G77<>""),"Y","N") -> Y | M77: =IF(L77="Y",C77*K77,0) -> 18 | N77: =IF(L77="Y",E77,0) -> 2
A78: 46191 | B78: Jogali | C78: 2 | D78: 1 | F78: 2 | G78: J/25-26/167 | H78: Foam / bubble / stretch + lashing + tarpaulin | J78: =IF(B78="","",IF(ISNUMBER(A78),A78,DATE(2000+VALUE(RIGHT(A78,2)),VALUE(MID(A78,4,2)),VALUE(LEFT(A78,2))))) -> 46191 | K78: =IF(B78="","",D78) -> 1 | L78: =IF(AND(OR(B78="Mistri",B78="Jogali"),G78<>""),"Y","N") -> Y | M78: =IF(L78="Y",C78*K78,0) -> 2 | N78: =IF(L78="Y",E78,0) -> 0
A79: 46191 | B79: Jogali | C79: 2 | D79: 8 | F79: 16 | H79: yard cleaning / shifting | J79: =IF(B79="","",IF(ISNUMBER(A79),A79,DATE(2000+VALUE(RIGHT(A79,2)),VALUE(MID(A79,4,2)),VALUE(LEFT(A79,2))))) -> 46191 | K79: =IF(B79="","",D79) -> 8 | L79: =IF(AND(OR(B79="Mistri",B79="Jogali"),G79<>""),"Y","N") -> N | M79: =IF(L79="Y",C79*K79,0) -> 0 | N79: =IF(L79="Y",E79,0) -> 0
A80: Total Jun-26 | E80: 10.5 | F80: 132 | J80: =IF(B80="","",IF(ISNUMBER(A80),A80,DATE(2000+VALUE(RIGHT(A80,2)),VALUE(MID(A80,4,2)),VALUE(LEFT(A80,2))))) | K80: =IF(B80="","",D80) | L80: =IF(AND(OR(B80="Mistri",B80="Jogali"),G80<>""),"Y","N") -> N | M80: =IF(L80="Y",C80*K80,0) -> 0 | N80: =IF(L80="Y",E80,0) -> 0
A82: 46223 | B82: Mistri | C82: 2 | D82: 9.5 | E82: 3 | F82: 19 | G82: J/26-27/018 | H82: Pallet / saddle making | J82: =IF(B82="","",IF(ISNUMBER(A82),A82,DATE(2000+VALUE(RIGHT(A82,2)),VALUE(MID(A82,4,2)),VALUE(LEFT(A82,2))))) -> 46223 | K82: =IF(B82="","",D82) -> 9.5 | L82: =IF(AND(OR(B82="Mistri",B82="Jogali"),G82<>""),"Y","N") -> Y | M82: =IF(L82="Y",C82*K82,0) -> 19 | N82: =IF(L82="Y",E82,0) -> 3
A83: 46223 | B83: Jogali | C83: 1 | D83: 9.5 | E83: 1.5 | F83: 9.5 | G83: J/26-27/018 | H83: helping mistri / shifting | J83: =IF(B83="","",IF(ISNUMBER(A83),A83,DATE(2000+VALUE(RIGHT(A83,2)),VALUE(MID(A83,4,2)),VALUE(LEFT(A83,2))))) -> 46223 | K83: =IF(B83="","",D83) -> 9.5 | L83: =IF(AND(OR(B83="Mistri",B83="Jogali"),G83<>""),"Y","N") -> Y | M83: =IF(L83="Y",C83*K83,0) -> 9.5 | N83: =IF(L83="Y",E83,0) -> 1.5
A84: 46224 | B84: Mistri | C84: 2 | D84: 1 | F84: 2 | G84: J/26-27/018 | H84: Pallet / saddle making | J84: =IF(B84="","",IF(ISNUMBER(A84),A84,DATE(2000+VALUE(RIGHT(A84,2)),VALUE(MID(A84,4,2)),VALUE(LEFT(A84,2))))) -> 46224 | K84: =IF(B84="","",D84) -> 1 | L84: =IF(AND(OR(B84="Mistri",B84="Jogali"),G84<>""),"Y","N") -> Y | M84: =IF(L84="Y",C84*K84,0) -> 2 | N84: =IF(L84="Y",E84,0) -> 0
A85: 46224 | B85: Jogali | C85: 1 | D85: 1 | F85: 1 | G85: J/26-27/018 | H85: helping mistri / shifting | J85: =IF(B85="","",IF(ISNUMBER(A85),A85,DATE(2000+VALUE(RIGHT(A85,2)),VALUE(MID(A85,4,2)),VALUE(LEFT(A85,2))))) -> 46224 | K85: =IF(B85="","",D85) -> 1 | L85: =IF(AND(OR(B85="Mistri",B85="Jogali"),G85<>""),"Y","N") -> Y | M85: =IF(L85="Y",C85*K85,0) -> 1 | N85: =IF(L85="Y",E85,0) -> 0
A86: 46225 | B86: Jogali | C86: 3 | D86: 9 | E86: 3 | F86: 27 | G86: J/26-27/018 | H86: Foam / bubble / stretch + lashing | J86: =IF(B86="","",IF(ISNUMBER(A86),A86,DATE(2000+VALUE(RIGHT(A86,2)),VALUE(MID(A86,4,2)),VALUE(LEFT(A86,2))))) -> 46225 | K86: =IF(B86="","",D86) -> 9 | L86: =IF(AND(OR(B86="Mistri",B86="Jogali"),G86<>""),"Y","N") -> Y | M86: =IF(L86="Y",C86*K86,0) -> 27 | N86: =IF(L86="Y",E86,0) -> 3
A87: 46226 | B87: Jogali | C87: 3 | D87: 5.5 | F87: 16.5 | G87: J/26-27/018 | H87: Foam / bubble / stretch + lashing | J87: =IF(B87="","",IF(ISNUMBER(A87),A87,DATE(2000+VALUE(RIGHT(A87,2)),VALUE(MID(A87,4,2)),VALUE(LEFT(A87,2))))) -> 46226 | K87: =IF(B87="","",D87) -> 5.5 | L87: =IF(AND(OR(B87="Mistri",B87="Jogali"),G87<>""),"Y","N") -> Y | M87: =IF(L87="Y",C87*K87,0) -> 16.5 | N87: =IF(L87="Y",E87,0) -> 0
A88: 46229 | B88: Jogali | C88: 2 | D88: 2.5 | F88: 5 | G88: J/26-27/018 | H88: re-wrap 2 vsl after rain | I88: shed roof leak | J88: =IF(B88="","",IF(ISNUMBER(A88),A88,DATE(2000+VALUE(RIGHT(A88,2)),VALUE(MID(A88,4,2)),VALUE(LEFT(A88,2))))) -> 46229 | K88: =IF(B88="","",D88) -> 2.5 | L88: =IF(AND(OR(B88="Mistri",B88="Jogali"),G88<>""),"Y","N") -> Y | M88: =IF(L88="Y",C88*K88,0) -> 5 | N88: =IF(L88="Y",E88,0) -> 0
A89: Total Jul-26 | E89: 7.5 | F89: 80 | J89: =IF(B89="","",IF(ISNUMBER(A89),A89,DATE(2000+VALUE(RIGHT(A89,2)),VALUE(MID(A89,4,2)),VALUE(LEFT(A89,2))))) | K89: =IF(B89="","",D89) | L89: =IF(AND(OR(B89="Mistri",B89="Jogali"),G89<>""),"Y","N") -> N | M89: =IF(L89="Y",C89*K89,0) -> 0 | N89: =IF(L89="Y",E89,0) -> 0
A91: 46255 | B91: Jogali | C91: 2 | D91: 8 | F91: 16 | H91: timber unloading | J91: =IF(B91="","",IF(ISNUMBER(A91),A91,DATE(2000+VALUE(RIGHT(A91,2)),VALUE(MID(A91,4,2)),VALUE(LEFT(A91,2))))) -> 46255 | K91: =IF(B91="","",D91) -> 8 | L91: =IF(AND(OR(B91="Mistri",B91="Jogali"),G91<>""),"Y","N") -> N | M91: =IF(L91="Y",C91*K91,0) -> 0 | N91: =IF(L91="Y",E91,0) -> 0
A92: Total Aug-26 | E92: 0 | F92: 16 | J92: =IF(B92="","",IF(ISNUMBER(A92),A92,DATE(2000+VALUE(RIGHT(A92,2)),VALUE(MID(A92,4,2)),VALUE(LEFT(A92,2))))) | K92: =IF(B92="","",D92) | L92: =IF(AND(OR(B92="Mistri",B92="Jogali"),G92<>""),"Y","N") -> N | M92: =IF(L92="Y",C92*K92,0) -> 0 | N92: =IF(L92="Y",E92,0) -> 0
A94: Include = N for monthly total rows and non-job work (yard cleaning, unloading). 3 dates were typed as text (dd.mm.yy) - fixed in col J.

Sheet Data - Rates
A1: Vendor rates - as received (bills, quotes, WhatsApp, phone)
A2: Green columns: my item name, use flag and conversion to the unit we consume.
A3: Date | B3: Item (as written) | C3: Party | D3: Rate | E3: Unit | F3: GST | G3: Incl/Excl | H3: How recd | I3: Remarks | J3: Item | K3: Use? | L3: Factor | M3: Rate per UoM | N3: Note
A4: 45870 | B4: Carpenter (contract) | C4: Labour contractor | D4: 760 | E4: per day | F4: - | G4: - | H4: Contract | I4: 8 hr day + 10% contractor; above WB skilled min Rs483-491; KA carpentry skilled Rs697-714 | J4: Carpenter | K4: Y | L4: 1 | M4: =D4*L4 -> 760
A5: 45870 | B5: Helper / khalasi | C5: Labour contractor | D5: 460 | E5: per day | F5: - | G5: - | H5: Contract | I5: above WB semi-skilled min Zone A Rs439 (Jan-Jun 26) | J5: Helper | K5: Y | L5: 1 | M5: =D5*L5 -> 460
A6: 45887 | B6: Pine wood 4x4, 6x3 (non HT) | C6: Saw mill A | D6: 640 | E6: per cft | F6: 18% | G6: Excl | H6: Verbal | I6: non-HT, domestic use only - NOT for export | J6: Timber | K6: N | L6: 1 | M6: =D6*L6 -> 640 | N6: not used: non-HT, domestic only
A7: 45890 | B7: Export pine HT stamped (IPPC) | C7: Timber trader B | D7: 700 | E7: per cft | F7: 18% | G7: Excl | H7: WhatsApp | I7: NZ pine Rs599-800 band + ~Rs50 HT premium | J7: Timber | K7: Y | L7: 1 | M7: =D7*L7 -> 700
A8: 45894 | B8: Air bubble roll 1mtr x 50mtr | C8: Packing material dealer | D8: 640 | E8: per roll | F8: 18% | G8: Excl | H8: Bill | I8: web ref Rs16.7/m2 (195 GSM roll); std 40-50 GSM cheaper per m2 | J8: Bubble wrap | K8: Y | L8: 1 | M8: =D8*L8 -> 640
A9: 45894 | B9: Stretch film 50 mic | C9: Packing material dealer | D9: 158 | E9: per kg | F9: 18% | G9: Excl | H9: Bill | I9: China FOB $1.29-1.58/kg Rs113-139 @87.7 + freight/duty/dealer | J9: Stretch film | K9: Y | L9: 1 | M9: =D9*L9 -> 158
A10: 45894 | B10: Gum tape 3in BOPP | C10: Packing material dealer | D10: 78 | E10: per roll | F10: 18% | G10: Excl | H10: Bill | I10: 65 m roll; no public anchor pulled (<1% of cost) | J10: Gum tape | K10: Y | L10: 1 | M10: =D10*L10 -> 78
A11: 45902 | B11: MS wire nails 2/3/4 inch | C11: Hardware shop | D11: 60 | E11: per kg | F11: 18% | G11: Excl | H11: Cash memo | I11: 1 set = approx 1.5 kg assorted; retail over IndiaMART Rs58/kg | J11: Nails | K11: Y | L11: 1.5 | M11: =D11*L11 -> 90 | N11: 1 set = approx 1.5 kg
A12: 45908 | B12: Ratchet belt 50mm 8mtr | C12: Packing material dealer | D12: 880 | E12: per pc | F12: 18% | G12: Excl | H12: Bill | I12: 8m local make; ~0.8 x IndiaMART 10m low end | J12: Ratchet belt | K12: Y | L12: 1 | M12: =D12*L12 -> 880
A13: 45910 | B13: Fumigation MB 40ft HC | C13: Fumigator (PPQS regd) | D13: 3000 | E13: per cntr | F13: 18% | G13: Excl | H13: Bill | I13: cert incl. | J13: Fumigation | K13: Y | L13: 1 | M13: =D13*L13 -> 3000
A14: 45915 | B14: 12mm ply (unbranded) for manhole/nozzle covers | C14: Saw mill A | D14: 50 | E14: per sqft | F14: 18% | G14: Excl | H14: Cash memo | I14: avg 3.2 sqft per cover (1xDN610,1xDN450,1xDN350,2 small) | J14: Ply cover | K14: Y | L14: 3.2 | M14: =D14*L14 -> 160 | N14: approx 3.2 sqft per cover
A15: 45915 | B15: HDPE tarpaulin 200 GSM | C15: Tarpaulin dealer | D15: 5 | E15: per sqft | F15: 18% | G15: Excl | H15: Verbal | I15: 200 GSM = 0.0186 kg/sqft x ~Rs260/kg + cut/eyelets | J15: Tarpaulin | K15: Y | L15: 1 | M15: =D15*L15 -> 5
A16: 45936 | B16: Kini foam 12mm x 1400mm | C16: Packing material dealer | D16: 2100 | E16: per roll | F16: 18% | G16: Excl | H16: Bill | I16: roll length 25m; 12mm so upper half of 10mm band | J16: Foam | K16: Y | L16: 1 | M16: =D16*L16 -> 2100
A17: 45964 | B17: Ratchet belt 50mm x 8m | C17: Packing material dealer | D17: 900 | E17: per pc | F17: 18% | G17: Excl | H17: Bill | I17: no test cert | J17: Ratchet belt | K17: Y | L17: 1 | M17: =D17*L17 -> 900
A18: 46034 | B18: Export pine HT | C18: Timber trader B | D18: 720 | E18: per cft | F18: 18% | G18: Excl | H18: Bill | J18: Timber | K18: Y | L18: 1 | M18: =D18*L18 -> 720
A19: 46042 | B19: Ratchet lashing 50mm 8m 5T EN12195 | C19: Lifting gear supplier | D19: 1650 | E19: per pc | F19: 18% | G19: Excl | H19: Quotation | I19: branded w/ cert - not ordered; IndiaMART upper band | J19: Ratchet belt | K19: N | L19: 1 | M19: =D19*L19 -> 1650 | N19: not used: branded, not ordered
A20: 46042 | B20: STRECH FILM 50MIC | C20: Packing material dealer | D20: 1660 | E20: per kg | F20: 18% | G20: Excl | H20: WhatsApp | J20: Stretch film | K20: Y | L20: 0.1 | M20: =D20*L20 -> 166 | N20: typo - 1,660 should be 166
A21: 46050 | B21: Fumigation MB 40ft HC | C21: Fumigator (PPQS regd) | D21: 3200 | E21: per cntr | F21: 18% | G21: Excl | H21: Bill | I21: cert incl. | J21: Fumigation | K21: Y | L21: 1 | M21: =D21*L21 -> 3200
A22: 46092 | B22: Bubble wrap 1m x 50m | C22: Packing material dealer | D22: 680 | E22: per roll | F22: 18% | G22: Excl | H22: Bill | J22: Bubble wrap | K22: Y | L22: 1 | M22: =D22*L22 -> 680
A23: 46105 | B23: PINE HT BATTEN | C23: Saw mill A | D23: 26200 | E23: per CBM | F23: 18% | G23: Excl | H23: Quotation | I23: quoted per CBM; rupee at record low - import cost up | J23: Timber | K23: Y | L23: =1/35.31 -> 0.028320589 | M23: =D23*L23 -> 741.99943 | N23: quoted per CBM - converted to cft
A24: 46113 | B24: Carpenter (contract) | C24: Labour contractor | D24: 800 | E24: per day | F24: - | G24: - | H24: Contract | I24: revised Apr-26 | J24: Carpenter | K24: Y | L24: 1 | M24: =D24*L24 -> 800
A25: 46126 | B25: Hydra 14T hire (loading) | C25: Crane hire | D25: 7500 | E25: per shift | F25: 18% | G25: Excl | H25: Verbal | I25: 8 hr x ~Rs940/hr; loading - shown for ref, NOT in pkg cost | J25: Hydra | K25: Y | L25: 1 | M25: =D25*L25 -> 7500
A26: 46183 | B26: Nails assorted | C26: Hardware shop | D26: 66 | E26: per kg | F26: 18% | G26: Excl | H26: Cash memo | I26: wire rod up ~8% Jan-Mar 26 | J26: Nails | K26: Y | L26: 1.5 | M26: =D26*L26 -> 99 | N26: 1 set = approx 1.5 kg
A27: 46188 | B27: Export pine HT | C27: Timber trader B | D27: 765 | E27: per cft | F27: 18% | G27: Excl | H27: Bill | J27: Timber | K27: Y | L27: 1 | M27: =D27*L27 -> 765
A28: 46204 | B28: Helper / khalasi | C28: Labour contractor | D28: 480 | E28: per day | F28: - | G28: - | H28: Contract | I28: revised after WB min wage Jul-26 (Rs447/day semi-skilled Zone A) | J28: Helper | K28: Y | L28: 1 | M28: =D28*L28 -> 480
A29: 46211 | B29: Ratchet belt 50mm 8m | C29: Packing material dealer | D29: 950 | E29: per pc | F29: 18% | G29: Excl | H29: Bill | J29: Ratchet belt | K29: Y | L29: 1 | M29: =D29*L29 -> 950
A30: 46211 | B30: Stretch wrap 50mic LLDPE | C30: Packing material dealer | D30: 198 | E30: per kg | F30: 18% | G30: Incl | H30: Bill | I30: incl GST | J30: Stretch film | K30: Y | L30: =1/1.18 -> 0.84745763 | M30: =D30*L30 -> 167.79661 | N30: rate incl. GST - GST removed
A31: 46211 | B31: EPE foam roll 12mm 1.4m | C31: Packing material dealer | D31: 2250 | E31: per roll | F31: 18% | G31: Excl | H31: Bill | J31: Foam | K31: Y | L31: 1 | M31: =D31*L31 -> 2250
A32: 46211 | B32: BOPP tape 3" brown | C32: Packing material dealer | D32: 1008 | E32: per box of 12 | F32: 18% | G32: Excl | H32: Bill | I32: box price | J32: Gum tape | K32: Y | L32: =1/12 -> 0.083333333 | M32: =D32*L32 -> 84 | N32: box of 12 rolls
A33: 46213 | B33: MB fumigation 40HC + cert | C33: Fumigator (PPQS regd) | D33: 3500 | E33: per cntr | F33: 18% | G33: Excl | H33: Bill | I33: within PUB range Rs1,000-5,000 per FCL | J33: Fumigation | K33: Y | L33: 1 | M33: =D33*L33 -> 3500
A34: 46238 | B34: Air bubble roll | C34: Packing material dealer | D34: 710 | E34: per roll | F34: 18% | G34: Excl | H34: Verbal | J34: Bubble wrap | K34: Y | L34: 1 | M34: =D34*L34 -> 710
A35: 46253 | B35: Export pine HT | C35: Timber trader B | D35: 780 | E35: per cft | F35: 18% | G35: Excl | H35: Verbal | I35: verbal, valid 15 days; top of IndiaMART band | J35: Timber | K35: Y | L35: 1 | M35: =D35*L35 -> 780
A37: Vendors wrote the same 13 items 27 different ways - col J maps each line to one item name.
A39: Market check on the web (Aug/Sep-26)
A40: Pine sawn (NZ) | C40: IndiaMART listings Rs 599 - 800 / cft | E40: https://www.mawoodwork.net/wood-timber.html
A41: HT pine pallets | C41: IndiaMART Rs 720 - 1,200 / cft | E41: https://m.indiamart.com/mr-packaging/industrial-pallet.html
A42: Seaworthy pkg service | C42: Rs 800 / cft onsite (basis not clear) | E42: https://m.indiamart.com/mpackagingindustryindia
A43: EPE foam 10mm roll | C43: Rs 1,600 - 2,500 / roll | E43: https://m.indiamart.com/matrix-engineering-co/epe-foam.html
A44: Ratchet 50mm x 10m | C44: USD 12 - 20 (IndiaMART) | E44: https://carinterior.alibaba.com/question/truck-belt-price-guide-buying-tips
A45: Stretch film | C45: China FOB USD 1.29 - 1.58 / kg | E45: https://sourcing.hktdc.com/zh-Hans/Product-Detail/LLDPE-Stretch-Film-Roll-for-Pallet-Wrapping-1Z03P3QZD
A46: MS wire nail 3in | C46: Rs 58 / kg | E46: https://m.indiamart.com/mdwirestrading
A47: Fumigation FCL | C47: Rs 1,000 - 5,000 / cntr | E47: https://wareiq.com/resources/blogs/fumigation-certificate/
A48: WB min wage Jul-Dec 26 | C48: Zone A: 406 / 447 / 491 per day | E48: https://wageindicator.org/ai/work/minimum-wage/countries/india/22516-west-bengal/22524-automobile-engineering-repairing-workshop-garages/
A49: GST | C49: 4415 crates 5% (from 22.9.25), 4407 sawn 18%, 3923 films 18% | E49: https://busy.in/gst-rates/packing-material

Sheet Data - Items
A1: Item master - packing items (from SAP), with cft per piece added
A3: Item code | B3: Item name | C3: UoM | D3: Group | E3: W (mm) | F3: T (mm) | G3: L (mm) | H3: cft per piece | I3: Rate item | J3: Last purchase ₹ | K3: Date
A4: 1900114 | B4: WOODEN BATTEN 150 X 75 X 2450 LG | C4: NOS | D4: TIMBER | E4: 150 | F4: 75 | G4: 2450 | H4: =IF(D4="TIMBER",E4*F4*G4/1000000000*35.31,0) -> 0.97323187 | I4: Timber | J4: 759.22 | K4: 46253
A5: 1900117 | B5: WOODEN BATTEN 100 X 100 X 1300 LG | C5: NOS | D5: TIMBER | E5: 100 | F5: 100 | G5: 1300 | H5: =IF(D5="TIMBER",E5*F5*G5/1000000000*35.31,0) -> 0.45903 | I5: Timber | J5: 358.09 | K5: 46253
A6: 1900124 | B6: WOODEN BATTEN 150 X 75 X 1300 LG | C6: NOS | D6: TIMBER | E6: 150 | F6: 75 | G6: 1300 | H6: =IF(D6="TIMBER",E6*F6*G6/1000000000*35.31,0) -> 0.51640875 | I6: Timber | J6: 402.85 | K6: 46253
A7: 1900127 | B7: WOODEN BATTEN 150 X 150 X 300 LG | C7: NOS | D7: TIMBER | E7: 150 | F7: 150 | G7: 300 | H7: =IF(D7="TIMBER",E7*F7*G7/1000000000*35.31,0) -> 0.2383425 | I7: Timber | J7: 185.93 | K7: 46253
A8: 1900130 | B8: WOODEN BATTEN 100 X 75 X 100 LG | C8: NOS | D8: TIMBER | E8: 100 | F8: 75 | G8: 100 | H8: =IF(D8="TIMBER",E8*F8*G8/1000000000*35.31,0) -> 0.0264825 | I8: Timber | J8: 20.66 | K8: 46253
A9: 1900137 | B9: NAILS (AS REQUIRED) | C9: SETS | D9: PKG-CONS | H9: =IF(D9="TIMBER",E9*F9*G9/1000000000*35.31,0) -> 0 | I9: Nails | J9: 99 | K9: 46253
A10: 1900144 | B10: KINI FOAM 12 MM THK X 1400 MM WD | C10: ROLL | D10: PKG-CONS | H10: =IF(D10="TIMBER",E10*F10*G10/1000000000*35.31,0) -> 0 | I10: Foam | J10: 2250 | K10: 46253
A11: 1900151 | B11: RATCHET LASHING BELT 8 M LG X 50 MM WD WITH LOCK | C11: NOS | D11: PKG-CONS | H11: =IF(D11="TIMBER",E11*F11*G11/1000000000*35.31,0) -> 0 | I11: Ratchet belt | J11: 950 | K11: 46253
A12: 1900158 | B12: GUM TAPE 3" | C12: NOS | D12: PKG-CONS | H12: =IF(D12="TIMBER",E12*F12*G12/1000000000*35.31,0) -> 0 | I12: Gum tape | J12: 84 | K12: 46253
A13: 1900160 | B13: STRETCH FILM 50 MICRON | C13: KG | D13: PKG-CONS | H13: =IF(D13="TIMBER",E13*F13*G13/1000000000*35.31,0) -> 0 | I13: Stretch film | J13: 167.8 | K13: 46253
A14: 1900162 | B14: AIR BUBBLE WRAP | C14: ROLL | D14: PKG-CONS | H14: =IF(D14="TIMBER",E14*F14*G14/1000000000*35.31,0) -> 0 | I14: Bubble wrap | J14: 710 | K14: 46253
A15: 1900169 | B15: WOODEN BATTEN 150 X 75 X 2550 LG | C15: NOS | D15: TIMBER | E15: 150 | F15: 75 | G15: 2550 | H15: =IF(D15="TIMBER",E15*F15*G15/1000000000*35.31,0) -> 1.0129556 | I15: Timber | J15: 790.21 | K15: 46253
A16: 1900171 | B16: WOODEN BATTEN 100 X 100 X 900 LG | C16: NOS | D16: TIMBER | E16: 100 | F16: 100 | G16: 900 | H16: =IF(D16="TIMBER",E16*F16*G16/1000000000*35.31,0) -> 0.31779 | I16: Timber | J16: 247.91 | K16: 46253
A17: 1900178 | B17: WOODEN BATTEN 150 X 75 X 900 LG | C17: NOS | D17: TIMBER | E17: 150 | F17: 75 | G17: 900 | H17: =IF(D17="TIMBER",E17*F17*G17/1000000000*35.31,0) -> 0.35751375 | I17: Timber | J17: 278.9 | K17: 46253
A18: 1900179 | B18: WOODEN BATTEN 150 X 75 X 2650 LG | C18: NOS | D18: TIMBER | E18: 150 | F18: 75 | G18: 2650 | H18: =IF(D18="TIMBER",E18*F18*G18/1000000000*35.31,0) -> 1.0526794 | I18: Timber | J18: 821.2 | K18: 46253
A19: 1900180 | B19: WOODEN BATTEN 100 X 100 X 1050 LG | C19: NOS | D19: TIMBER | E19: 100 | F19: 100 | G19: 1050 | H19: =IF(D19="TIMBER",E19*F19*G19/1000000000*35.31,0) -> 0.370755 | I19: Timber | J19: 289.23 | K19: 46253
A20: 1900183 | B20: WOODEN BATTEN 150 X 75 X 1050 LG | C20: NOS | D20: TIMBER | E20: 150 | F20: 75 | G20: 1050 | H20: =IF(D20="TIMBER",E20*F20*G20/1000000000*35.31,0) -> 0.41709937 | I20: Timber | J20: 325.38 | K20: 46253
A21: 1900184 | B21: WOODEN BATTEN 150 X 75 X 2850 LG | C21: NOS | D21: TIMBER | E21: 150 | F21: 75 | G21: 2850 | H21: =IF(D21="TIMBER",E21*F21*G21/1000000000*35.31,0) -> 1.1321269 | I21: Timber | J21: 883.18 | K21: 46253
A22: 1900186 | B22: WOODEN BATTEN 100 X 100 X 1150 LG | C22: NOS | D22: TIMBER | E22: 100 | F22: 100 | G22: 1150 | H22: =IF(D22="TIMBER",E22*F22*G22/1000000000*35.31,0) -> 0.406065 | I22: Timber | J22: 316.77 | K22: 46253
A23: 1900189 | B23: WOODEN BATTEN 150 X 75 X 1150 LG | C23: NOS | D23: TIMBER | E23: 150 | F23: 75 | G23: 1150 | H23: =IF(D23="TIMBER",E23*F23*G23/1000000000*35.31,0) -> 0.45682312 | I23: Timber | J23: 356.37 | K23: 46253
A24: 1900190 | B24: WOODEN BATTEN 150 X 75 X 3550 LG | C24: NOS | D24: TIMBER | E24: 150 | F24: 75 | G24: 3550 | H24: =IF(D24="TIMBER",E24*F24*G24/1000000000*35.31,0) -> 1.4101931 | I24: Timber | J24: 1100.1 | K24: 46253
A25: 1900192 | B25: WOODEN BATTEN 100 X 100 X 1550 LG | C25: NOS | D25: TIMBER | E25: 100 | F25: 100 | G25: 1550 | H25: =IF(D25="TIMBER",E25*F25*G25/1000000000*35.31,0) -> 0.547305 | I25: Timber | J25: 426.95 | K25: 46253
A26: 1900194 | B26: WOODEN BATTEN 150 X 75 X 1550 LG | C26: NOS | D26: TIMBER | E26: 150 | F26: 75 | G26: 1550 | H26: =IF(D26="TIMBER",E26*F26*G26/1000000000*35.31,0) -> 0.61571813 | I26: Timber | J26: 480.32 | K26: 46253
... A33: 1900219 | B33: WOODEN BATTEN 150 X 75 X 1950 LG | C33: NOS | D33: TIMBER | E33: 150 | F33: 75 | G33: 1950 | H33: =IF(D33="TIMBER",E33*F33*G33/1000000000*35.31,0) -> 0.77461313 | I33: Timber | J33: 604.28 | K33: 46253
A34: 1900222 | B34: PLY COVER 12 MM (MANHOLE/NOZZLE) | C34: NOS | D34: PKG-CONS | H34: =IF(D34="TIMBER",E34*F34*G34/1000000000*35.31,0) -> 0 | I34: Ply cover | J34: 160 | K34: 46253
A35: 1900223 | B35: HDPE TARPAULIN 200 GSM | C35: SQFT | D35: PKG-CONS | H35: =IF(D35="TIMBER",E35*F35*G35/1000000000*35.31,0) -> 0 | I35: Tarpaulin | J35: 5 | K35: 46253
A37: cft per piece = W x T x L (mm) / 10^9 x 35.31. Rate item typed so each item can be priced from Inputs.

Sheet Data - 2.0m BOM
A1: Packing BOM - 2.0 m vessel - the only written packing BOM
A2: BOM written for a 6-vessel shipment. No BOM exists for the other sizes.
A3: S/N | B3: Item | C3: MOC | D3: Qty / vessel | E3: UoM | F3: Qty for 6 vessels | G3: cft per piece | H3: cft per vessel
A4: 1 | B4: WOODEN BATTEN 150 X 75 X 2450 LG | C4: EXPORT PINE WOOD | D4: 3 | E4: nos. | F4: =D4*6 -> 18 | G4: =IFERROR(VLOOKUP(B4,'Data - Items'!$B$4:$H$35,7,0),0) -> 0.97323187 | H4: =D4*G4 -> 2.9196956
A5: 2 | B5: WOODEN BATTEN 100 X 100 X 1300 LG | C5: EXPORT PINE WOOD | D5: 4 | E5: nos. | F5: =D5*6 -> 24 | G5: =IFERROR(VLOOKUP(B5,'Data - Items'!$B$4:$H$35,7,0),0) -> 0.45903 | H5: =D5*G5 -> 1.83612
A6: 3 | B6: WOODEN BATTEN 150 X 75 X 1300 LG | C6: EXPORT PINE WOOD | D6: 2 | E6: nos. | F6: =D6*6 -> 12 | G6: =IFERROR(VLOOKUP(B6,'Data - Items'!$B$4:$H$35,7,0),0) -> 0.51640875 | H6: =D6*G6 -> 1.0328175
A7: 4 | B7: WOODEN BATTEN 150 X 150 X 300 LG | C7: EXPORT PINE WOOD | D7: 4 | E7: nos. | F7: =D7*6 -> 24 | G7: =IFERROR(VLOOKUP(B7,'Data - Items'!$B$4:$H$35,7,0),0) -> 0.2383425 | H7: =D7*G7 -> 0.95337
A8: 5 | B8: WOODEN BATTEN 100 X 75 X 100 LG | C8: EXPORT PINE WOOD | D8: 4 | E8: nos. | F8: =D8*6 -> 24 | G8: =IFERROR(VLOOKUP(B8,'Data - Items'!$B$4:$H$35,7,0),0) -> 0.0264825 | H8: =D8*G8 -> 0.10593
A9: 6 | B9: NAILS (AS REQUIRED) | C9: MS | D9: 1 | E9: sets | F9: =D9*6 -> 6 | G9: =IFERROR(VLOOKUP(B9,'Data - Items'!$B$4:$H$35,7,0),0) -> 0 | H9: =D9*G9 -> 0
A10: 7 | B10: KINI FOAM 12 MM THK X 1400 MM WD | C10: FOAM | D10: 0.5 | E10: rolls | F10: =D10*6 -> 3 | G10: =IFERROR(VLOOKUP(B10,'Data - Items'!$B$4:$H$35,7,0),0) -> 0 | H10: =D10*G10 -> 0
A11: 8 | B11: RATCHET LASHING BELT 8 M LG X 50 MM WD WITH LOCK | C11: PE/PP/NYLON | D11: 2 | E11: nos. | F11: =D11*6 -> 12 | G11: =IFERROR(VLOOKUP(B11,'Data - Items'!$B$4:$H$35,7,0),0) -> 0 | H11: =D11*G11 -> 0
A12: 9 | B12: GUM TAPE 3" | C12: - - - | D12: 0.833 | E12: nos. | F12: =D12*6 -> 4.998 | G12: =IFERROR(VLOOKUP(B12,'Data - Items'!$B$4:$H$35,7,0),0) -> 0 | H12: =D12*G12 -> 0
A13: 10 | B13: STRETCH FILM 50 MICRON | C13: LDPE | D13: 2.333 | E13: kg | F13: =D13*6 -> 13.998 | G13: =IFERROR(VLOOKUP(B13,'Data - Items'!$B$4:$H$35,7,0),0) -> 0 | H13: =D13*G13 -> 0
A14: 11 | B14: AIR BUBBLE WRAP | C14: LDPE | D14: 0.833 | E14: rolls | F14: =D14*6 -> 4.998 | G14: =IFERROR(VLOOKUP(B14,'Data - Items'!$B$4:$H$35,7,0),0) -> 0 | H14: =D14*G14 -> 0
